Workbook

Sheet TOTAL
M1: Horas Normais | N1: PROV.: 420 - DSR | O1: AD. Noturno | P1: Periculosidade | Q1: SOMAR COM A PERICULOSIDADE!!!! | R1: UNIFCADO Reembolso Desc. Indev. | S1: UNIFCADO Reembolso Desc. Indev. | T1: Aux. Educação | U1: PROV.: 159 - Dissidio Retroativo | W1: juntar com SALÁRIO BASE!!! | Y1: Gratificação | Z1: Sobre Aviso | AA1: Adicional de transferência | AB1: PROV.: 296 - Adic. de Transferência/Aux. Viagem | AC1: Comissão | AD1: HE 50% | AE1: HE 100% | AF1: Reflexo DSR HE | AG1: Reembolso Desc. Indev. | AH1: PROV:. 433 - DEV DESCONTO INDEVIDO | AI1: PROV.: 420 - DSR | AJ1: Salário Familia | AK1: PROV:. 433 - DEV DESCONTO INDEVIDO | AL1: Insuficiencia de saldo | AM1: Arredondamento | AO1: Falta + DSR | AP1: VA | AQ1: VT | AR1: Adiantamento | AS1: Insuficiencia de Saldo | AT1: Arredondamento | AU1: 2 via de VT | AV1: Plano Odontologico | AW1: Plano Odontologico | AY1: Contribuição sindical | AZ1: UNIFICADO COM 398 - FALTA + DSR | BA1: Multa de Transito | BB1: Plano de Saúde descontado na folha | BC1: Plano de Saúde descontado na folha | BD1: Plano de Saúde descontado na folha | BE1: EXTRA | BF1: Emprestimo (cred trab) | BG1: INSS | BH1: IRRF | BI1: Pensão Alimenticia | BJ1: Pensão Alimenticia 2 | BK1: DESC.: 609 - Insuficiência de Saldo | CH1: Plano de Saúde TOTAL (Titular+dependentes+cop.) | CM1: Odontológico TOTAL (titular+dependentes)
K2: Locação/Sal. Contratual | AA2: UNIFICADO COM AUXILIO VIAGEM | AB2: UNIFICADO COM AD TRANSFERENCIA | AG2: 433 e 456 UNIFICADOS!! | AH2: 433 e 456 UNIFICADOS!! | AI2: UNIFICADO COM DSR!!! | AS2: DUPLICADO | AV2: UNIFICADO AP+AQ | AW2: UNIFICADO AP+AQ | AZ2: UNIFICADO COM 398 - FALTA + DSR | BB2: UNIFICADO COM 699 - AU+AV+AW | BI2: UNFICADO EM 920 - BB+BC | BJ2: UNFICADO EM 920 - BB+BC | CD2: CUSTO EMPRESA - VALORES DEPOSITADOS
A3: NOME/SÓLIDES | B3: DATA DEMISSÃO | C3: CONFERIR | D3: R$ Total Custos | E3: Referência | F3: CNPJ | G3: Matrícula | H3: Colaborador | I3: Função | J3: Admissão | K3: Sal. Contratual | L3: Observações | M3: PROV.: 001 - Salário Base | N3: PROV.: 014 - Férias Períodos Quebrados ou Cheios | O3: PROV.: 017 - Noturno 20% | P3: PROV.: 020 - Periculosidade 30% | Q3: PROV.: 026 - Insalubridade 20% | R3: PROV.: 027 - Dif. Férias | S3: PROV.: 069 - Diferença de salario | T3: PROV.: 155 - Auxílio Creche/Educaçao | U3: PROV.: 159 - Dissidio Retroativo 1/3 | V3: PROV:. 183- Acumulo de Função | W3: PROV.: 200 - Salário Maternidade | X3: PROV:. 231 - Devolução Ass Odontológica | Y3: PROV.: 245 - Prêmio | Z3: PROV.: 259 - Adicional de Horas Sobre Aviso | AA3: PROV.: 296 - Adicional de Transferencia | AB3: PROV.: 313 - Auxilio viagem 25% | AC3: PROV.: 400 - Comissão | AD3: PROV.: 401 - Hora Extra 50% | AE3: PROV.: 402 - Hora Extra 100% | AF3: PROV.: 420 - Repouso Remunerado | AG3: PROV:. 433 - DEV DESCONTO INDEVIDO VT | AH3: PROV.: 456 - Estorno de Provisão (Crédito Trabalhado) | AI3: PROV.: 461 - DSR Sobre Comissões | AJ3: PROV.: 599 - Salário Família | AK3: PROV.: 647 - DEVOLUÇÃO PLANO | AL3: PROV.: 998 - Insuficiência de Saldo | AM3: PROV.: 999 - Arredondamento | AN3: R$ Proventos | AO3: DESC.: 398 - Faltas em Dias | AP3: DESC.: 600 - Alimentação | AQ3: DESC.: 604 - Vale Transporte | AR3: DESC.: 606 - Adiantamento viagem | AS3: DESC.: 609 - Insuficiência de Saldo | AT3: DESC.: 610 - Arredondamento | AU3: DESC.: 616 - Rio Card | AV3: DESC.: 623 - Assistência Odontológica - Part. | AW3: DESC.: 623 - Assistência Odontológica - Part. Dep. | AX3: DESC.: 636 - Aux. Viagem | AY3: DESC.: 645 - Contribuicao Assistencial | AZ3: DESC.: 674 - Desconto Repouso Remunerado | BA3: DESC.: 681 - Desconto multa de transito | BB3: DESC.: 698 - Outras Despesas Co-participação - Part. | BC3: DESC.: 699 - Plano De Saúde Part. | BD3: DESC.: 699 - Plano De Saúde - Part. Dep. | BE3: DESC.: 701 - 13° Pago Durante o Ano (Desconto) | BF3: DESC.: 711 - Empréstimo (Crédito Trabalhador) Parc. | BG3: DESC.: 903 - INSS Folha | BH3: DESC.: 914 - IRRF Folha | BI3: DESC.: 920 - Pensao Alimenticia | BJ3: DESC.: 997 - Pensão | BK3: DESC.: 998 - Insuficiência de Saldo | BL3: R$ Descontos | BM3: R$ Líquido | BN3: Parcela 13º salário | BO3: Parcela de Férias | BP3: 1/3 de Férias | BQ3: INSS Empresa | BR3: FGTS | BS3: Rest. Alimentação | BT3: Rest. Transporte | BU3: Rest. Plano de Saúde TOTAL | BV3: SEGURO DE VIDA | BW3: TREINAMENTOS | BX3: EXAMES | BY3: R$ Empresa | CA3: Nome | CB3: Rest. Plano de saúde | CC3: Rest. Plano Odonto | CD3: ALIMENTAÇÃO | CE3: TRANSPORTE | CF3: PLANO DE SAÚDE | CG3: PLANO ODONTO | CH3: DESC.: 699 - Plano De Saúde | CI3: DESC.: 920 - Pensao Alimenticia | CJ3: PROV.: 296 - Adic. de Transferência/Aux. Viagem | CK3: PROV.: 461 - DSR Sobre Comissões | CL3: PROV:. 433 - DEV DESCONTO INDEVIDO | CM3: DESC.: 623 - Assistência Odontológica | CN3: Total Proventos (R$) | CO3: Total Descontos (R$) | CP3: Valor Líquido (R$) | CQ3: Base INSS (R$) | CR3: Alíquota INSS () | CS3: Base FGTS (R$) | CT3: Valor FGTS (R$) | CU3: Base IRRF (R$)
A4: =IFERROR(__xludf.DUMMYFUNCTION("unique(flatten(LISTAFOLHAS!A3:A1001))"),"ADRIANO SOUZA SANTOS") -> ADRIANO SOUZA SANTOS | C4: =IF(COUNTIF(A:A, H4)>0, "OK", "Incompleto") -> OK | D4: =AN4+BY4 -> 5074.1297 | E4: 45809 | F4: 07.391.921/0001-71 | G4: 136 | H4: ADRIANO SOUZA SANTOS | I4: TECNICO DE TELECOMUNI | J4: 41992 | K4: 3159.37 | M4: 3159.37 | O4: 0 | P4: 0 | W4: 0 | AB4: 0 | AD4: 0 | AE4: 0 | AF4: 0 | AM4: 0.44 | AN4: =SUM(M4:AM4) -> 3159.81 | AQ4: -189.56 | AT4: -0.18 | AV4: -14 | AW4: -42 | BB4: 0 | BC4: -34.55 | BD4: 0 | BG4: -272.52 | BH4: 0 | BI4: 0 | BL4: =SUM(AO4:BK4) -> -552.81 | BM4: =AN4+BL4 -> 2607 | BN4: =K4/12*1 -> 263.28083 | BO4: =K4/12*1 -> 263.28083 | BP4: =BO4/3 -> 87.760278 | BQ4: =CQ4*CR4% -> 272.51778 | BR4: =CT4 -> 252.74 | BS4: =-(-CD4-AP4) -> 560 | BT4: =IF(CE4+AQ4<0, 0, CE4+AQ4) -> 49.84 | BU4: =CB4+CC4 -> 151.19 | BV4: =SUMIFS('SEGURO DE VIDA'!E:E, 'SEGURO DE VIDA'!D:D, H4, 'SEGURO DE VIDA'!G:G, E4) -> 13.71 | BW4: =SUMIFS(TREINAMENTOS!E:E, TREINAMENTOS!D:D, H4, TREINAMENTOS!G:G, E4) -> 0 | BX4: =SUMIFS(EXAMES!E:E, EXAMES!D:D, H4, EXAMES!G:G, E4) -> 0 | BY4: =SUM(BN4:BU4)+SUM(BV4:BX4) -> 1914.3197 | CA4: ADRIANO SOUZA SANTOS | CB4: =IF(SUM(BB4:BD4)+CF4<0, 0, SUM(BB4:BD4)+CF4) -> 151.19 | CC4: =IF(SUM(AV4:AW4)+CG4<0, 0, SUM(AV4:AW4)+CG4) -> 0 | CD4: =SUMIFS(ALIMENTAÇÃO!E:E, ALIMENTAÇÃO!D:D, H4, ALIMENTAÇÃO!G:G, E4) -> 560 | CE4: =SUMIFS(TRANSPORTE!E:E, TRANSPORTE!D:D, H4, TRANSPORTE!G:G, E4) -> 239.4 | CF4: =SUMIFS('PLANO DE SAÚDE'!E:E, 'PLANO DE SAÚDE'!D:D, H4, 'PLANO DE SAÚDE'!G:G, E4) -> 185.74 | CG4: =SUMIFS('PLANO ODONTO'!E:E, 'PLANO ODONTO'!D:D, H4, 'PLANO ODONTO'!G:G, E4) -> 56 | CH4: =BB4+BC4+BD4 -> -34.55 | CI4: =BI4+BJ4 -> 0 | CJ4: =AA4+AB4 -> 0 | CM4: =AV4+AW4 -> -56 | CN4: 3159.81 | CO4: -552.81 | CP4: 2607 | CQ4: 3159.37 | CR4: 8.6257 | CS4: 3159.37 | CT4: 252.74 | CU4: 2552.17
A5: =IFERROR(__xludf.DUMMYFUNCTION("""COMPUTED_VALUE"""),"ALESSANDRO SOARES RIBEIRO") -> ALESSANDRO SOARES RIBEIRO | C5: =IF(COUNTIF(A:A, H5)>0, "OK", "Incompleto") -> OK | D5: =AN5+BY5 -> 3618.1086 | E5: 45809 | F5: 07.391.921/0001-71 | G5: 3467 | H5: ALESSANDRO SOARES RIBEIRO | I5: MOTORISTA DE CARRO DE | J5: 45551 | K5: 1800 | M5: 1800 | O5: 0 | P5: 0 | W5: 0 | AB5: 0 | AD5: 279 | AE5: 0 | AF5: 69.75 | AM5: 0.88 | AN5: =SUM(M5:AM5) -> 2149.63 | AQ5: 0 | AT5: -0.78 | AV5: -14 | AW5: 0 | BB5: 0 | BC5: -2.24 | BD5: 0 | BG5: -170.61 | BH5: 0 | BI5: 0 | BL5: =SUM(AO5:BK5) -> -187.63 | BM5: =AN5+BL5 -> 1962 | BN5: =K5/12*1 -> 150 | BO5: =K5/12*1 -> 150 | BP5: =BO5/3 -> 50 | BQ5: =CQ5*CR5% -> 170.6086 | BR5: =CT5 -> 171.9 | BS5: =-(-CD5-AP5) -> 630 | BT5: =IF(CE5+AQ5<0, 0, CE5+AQ5) -> 0 | BU5: =CB5+CC5 -> 132.26 | BV5: =SUMIFS('SEGURO DE VIDA'!E:E, 'SEGURO DE VIDA'!D:D, H5, 'SEGURO DE VIDA'!G:G, E5) -> 13.71 | BW5: =SUMIFS(TREINAMENTOS!E:E, TREINAMENTOS!D:D, H5, TREINAMENTOS!G:G, E5) -> 0 | BX5: =SUMIFS(EXAMES!E:E, EXAMES!D:D, H5, EXAMES!G:G, E5) -> 0 | BY5: =SUM(BN5:BU5)+SUM(BV5:BX5) -> 1468.4786 | CA5: ALESSANDRO SOARES RIBEIRO | CB5: =IF(SUM(BB5:BD5)+CF5<0, 0, SUM(BB5:BD5)+CF5) -> 132.26 | CC5: =IF(SUM(AV5:AW5)+CG5<0, 0, SUM(AV5:AW5)+CG5) -> 0 | CD5: =SUMIFS(ALIMENTAÇÃO!E:E, ALIMENTAÇÃO!D:D, H5, ALIMENTAÇÃO!G:G, E5) -> 630 | CE5: =SUMIFS(TRANSPORTE!E:E, TRANSPORTE!D:D, H5, TRANSPORTE!G:G, E5) -> 0 | CF5: =SUMIFS('PLANO DE SAÚDE'!E:E, 'PLANO DE SAÚDE'!D:D, H5, 'PLANO DE SAÚDE'!G:G, E5) -> 134.5 | CG5: =SUMIFS('PLANO ODONTO'!E:E, 'PLANO ODONTO'!D:D, H5, 'PLANO ODONTO'!G:G, E5) -> 14 | CH5: =BB5+BC5+BD5 -> -2.24 | CI5: =BI5+BJ5 -> 0 | CJ5: =AA5+AB5 -> 0 | CM5: =AV5+AW5 -> -14 | CN5: 2149.63 | CO5: -187.63 | CP5: 1962 | CQ5: 2148.75 | CR5: 7.9399 | CS5: 2148.75 | CT5: 171.9 | CU5: 1541.55
A6: =IFERROR(__xludf.DUMMYFUNCTION("""COMPUTED_VALUE"""),"ALEXANDRE FERREIRA DE LIMA") -> ALEXANDRE FERREIRA DE LIMA | C6: =IF(COUNTIF(A:A, H6)>0, "OK", "Incompleto") -> OK | D6: =AN6+BY6 -> 3787.5095 | E6: 45809 | F6: 07.391.921/0001-71 | G6: 3465 | H6: ALEX ANTONIO VICTORINO | I6: INSTALADOR JUNIOR | J6: 45537 | K6: 1600 | M6: 1600 | O6: 0 | P6: 480 | W6: 0 | AB6: 0 | AD6: 123.24 | AE6: 0 | AF6: 30.81 | AM6: 0.74 | AN6: =SUM(M6:AM6) -> 2234.79 | AQ6: -96 | AT6: -0.95 | AV6: 0 | AW6: 0 | BB6: 0 | BC6: -34.55 | BD6: 0 | BG6: -178.29 | BH6: 0 | BI6: 0 | BL6: =SUM(AO6:BK6) -> -309.79 | BM6: =AN6+BL6 -> 1925 | BN6: =K6/12*1 -> 133.33333 | BO6: =K6/12*1 -> 133.33333 | BP6: =BO6/3 -> 44.444444 | BQ6: =CQ6*CR6% -> 178.28836 | BR6: =CT6 -> 178.72 | BS6: =-(-CD6-AP6) -> 525 | BT6: =IF(CE6+AQ6<0, 0, CE6+AQ6) -> 194.7 | BU6: =CB6+CC6 -> 151.19 | BV6: =SUMIFS('SEGURO DE VIDA'!E:E, 'SEGURO DE VIDA'!D:D, H6, 'SEGURO DE VIDA'!G:G, E6) -> 13.71 | BW6: =SUMIFS(TREINAMENTOS!E:E, TREINAMENTOS!D:D, H6, TREINAMENTOS!G:G, E6) -> 0 | BX6: =SUMIFS(EXAMES!E:E, EXAMES!D:D, H6, EXAMES!G:G, E6) -> 0 | BY6: =SUM(BN6:BU6)+SUM(BV6:BX6) -> 1552.7195 | CA6: ALEX ANTONIO VICTORINO | CB6: =IF(SUM(BB6:BD6)+CF6<0, 0, SUM(BB6:BD6)+CF6) -> 151.19 | CC6: =IF(SUM(AV6:AW6)+CG6<0, 0, SUM(AV6:AW6)+CG6) -> 0 | CD6: =SUMIFS(ALIMENTAÇÃO!E:E, ALIMENTAÇÃO!D:D, H6, ALIMENTAÇÃO!G:G, E6) -> 525 | CE6: =SUMIFS(TRANSPORTE!E:E, TRANSPORTE!D:D, H6, TRANSPORTE!G:G, E6) -> 290.7 | CF6: =SUMIFS('PLANO DE SAÚDE'!E:E, 'PLANO DE SAÚDE'!D:D, H6, 'PLANO DE SAÚDE'!G:G, E6) -> 185.74 | CG6: =SUMIFS('PLANO ODONTO'!E:E, 'PLANO ODONTO'!D:D, H6, 'PLANO ODONTO'!G:G, E6) -> 0 | CH6: =BB6+BC6+BD6 -> -34.55 | CI6: =BI6+BJ6 -> 0 | CJ6: =AA6+AB6 -> 0 | CM6: =AV6+AW6 -> 0 | CN6: 2234.79 | CO6: -309.79 | CP6: 1925 | CQ6: 2234.05 | CR6: 7.9805 | CS6: 2234.05 | CT6: 178.72 | CU6: 1626.85
A7: =IFERROR(__xludf.DUMMYFUNCTION("""COMPUTED_VALUE"""),"ALEXANDRE SOUZA DE ABREU") -> ALEXANDRE SOUZA DE ABREU | C7: =IF(COUNTIF(A:A, H7)>0, "OK", "Incompleto") -> OK | D7: =AN7+BY7 -> 4931.367 | E7: 45809 | F7: 07.391.921/0001-71 | G7: 3373 | H7: ALEX SENA DE SOUZA | I7: TECNICO EM FIBRA OPTICA | J7: 45065 | K7: 2776.98 | M7: 2776.98 | O7: 0 | P7: 0 | W7: 0 | AB7: 0 | AD7: 0 | AE7: 0 | AF7: 0 | AM7: 0.96 | AN7: =SUM(M7:AM7) -> 2777.94 | AQ7: -166.62 | AT7: -0.56 | AV7: -14 | AW7: 0 | BB7: 0 | BC7: -94.61 | BD7: 0 | BG7: -227.15 | BH7: 0 | BI7: 0 | BL7: =SUM(AO7:BK7) -> -502.94 | BM7: =AN7+BL7 -> 2275 | BN7: =K7/12*1 -> 231.415 | BO7: =K7/12*1 -> 231.415 | BP7: =BO7/3 -> 77.138333 | BQ7: =CQ7*CR7% -> 227.14863 | BR7: =CT7 -> 222.15 | BS7: =-(-CD7-AP7) -> 665 | BT7: =IF(CE7+AQ7<0, 0, CE7+AQ7) -> 158.28 | BU7: =CB7+CC7 -> 127.17 | BV7: =SUMIFS('SEGURO DE VIDA'!E:E, 'SEGURO DE VIDA'!D:D, H7, 'SEGURO DE VIDA'!G:G, E7) -> 13.71 | BW7: =SUMIFS(TREINAMENTOS!E:E, TREINAMENTOS!D:D, H7, TREINAMENTOS!G:G, E7) -> 200 | BX7: =SUMIFS(EXAMES!E:E, EXAMES!D:D, H7, EXAMES!G:G, E7) -> 0 | BY7: =SUM(BN7:BU7)+SUM(BV7:BX7) -> 2153.427 | CA7: ALEX SENA DE SOUZA | CB7: =IF(SUM(BB7:BD7)+CF7<0, 0, SUM(BB7:BD7)+CF7) -> 127.17 | CC7: =IF(SUM(AV7:AW7)+CG7<0, 0, SUM(AV7:AW7)+CG7) -> 0 | CD7: =SUMIFS(ALIMENTAÇÃO!E:E, ALIMENTAÇÃO!D:D, H7, ALIMENTAÇÃO!G:G, E7) -> 665 | CE7: =SUMIFS(TRANSPORTE!E:E, TRANSPORTE!D:D, H7, TRANSPORTE!G:G, E7) -> 324.9 | CF7: =SUMIFS('PLANO DE SAÚDE'!E:E, 'PLANO DE SAÚDE'!D:D, H7, 'PLANO DE SAÚDE'!G:G, E7) -> 221.78 | CG7: =SUMIFS('PLANO ODONTO'!E:E, 'PLANO ODONTO'!D:D, H7, 'PLANO ODONTO'!G:G, E7) -> 14 | CH7: =BB7+BC7+BD7 -> -94.61 | CI7: =BI7+BJ7 -> 0 | CJ7: =AA7+AB7 -> 0 | CM7: =AV7+AW7 -> -14 | CN7: 2777.94 | CO7: -502.94 | CP7: 2275 | CQ7: 2776.98 | CR7: 8.1797 | CS7: 2776.98 | CT7: 222.15 | CU7: 2169.78
A8: =IFERROR(__xludf.DUMMYFUNCTION("""COMPUTED_VALUE"""),"ALEX ANTONIO VICTORINO") -> ALEX ANTONIO VICTORINO | C8: =IF(COUNTIF(A:A, H8)>0, "OK", "Incompleto") -> OK | D8: =AN8+BY8 -> 4164.0681 | E8: 45809 | F8: 07.391.921/0001-71 | G8: 3515 | H8: ALEXANDRE FERREIRA DE LIMA | I8: ELETRICISTA | J8: 45726 | K8: 2000 | M8: 2000 | O8: 0 | P8: 600 | W8: 0 | AB8: 0 | AD8: 0 | AE8: 0 | AF8: 0 | AM8: 0.43 | AN8: =SUM(M8:AM8) -> 2600.43 | AQ8: 0 | AT8: -0.7 | AV8: -14 | AW8: -14 | BB8: 0 | BC8: -94.61 | BD8: -125.89 | BG8: -211.23 | BH8: 0 | BI8: 0 | BL8: =SUM(AO8:BK8) -> -460.43 | BM8: =AN8+BL8 -> 2140 | BN8: =K8/12*1 -> 166.66667 | BO8: =K8/12*1 -> 166.66667 | BP8: =BO8/3 -> 55.555556 | BQ8: =CQ8*CR8% -> 211.2292 | BR8: =CT8 -> 208 | BS8: =-(-CD8-AP8) -> 665 | BT8: =IF(CE8+AQ8<0, 0, CE8+AQ8) -> 0 | BU8: =CB8+CC8 -> 76.81 | BV8: =SUMIFS('SEGURO DE VIDA'!E:E, 'SEGURO DE VIDA'!D:D, H8, 'SEGURO DE VIDA'!G:G, E8) -> 13.71 | BW8: =SUMIFS(TREINAMENTOS!E:E, TREINAMENTOS!D:D, H8, TREINAMENTOS!G:G, E8) -> 0 | BX8: =SUMIFS(EXAMES!E:E, EXAMES!D:D, H8, EXAMES!G:G, E8) -> 0 | BY8: =SUM(BN8:BU8)+SUM(BV8:BX8) -> 1563.6381 | CA8: ALEXANDRE FERREIRA DE LIMA | CB8: =IF(SUM(BB8:BD8)+CF8<0, 0, SUM(BB8:BD8)+CF8) -> 76.81 | CC8: =IF(SUM(AV8:AW8)+CG8<0, 0, SUM(AV8:AW8)+CG8) -> 0 | CD8: =SUMIFS(ALIMENTAÇÃO!E:E, ALIMENTAÇÃO!D:D, H8, ALIMENTAÇÃO!G:G, E8) -> 665 | CE8: =SUMIFS(TRANSPORTE!E:E, TRANSPORTE!D:D, H8, TRANSPORTE!G:G, E8) -> 0 | CF8: =SUMIFS('PLANO DE SAÚDE'!E:E, 'PLANO DE SAÚDE'!D:D, H8, 'PLANO DE SAÚDE'!G:G, E8) -> 297.31 | CG8: =SUMIFS('PLANO ODONTO'!E:E, 'PLANO ODONTO'!D:D, H8, 'PLANO ODONTO'!G:G, E8) -> 28 | CH8: =BB8+BC8+BD8 -> -220.5 | CI8: =BI8+BJ8 -> 0 | CJ8: =AA8+AB8 -> 0 | CM8: =AV8+AW8 -> -28 | CN8: 2600.43 | CO8: -460.43 | CP8: 2140 | CQ8: 2600 | CR8: 8.1242 | CS8: 2600 | CT8: 208 | CU8: 1992.8
A9: =IFERROR(__xludf.DUMMYFUNCTION("""COMPUTED_VALUE"""),"ALEX SENA DE SOUZA") -> ALEX SENA DE SOUZA | C9: =IF(COUNTIF(A:A, H9)>0, "OK", "Incompleto") -> OK | D9: =AN9+BY9 -> 4308.0105 | E9: 45809 | F9: 07.391.921/0001-71 | G9: 187 | H9: ALEXANDRE SOUZA DE ABREU | I9: INST REDES TELEMATICAS | J9: 42248 | K9: 2495.63 | M9: 2495.63 | O9: 0 | P9: 0 | W9: 0 | AB9: 0 | AD9: 0 | AE9: 0 | AF9: 0 | AM9: 0.86 | AN9: =SUM(M9:AM9) -> 2496.49 | AQ9: -149.74 | AT9: -0.23 | AV9: -14 | AW9: 0 | BB9: -21.45 | BC9: -34.55 | BD9: -200.69 | BG9: -201.83 | BH9: 0 | BI9: 0 | BL9: =SUM(AO9:BK9) -> -622.49 | BM9: =AN9+BL9 -> 1874 | BN9: =K9/12*1 -> 207.96917 | BO9: =K9/12*1 -> 207.96917 | BP9: =BO9/3 -> 69.323056 | BQ9: =CQ9*CR9% -> 201.82908 | BR9: =CT9 -> 199.65 | BS9: =-(-CD9-AP9) -> 665 | BT9: =IF(CE9+AQ9<0, 0, CE9+AQ9) -> 175.16 | BU9: =CB9+CC9 -> 70.91 | BV9: =SUMIFS('SEGURO DE VIDA'!E:E, 'SEGURO DE VIDA'!D:D, H9, 'SEGURO DE VIDA'!G:G, E9) -> 13.71 | BW9: =SUMIFS(TREINAMENTOS!E:E, TREINAMENTOS!D:D, H9, TREINAMENTOS!G:G, E9) -> 0 | BX9: =SUMIFS(EXAMES!E:E, EXAMES!D:D, H9, EXAMES!G:G, E9) -> 0 | BY9: =SUM(BN9:BU9)+SUM(BV9:BX9) -> 1811.5205 | CA9: ALEXANDRE SOUZA DE ABREU | CB9: =IF(SUM(BB9:BD9)+CF9<0, 0, SUM(BB9:BD9)+CF9) -> 70.91 | CC9: =IF(SUM(AV9:AW9)+CG9<0, 0, SUM(AV9:AW9)+CG9) -> 0 | CD9: =SUMIFS(ALIMENTAÇÃO!E:E, ALIMENTAÇÃO!D:D, H9, ALIMENTAÇÃO!G:G, E9) -> 665 | CE9: =SUMIFS(TRANSPORTE!E:E, TRANSPORTE!D:D, H9, TRANSPORTE!G:G, E9) -> 324.9 | CF9: =SUMIFS('PLANO DE SAÚDE'!E:E, 'PLANO DE SAÚDE'!D:D, H9, 'PLANO DE SAÚDE'!G:G, E9) -> 327.6 | CG9: =SUMIFS('PLANO ODONTO'!E:E, 'PLANO ODONTO'!D:D, H9, 'PLANO ODONTO'!G:G, E9) -> 14 | CH9: =BB9+BC9+BD9 -> -256.69 | CI9: =BI9+BJ9 -> 0 | CJ9: =AA9+AB9 -> 0 | CM9: =AV9+AW9 -> -14 | CN9: 2496.49 | CO9: -622.49 | CP9: 1874 | CQ9: 2495.63 | CR9: 8.0873 | CS9: 2495.63 | CT9: 199.65 | CU9: 1888.43
A10: =IFERROR(__xludf.DUMMYFUNCTION("""COMPUTED_VALUE"""),"ALIENE FORAPANI LOPES") -> ALIENE FORAPANI LOPES | C10: =IF(COUNTIF(A:A, H10)>0, "OK", "Incompleto") -> OK | D10: =AN10+BY10 -> 3493.1145 | E10: 45809 | F10: 07.391.921/0001-71 | G10: 299 | H10: ALIENE FORAPANI LOPES | I10: TECNICO EM SEGURANCA | J10: 44333 | K10: 2566.52 | L10: Salário Maternidade | M10: 2566.52 | O10: 0 | P10: 0 | AB10: 0 | AD10: 0 | AE10: 0 | AF10: 0 | AM10: 0.31 | AN10: =SUM(M10:AM10) -> 2566.83 | AQ10: 0 | AT10: -0.62 | AV10: 0 | AW10: 0 | BB10: 0 | BC10: 0 | BD10: 0 | BG10: -208.21 | BH10: 0 | BI10: 0 | BL10: =SUM(AO10:BK10) -> -208.83 | BM10: =AN10+BL10 -> 2358 | BN10: =K10/12*1 -> 213.87667 | BO10: =K10/12*1 -> 213.87667 | BP10: =BO10/3 -> 71.292222 | BQ10: =CQ10*CR10% -> 208.20893 | BR10: =CT10 -> 205.32 | BS10: =-(-CD10-AP10) -> 0 | BT10: =IF(CE10+AQ10<0, 0, CE10+AQ10) -> 0 | BU10: =CB10+CC10 -> 0 | BV10: =SUMIFS('SEGURO DE VIDA'!E:E, 'SEGURO DE VIDA'!D:D, H10, 'SEGURO DE VIDA'!G:G, E10) -> 13.71 | BW10: =SUMIFS(TREINAMENTOS!E:E, TREINAMENTOS!D:D, H10, TREINAMENTOS!G:G, E10) -> 0 | BX10: =SUMIFS(EXAMES!E:E, EXAMES!D:D, H10, EXAMES!G:G, E10) -> 0 | BY10: =SUM(BN10:BU10)+SUM(BV10:BX10) -> 926.28449 | CA10: ALIENE FORAPANI LOPES | CB10: =IF(SUM(BB10:BD10)+CF10<0, 0, SUM(BB10:BD10)+CF10) -> 0 | CC10: =IF(SUM(AV10:AW10)+CG10<0, 0, SUM(AV10:AW10)+CG10) -> 0 | CD10: =SUMIFS(ALIMENTAÇÃO!E:E, ALIMENTAÇÃO!D:D, H10, ALIMENTAÇÃO!G:G, E10) -> 0 | CE10: =SUMIFS(TRANSPORTE!E:E, TRANSPORTE!D:D, H10, TRANSPORTE!G:G, E10) -> 0 | CF10: =SUMIFS('PLANO DE SAÚDE'!E:E, 'PLANO DE SAÚDE'!D:D, H10, 'PLANO DE SAÚDE'!G:G, E10) -> 0 | CG10: =SUMIFS('PLANO ODONTO'!E:E, 'PLANO ODONTO'!D:D, H10, 'PLANO ODONTO'!G:G, E10) -> 0 | CH10: =BB10+BC10+BD10 -> 0 | CI10: =BI10+BJ10 -> 0 | CJ10: =AA10+AB10 -> 0 | CM10: =AV10+AW10 -> 0 | CN10: 2566.83 | CO10: -208.83 | CP10: 2358 | CQ10: 2566.52 | CR10: 8.1125 | CS10: 2566.52 | CT10: 205.32 | CU10: 1959.32
A11: =IFERROR(__xludf.DUMMYFUNCTION("""COMPUTED_VALUE"""),"ALISSON SANTOS DO NASCIMENTO") -> ALISSON SANTOS DO NASCIMENTO | C11: =IF(COUNTIF(A:A, H11)>0, "OK", "Incompleto") -> OK | D11: =AN11+BY11 -> 5062.6014 | E11: 45809 | F11: 07.391.921/0001-71 | G11: 176 | H11: ALLAM LUCAS MESQUITA DA SILVA | I11: TECNICO DE TELECOMUNI | J11: 42041 | K11: 3159.37 | M11: 3159.37 | O11: 0.84 | P11: 0 | W11: 0 | AB11: 0 | AD11: 0 | AE11: 0 | AF11: 0.21 | AM11: 0.27 | AN11: =SUM(M11:AM11) -> 3160.69 | AQ11: 0 | AT11: -0.03 | AV11: -14 | AW11: 0 | BB11: 0 | BC11: -2.01 | BD11: 0 | BG11: -272.65 | BH11: 0 | BI11: 0 | BL11: =SUM(AO11:BK11) -> -288.69 | BM11: =AN11+BL11 -> 2872 | BN11: =K11/12*1 -> 263.28083 | BO11: =K11/12*1 -> 263.28083 | BP11: =BO11/3 -> 87.760278 | BQ11: =CQ11*CR11% -> 272.64943 | BR11: =CT11 -> 252.83 | BS11: =-(-CD11-AP11) -> 630 | BT11: =IF(CE11+AQ11<0, 0, CE11+AQ11) -> 0 | BU11: =CB11+CC11 -> 118.4 | BV11: =SUMIFS('SEGURO DE VIDA'!E:E, 'SEGURO DE VIDA'!D:D, H11, 'SEGURO DE VIDA'!G:G, E11) -> 13.71 | BW11: =SUMIFS(TREINAMENTOS!E:E, TREINAMENTOS!D:D, H11, TREINAMENTOS!G:G, E11) -> 0 | BX11: =SUMIFS(EXAMES!E:E, EXAMES!D:D, H11, EXAMES!G:G, E11) -> 0 | BY11: =SUM(BN11:BU11)+SUM(BV11:BX11) -> 1901.9114 | CA11: ALLAM LUCAS MESQUITA DA SILVA | CB11: =IF(SUM(BB11:BD11)+CF11<0, 0, SUM(BB11:BD11)+CF11) -> 118.4 | CC11: =IF(SUM(AV11:AW11)+CG11<0, 0, SUM(AV11:AW11)+CG11) -> 0 | CD11: =SUMIFS(ALIMENTAÇÃO!E:E, ALIMENTAÇÃO!D:D, H11, ALIMENTAÇÃO!G:G, E11) -> 630 | CE11: =SUMIFS(TRANSPORTE!E:E, TRANSPORTE!D:D, H11, TRANSPORTE!G:G, E11) -> 0 | CF11: =SUMIFS('PLANO DE SAÚDE'!E:E, 'PLANO DE SAÚDE'!D:D, H11, 'PLANO DE SAÚDE'!G:G, E11) -> 120.41 | CG11: =SUMIFS('PLANO ODONTO'!E:E, 'PLANO ODONTO'!D:D, H11, 'PLANO ODONTO'!G:G, E11) -> 14 | CH11: =BB11+BC11+BD11 -> -2.01 | CI11: =BI11+BJ11 -> 0 | CJ11: =AA11+AB11 -> 0 | CM11: =AV11+AW11 -> -14 | CN11: 3160.69 | CO11: -288.69 | CP11: 2872 | CQ11: 3160.42 | CR11: 8.627 | CS11: 3160.42 | CT11: 252.83 | CU11: 2553.22
A12: =IFERROR(__xludf.DUMMYFUNCTION("""COMPUTED_VALUE"""),"ALLAM LUCAS MESQUITA DA SILVA") -> ALLAM LUCAS MESQUITA DA SILVA | C12: =IF(COUNTIF(A:A, H12)>0, "OK", "Incompleto") -> OK | D12: =AN12+BY12 -> 3291.3457 | E12: 45809 | F12: 07.391.921/0001-71 | G12: 3468 | H12: ALLAN DELFIM DOS SANTOS | I12: AUX INST REDE TEL JR | J12: 45566 | K12: 1518 | M12: 1518 | O12: 0 | P12: 455.4 | W12: 0 | AB12: 0 | AD12: 0 | AE12: 0 | AF12: 0 | AM12: 0.5 | AN12: =SUM(M12:AM12) -> 1973.9 | AQ12: 0 | AT12: -0.36 | AV12: -14 | AW12: 0 | BB12: 0 | BC12: -1.71 | BD12: 0 | BG12: -154.83 | BH12: 0 | BI12: 0 | BL12: =SUM(AO12:BK12) -> -170.9 | BM12: =AN12+BL12 -> 1803 | BN12: =K12/12*1 -> 126.5 | BO12: =K12/12*1 -> 126.5 | BP12: =BO12/3 -> 42.166667 | BQ12: =CQ12*CR12% -> 154.82902 | BR12: =CT12 -> 157.87 | BS12: =-(-CD12-AP12) -> 595 | BT12: =IF(CE12+AQ12<0, 0, CE12+AQ12) -> 0 | BU12: =CB12+CC12 -> 100.87 | BV12: =SUMIFS('SEGURO DE VIDA'!E:E, 'SEGURO DE VIDA'!D:D, H12, 'SEGURO DE VIDA'!G:G, E12) -> 13.71 | BW12: =SUMIFS(TREINAMENTOS!E:E, TREINAMENTOS!D:D, H12, TREINAMENTOS!G:G, E12) -> 0 | BX12: =SUMIFS(EXAMES!E:E, EXAMES!D:D, H12, EXAMES!G:G, E12) -> 0 | BY12: =SUM(BN12:BU12)+SUM(BV12:BX12) -> 1317.4457 | CA12: ALLAN DELFIM DOS SANTOS | CB12: =IF(SUM(BB12:BD12)+CF12<0, 0, SUM(BB12:BD12)+CF12) -> 100.87 | CC12: =IF(SUM(AV12:AW12)+CG12<0, 0, SUM(AV12:AW12)+CG12) -> 0 | CD12: =SUMIFS(ALIMENTAÇÃO!E:E, ALIMENTAÇÃO!D:D, H12, ALIMENTAÇÃO!G:G, E12) -> 595 | CE12: =SUMIFS(TRANSPORTE!E:E, TRANSPORTE!D:D, H12, TRANSPORTE!G:G, E12) -> 0 | CF12: =SUMIFS('PLANO DE SAÚDE'!E:E, 'PLANO DE SAÚDE'!D:D, H12, 'PLANO DE SAÚDE'!G:G, E12) -> 102.58 | CG12: =SUMIFS('PLANO ODONTO'!E:E, 'PLANO ODONTO'!D:D, H12, 'PLANO ODONTO'!G:G, E12) -> 14 | CH12: =BB12+BC12+BD12 -> -1.71 | CI12: =BI12+BJ12 -> 0 | CJ12: =AA12+AB12 -> 0 | CM12: =AV12+AW12 -> -14 | CN12: 1973.9 | CO12: -170.9 | CP12: 1803 | CQ12: 1973.4 | CR12: 7.8458 | CS12: 1973.4 | CT12: 157.87 | CU12: 1366.2
A13: =IFERROR(__xludf.DUMMYFUNCTION("""COMPUTED_VALUE"""),"ALLAN DELFIM DOS SANTOS") -> ALLAN DELFIM DOS SANTOS | C13: =IF(COUNTIF(A:A, H13)>0, "OK", "Incompleto") -> OK | D13: =AN13+BY13 -> 1883.8433 | E13: 45809 | F13: 07.391.921/0001-71 | G13: 3540 | H13: ANA BEATRIZ SAMPAIO TORRES DOS SANTOS | I13: ESTAGIARIO EM TELECOM | J13: 45810 | K13: 750 | M13: 725 | O13: 0 | P13: 0 | W13: 0 | AB13: 0 | AD13: 0 | AE13: 0 | AF13: 0 | AM13: 0 | AN13: =SUM(M13:AM13) -> 725 | AQ13: 0 | AT13: 0 | AV13: 0 | AW13: 0 | BB13: 0 | BC13: 0 | BD13: 0 | BG13: 0 | BH13: 0 | BI13: 0 | BL13: =SUM(AO13:BK13) -> 0 | BM13: =AN13+BL13 -> 725 | BN13: =K13/12*1 -> 62.5 | BO13: =K13/12*1 -> 62.5 | BP13: =BO13/3 -> 20.833333 | BQ13: =CQ13*CR13% -> 0 | BR13: =CT13 -> 0 | BS13: =-(-CD13-AP13) -> 665 | BT13: =IF(CE13+AQ13<0, 0, CE13+AQ13) -> 334.3 | BU13: =CB13+CC13 -> 0 | BV13: =SUMIFS('SEGURO DE VIDA'!E:E, 'SEGURO DE VIDA'!D:D, H13, 'SEGURO DE VIDA'!G:G, E13) -> 13.71 | BW13: =SUMIFS(TREINAMENTOS!E:E, TREINAMENTOS!D:D, H13, TREINAMENTOS!G:G, E13) -> 0 | BX13: =SUMIFS(EXAMES!E:E, EXAMES!D:D, H13, EXAMES!G:G, E13) -> 0 | BY13: =SUM(BN13:BU13)+SUM(BV13:BX13) -> 1158.8433 | CA13: ΑNA BEATRIZ SAMPAIO TORRES DC | CB13: =IF(SUM(BB13:BD13)+CF13<0, 0, SUM(BB13:BD13)+CF13) -> 0 | CC13: =IF(SUM(AV13:AW13)+CG13<0, 0, SUM(AV13:AW13)+CG13) -> 0 | CD13: =SUMIFS(ALIMENTAÇÃO!E:E, ALIMENTAÇÃO!D:D, H13, ALIMENTAÇÃO!G:G, E13) -> 665 | CE13: =SUMIFS(TRANSPORTE!E:E, TRANSPORTE!D:D, H13, TRANSPORTE!G:G, E13) -> 334.3 | CF13: =SUMIFS('PLANO DE SAÚDE'!E:E, 'PLANO DE SAÚDE'!D:D, H13, 'PLANO DE SAÚDE'!G:G, E13) -> 0 | CG13: =SUMIFS('PLANO ODONTO'!E:E, 'PLANO ODONTO'!D:D, H13, 'PLANO ODONTO'!G:G, E13) -> 0 | CH13: =BB13+BC13+BD13 -> 0 | CI13: =BI13+BJ13 -> 0 | CJ13: =AA13+AB13 -> 0 | CM13: =AV13+AW13 -> 0 | CN13: 725 | CO13: 0 | CP13: 725 | CQ13: 0 | CR13: 0 | CS13: 0 | CT13: 0 | CU13: 117.8
A14: =IFERROR(__xludf.DUMMYFUNCTION("""COMPUTED_VALUE"""),"AMANDA CRISTINA DE SOUZA ESTEVES") -> AMANDA CRISTINA DE SOUZA ESTEVES | C14: =IF(COUNTIF(A:A, H14)>0, "OK", "Incompleto") -> OK | D14: =AN14+BY14 -> 1691.3433 | E14: 45809 | F14: 07.391.921/0001-71 | G14: 3544 | H14: ANA BEATRIZ SOARES FERREIRA DE OLIVEIRA | I14: ESTAGIARIO EM TELECOM | J14: 45824 | K14: 750 | M14: 375 | O14: 0 | P14: 0 | W14: 0 | AB14: 0 | AD14: 0 | AE14: 0 | AF14: 0 | AM14: 0 | AN14: =SUM(M14:AM14) -> 375 | AQ14: 0 | AT14: 0 | AV14: 0 | AW14: 0 | BB14: 0 | BC14: 0 | BD14: 0 | BG14: 0 | BH14: 0 | BI14: 0 | BL14: =SUM(AO14:BK14) -> 0 | BM14: =AN14+BL14 -> 375 | BN14: =K14/12*1 -> 62.5 | BO14: =K14/12*1 -> 62.5 | BP14: =BO14/3 -> 20.833333 | BQ14: =CQ14*CR14% -> 0 | BR14: =CT14 -> 0 | BS14: =-(-CD14-AP14) -> 315 | BT14: =IF(CE14+AQ14<0, 0, CE14+AQ14) -> 256.5 | BU14: =CB14+CC14 -> 0 | BV14: =SUMIFS('SEGURO DE VIDA'!E:E, 'SEGURO DE VIDA'!D:D, H14, 'SEGURO DE VIDA'!G:G, E14) -> 0 | BW14: =SUMIFS(TREINAMENTOS!E:E, TREINAMENTOS!D:D, H14, TREINAMENTOS!G:G, E14) -> 0 | BX14: =SUMIFS(EXAMES!E:E, EXAMES!D:D, H14, EXAMES!G:G, E14) -> 599.01 | BY14: =SUM(BN14:BU14)+SUM(BV14:BX14) -> 1316.3433 | CA14: ΑNA BEATRIZ SOARES FERREIRA D | CB14: =IF(SUM(BB14:BD14)+CF14<0, 0, SUM(BB14:BD14)+CF14) -> 0 | CC14: =IF(SUM(AV14:AW14)+CG14<0, 0, SUM(AV14:AW14)+CG14) -> 0 | CD14: =SUMIFS(ALIMENTAÇÃO!E:E, ALIMENTAÇÃO!D:D, H14, ALIMENTAÇÃO!G:G, E14) -> 315 | CE14: =SUMIFS(TRANSPORTE!E:E, TRANSPORTE!D:D, H14, TRANSPORTE!G:G, E14) -> 256.5 | CF14: =SUMIFS('PLANO DE SAÚDE'!E:E, 'PLANO DE SAÚDE'!D:D, H14, 'PLANO DE SAÚDE'!G:G, E14) -> 0 | CG14: =SUMIFS('PLANO ODONTO'!E:E, 'PLANO ODONTO'!D:D, H14, 'PLANO ODONTO'!G:G, E14) -> 0 | CH14: =BB14+BC14+BD14 -> 0 | CI14: =BI14+BJ14 -> 0 | CJ14: =AA14+AB14 -> 0 | CM14: =AV14+AW14 -> 0 | CN14: 375 | CO14: 0 | CP14: 375 | CQ14: 0 | CR14: 0 | CS14: 0 | CT14: 0 | CU14: 0
A15: =IFERROR(__xludf.DUMMYFUNCTION("""COMPUTED_VALUE"""),"AMANDA GOMES ALFENAS") -> AMANDA GOMES ALFENAS | C15: =IF(COUNTIF(A:A, H15)>0, "OK", "Incompleto") -> OK | D15: =AN15+BY15 -> 3756.5092 | E15: 45809 | F15: 07.391.921/0001-71 | G15: 3527 | H15: ANDERSON PACHECO LOULA SALES | I15: Operador de Audio e Video | J15: 45771 | K15: 2239.36 | M15: 2239.36 | O15: 0 | P15: 0 | W15: 0 | AB15: 0 | AD15: 0 | AE15: 0 | AF15: 0 | AM15: 0.86 | AN15: =SUM(M15:AM15) -> 2240.22 | AQ15: -134.36 | AT15: -0.09 | AV15: 0 | AW15: 0 | BB15: 0 | BC15: 0 | BD15: 0 | BG15: -178.77 | BH15: 0 | BI15: 0 | BL15: =SUM(AO15:BK15) -> -313.22 | BM15: =AN15+BL15 -> 1927 | BN15: =K15/12*1 -> 186.61333 | BO15: =K15/12*1 -> 186.61333 | BP15: =BO15/3 -> 62.204444 | BQ15: =CQ15*CR15% -> 178.76811 | BR15: =CT15 -> 179.14 | BS15: =-(-CD15-AP15) -> 665 | BT15: =IF(CE15+AQ15<0, 0, CE15+AQ15) -> 44.24 | BU15: =CB15+CC15 -> 0 | BV15: =SUMIFS('SEGURO DE VIDA'!E:E, 'SEGURO DE VIDA'!D:D, H15, 'SEGURO DE VIDA'!G:G, E15) -> 13.71 | BW15: =SUMIFS(TREINAMENTOS!E:E, TREINAMENTOS!D:D, H15, TREINAMENTOS!G:G, E15) -> 0 | BX15: =SUMIFS(EXAMES!E:E, EXAMES!D:D, H15, EXAMES!G:G, E15) -> 0 | BY15: =SUM(BN15:BU15)+SUM(BV15:BX15) -> 1516.2892 | CA15: ANDERSON PACHECO LOULA SALE | CB15: =IF(SUM(BB15:BD15)+CF15<0, 0, SUM(BB15:BD15)+CF15) -> 0 | CC15: =IF(SUM(AV15:AW15)+CG15<0, 0, SUM(AV15:AW15)+CG15) -> 0 | CD15: =SUMIFS(ALIMENTAÇÃO!E:E, ALIMENTAÇÃO!D:D, H15, ALIMENTAÇÃO!G:G, E15) -> 665 | CE15: =SUMIFS(TRANSPORTE!E:E, TRANSPORTE!D:D, H15, TRANSPORTE!G:G, E15) -> 178.6 | CF15: =SUMIFS('PLANO DE SAÚDE'!E:E, 'PLANO DE SAÚDE'!D:D, H15, 'PLANO DE SAÚDE'!G:G, E15) -> 0 | CG15: =SUMIFS('PLANO ODONTO'!E:E, 'PLANO ODONTO'!D:D, H15, 'PLANO ODONTO'!G:G, E15) -> 0 | CH15: =BB15+BC15+BD15 -> 0 | CI15: =BI15+BJ15 -> 0 | CJ15: =AA15+AB15 -> 0 | CM15: =AV15+AW15 -> 0 | CN15: 2240.22 | CO15: -313.22 | CP15: 1927 | CQ15: 2239.36 | CR15: 7.983 | CS15: 2239.36 | CT15: 179.14 | CU15: 1632.16
A16: =IFERROR(__xludf.DUMMYFUNCTION("""COMPUTED_VALUE"""),"ANA BEATRIZ SAMPAIO TORRES DOS SANTOS") -> ANA BEATRIZ SAMPAIO TORRES DOS SANTOS | C16: =IF(COUNTIF(A:A, H16)>0, "OK", "Incompleto") -> OK | D16: =AN16+BY16 -> 4179.7805 | E16: 45809 | F16: 07.391.921/0001-71 | G16: 212 | H16: ANDERSON SANTOS PROMMERCHENKEL | I16: INST REDES TELEMATICAS | J16: 42569 | K16: 2495.63 | M16: 2495.63 | O16: 0 | P16: 0 | W16: 0 | AB16: 0 | AD16: 0 | AE16: 0 | AF16: 0 | AM16: 0.3 | AN16: =SUM(M16:AM16) -> 2495.93 | AQ16: 0 | AT16: -0.09 | AV16: 0 | AW16: 0 | BB16: 0 | BC16: -2.01 | BD16: 0 | BG16: -201.83 | BH16: 0 | BI16: 0 | BL16: =SUM(AO16:BK16) -> -203.93 | BM16: =AN16+BL16 -> 2292 | BN16: =K16/12*1 -> 207.96917 | BO16: =K16/12*1 -> 207.96917 | BP16: =BO16/3 -> 69.323056 | BQ16: =CQ16*CR16% -> 201.82908 | BR16: =CT16 -> 199.65 | BS16: =-(-CD16-AP16) -> 665 | BT16: =IF(CE16+AQ16<0, 0, CE16+AQ16) -> 0 | BU16: =CB16+CC16 -> 118.4 | BV16: =SUMIFS('SEGURO DE VIDA'!E:E, 'SEGURO DE VIDA'!D:D, H16, 'SEGURO DE VIDA'!G:G, E16) -> 13.71 | BW16: =SUMIFS(TREINAMENTOS!E:E, TREINAMENTOS!D:D, H16, TREINAMENTOS!G:G, E16) -> 0 | BX16: =SUMIFS(EXAMES!E:E, EXAMES!D:D, H16, EXAMES!G:G, E16) -> 0 | BY16: =SUM(BN16:BU16)+SUM(BV16:BX16) -> 1683.8505 | CA16: ANDERSON SANTOS PROMMERCHE | CB16: =IF(SUM(BB16:BD16)+CF16<0, 0, SUM(BB16:BD16)+CF16) -> 118.4 | CC16: =IF(SUM(AV16:AW16)+CG16<0, 0, SUM(AV16:AW16)+CG16) -> 0 | CD16: =SUMIFS(ALIMENTAÇÃO!E:E, ALIMENTAÇÃO!D:D, H16, ALIMENTAÇÃO!G:G, E16) -> 665 | CE16: =SUMIFS(TRANSPORTE!E:E, TRANSPORTE!D:D, H16, TRANSPORTE!G:G, E16) -> 0 | CF16: =SUMIFS('PLANO DE SAÚDE'!E:E, 'PLANO DE SAÚDE'!D:D, H16, 'PLANO DE SAÚDE'!G:G, E16) -> 120.41 | CG16: =SUMIFS('PLANO ODONTO'!E:E, 'PLANO ODONTO'!D:D, H16, 'PLANO ODONTO'!G:G, E16) -> 0 | CH16: =BB16+BC16+BD16 -> -2.01 | CI16: =BI16+BJ16 -> 0 | CJ16: =AA16+AB16 -> 0 | CM16: =AV16+AW16 -> 0 | CN16: 2495.93 | CO16: -203.93 | CP16: 2292 | CQ16: 2495.63 | CR16: 8.0873 | CS16: 2495.63 | CT16: 199.65 | CU16: 1888.43
A17: =IFERROR(__xludf.DUMMYFUNCTION("""COMPUTED_VALUE"""),"ANA BEATRIZ SOARES FERREIRA DE OLIVEIRA") -> ANA BEATRIZ SOARES FERREIRA DE OLIVEIRA | C17: =IF(COUNTIF(A:A, H17)>0, "OK", "Incompleto") -> OK | D17: =AN17+BY17 -> 7623.2213 | E17: 45809 | F17: 07.391.921/0001-71 | G17: 331 | H17: ANDERSON VIEIRA BARBOZA | I17: ELETRICISTA | J17: 44531 | K17: 2489.57 | M17: 2489.57 | O17: 0 | P17: 746.87 | W17: 0 | AB17: 623.9 | AD17: 1100.39 | AE17: 0 | AF17: 275.1 | AM17: 0.18 | AN17: =SUM(M17:AM17) -> 5236.01 | AQ17: -149.37 | AT17: -1.22 | AV17: -14 | AW17: 0 | BB17: 0 | BC17: 0 | BD17: 0 | BG17: -455.25 | BH17: -217.11 | BI17: -1313.06 | BL17: =SUM(AO17:BK17) -> -2150.01 | BM17: =AN17+BL17 -> 3086 | BN17: =K17/12*1 -> 207.46417 | BO17: =K17/12*1 -> 207.46417 | BP17: =BO17/3 -> 69.154722 | BQ17: =CQ17*CR17% -> 455.24822 | BR17: =CT17 -> 368.95 | BS17: =-(-CD17-AP17) -> 540 | BT17: =IF(CE17+AQ17<0, 0, CE17+AQ17) -> 36.83 | BU17: =CB17+CC17 -> 488.39 | BV17: =SUMIFS('SEGURO DE VIDA'!E:E, 'SEGURO DE VIDA'!D:D, H17, 'SEGURO DE VIDA'!G:G, E17) -> 13.71 | BW17: =SUMIFS(TREINAMENTOS!E:E, TREINAMENTOS!D:D, H17, TREINAMENTOS!G:G, E17) -> 0 | BX17: =SUMIFS(EXAMES!E:E, EXAMES!D:D, H17, EXAMES!G:G, E17) -> 0 | BY17: =SUM(BN17:BU17)+SUM(BV17:BX17) -> 2387.2113 | CA17: ANDERSON VIEIRA BARBOZA | CB17: =IF(SUM(BB17:BD17)+CF17<0, 0, SUM(BB17:BD17)+CF17) -> 488.39 | CC17: =IF(SUM(AV17:AW17)+CG17<0, 0, SUM(AV17:AW17)+CG17) -> 0 | CD17: =SUMIFS(ALIMENTAÇÃO!E:E, ALIMENTAÇÃO!D:D, H17, ALIMENTAÇÃO!G:G, E17) -> 540 | CE17: =SUMIFS(TRANSPORTE!E:E, TRANSPORTE!D:D, H17, TRANSPORTE!G:G, E17) -> 186.2 | CF17: =SUMIFS('PLANO DE SAÚDE'!E:E, 'PLANO DE SAÚDE'!D:D, H17, 'PLANO DE SAÚDE'!G:G, E17) -> 488.39 | CG17: =SUMIFS('PLANO ODONTO'!E:E, 'PLANO ODONTO'!D:D, H17, 'PLANO ODONTO'!G:G, E17) -> 14 | CH17: =BB17+BC17+BD17 -> 0 | CI17: =BI17+BJ17 -> -1313.06 | CJ17: =AA17+AB17 -> 623.9 | CM17: =AV17+AW17 -> -14 | CN17: 5236.01 | CO17: -2150.01 | CP17: 3086 | CQ17: 4611.93 | CR17: 9.8711 | CS17: 4611.93 | CT17: 368.95 | CU17: 3967.09
A18: =IFERROR(__xludf.DUMMYFUNCTION("""COMPUTED_VALUE"""),"ANA CAROLINA MARQUES SERAFIM") -> ANA CAROLINA MARQUES SERAFIM | C18: =IF(COUNTIF(A:A, H18)>0, "OK", "Incompleto") -> OK | D18: =AN18+BY18 -> 4523.7805 | E18: 45809 | F18: 07.391.921/0001-71 | G18: 220 | H18: ANDRE LUIZ PEREIRA COSTA | I18: INST REDES TELEMATICAS | J18: 43060 | K18: 2495.63 | M18: 2495.63 | O18: 0 | P18: 0 | W18: 0 | AB18: 0 | AD18: 0 | AE18: 0 | AF18: 0 | AM18: 0.23 | AN18: =SUM(M18:AM18) -> 2495.86 | AQ18: -149.74 | AT18: -0.74 | AV18: -14 | AW18: -14 | BB18: 0 | BC18: -34.55 | BD18: 0 | BG18: -201.83 | BH18: 0 | BI18: 0 | BL18: =SUM(AO18:BK18) -> -414.86 | BM18: =AN18+BL18 -> 2081 | BN18: =K18/12*1 -> 207.96917 | BO18: =K18/12*1 -> 207.96917 | BP18: =BO18/3 -> 69.323056 | BQ18: =CQ18*CR18% -> 201.82908 | BR18: =CT18 -> 199.65 | BS18: =-(-CD18-AP18) -> 630 | BT18: =IF(CE18+AQ18<0, 0, CE18+AQ18) -> 163.76 | BU18: =CB18+CC18 -> 231.59 | BV18: =SUMIFS('SEGURO DE VIDA'!E:E, 'SEGURO DE VIDA'!D:D, H18, 'SEGURO DE VIDA'!G:G, E18) -> 13.71 | BW18: =SUMIFS(TREINAMENTOS!E:E, TREINAMENTOS!D:D, H18, TREINAMENTOS!G:G, E18) -> 0 | BX18: =SUMIFS(EXAMES!E:E, EXAMES!D:D, H18, EXAMES!G:G, E18) -> 102.12 | BY18: =SUM(BN18:BU18)+SUM(BV18:BX18) -> 2027.9205 | CA18: ANDRE LUIZ PEREIRA COSTA | CB18: =IF(SUM(BB18:BD18)+CF18<0, 0, SUM(BB18:BD18)+CF18) -> 206.41 | CC18: =IF(SUM(AV18:AW18)+CG18<0, 0, SUM(AV18:AW18)+CG18) -> 25.18 | CD18: =SUMIFS(ALIMENTAÇÃO!E:E, ALIMENTAÇÃO!D:D, H18, ALIMENTAÇÃO!G:G, E18) -> 630 | CE18: =SUMIFS(TRANSPORTE!E:E, TRANSPORTE!D:D, H18, TRANSPORTE!G:G, E18) -> 313.5 | CF18: =SUMIFS('PLANO DE SAÚDE'!E:E, 'PLANO DE SAÚDE'!D:D, H18, 'PLANO DE SAÚDE'!G:G, E18) -> 240.96 | CG18: =SUMIFS('PLANO ODONTO'!E:E, 'PLANO ODONTO'!D:D, H18, 'PLANO ODONTO'!G:G, E18) -> 53.18 | CH18: =BB18+BC18+BD18 -> -34.55 | CI18: =BI18+BJ18 -> 0 | CJ18: =AA18+AB18 -> 0 | CM18: =AV18+AW18 -> -28 | CN18: 2495.86 | CO18: -414.86 | CP18: 2081 | CQ18: 2495.63 | CR18: 8.0873 | CS18: 2495.63 | CT18: 199.65 | CU18: 1888.43
A19: =IFERROR(__xludf.DUMMYFUNCTION("""COMPUTED_VALUE"""),"ANDERSON BARBOSA PEREIRA") -> ANDERSON BARBOSA PEREIRA | C19: =IF(COUNTIF(A:A, H19)>0, "OK", "Incompleto") -> OK | D19: =AN19+BY19 -> 4063.6334 | E19: 45809 | F19: 07.391.921/0001-71 | G19: 3504 | H19: ANGÉLICA DE FRANÇA RAMOS | I19: ASSIST PROJETOS | J19: 45677 | K19: 2390.42 | M19: 2390.42 | O19: 0 | P19: 0 | W19: 0 | AB19: 0 | AD19: 0 | AE19: 0 | AF19: 0 | AM19: 0.89 | AN19: =SUM(M19:AM19) -> 2391.31 | AQ19: 0 | AT19: -0.87 | AV19: 0 | AW19: 0 | BB19: 0 | BC19: -100.08 | BD19: 0 | BG19: -192.36 | BH19: 0 | BI19: 0 | BL19: =SUM(AO19:BK19) -> -293.31 | BM19: =AN19+BL19 -> 2098 | BN19: =K19/12*1 -> 199.20167 | BO19: =K19/12*1 -> 199.20167 | BP19: =BO19/3 -> 66.400556 | BQ19: =CQ19*CR19% -> 192.35949 | BR19: =CT19 -> 191.23 | BS19: =-(-CD19-AP19) -> 510 | BT19: =IF(CE19+AQ19<0, 0, CE19+AQ19) -> 0 | BU19: =CB19+CC19 -> 300.22 | BV19: =SUMIFS('SEGURO DE VIDA'!E:E, 'SEGURO DE VIDA'!D:D, H19, 'SEGURO DE VIDA'!G:G, E19) -> 13.71 | BW19: =SUMIFS(TREINAMENTOS!E:E, TREINAMENTOS!D:D, H19, TREINAMENTOS!G:G, E19) -> 0 | BX19: =SUMIFS(EXAMES!E:E, EXAMES!D:D, H19, EXAMES!G:G, E19) -> 0 | BY19: =SUM(BN19:BU19)+SUM(BV19:BX19) -> 1672.3234 | CA19: ANGELICA DE FRANCA RAMOS | CB19: =IF(SUM(BB19:BD19)+CF19<0, 0, SUM(BB19:BD19)+CF19) -> 300.22 | CC19: =IF(SUM(AV19:AW19)+CG19<0, 0, SUM(AV19:AW19)+CG19) -> 0 | CD19: =SUMIFS(ALIMENTAÇÃO!E:E, ALIMENTAÇÃO!D:D, H19, ALIMENTAÇÃO!G:G, E19) -> 510 | CE19: =SUMIFS(TRANSPORTE!E:E, TRANSPORTE!D:D, H19, TRANSPORTE!G:G, E19) -> 0 | CF19: =SUMIFS('PLANO DE SAÚDE'!E:E, 'PLANO DE SAÚDE'!D:D, H19, 'PLANO DE SAÚDE'!G:G, E19) -> 400.3 | CG19: =SUMIFS('PLANO ODONTO'!E:E, 'PLANO ODONTO'!D:D, H19, 'PLANO ODONTO'!G:G, E19) -> 0 | CH19: =BB19+BC19+BD19 -> -100.08 | CI19: =BI19+BJ19 -> 0 | CJ19: =AA19+AB19 -> 0 | CM19: =AV19+AW19 -> 0 | CN19: 2391.31 | CO19: -293.31 | CP19: 2098 | CQ19: 2390.42 | CR19: 8.0471 | CS19: 2390.42 | CT19: 191.23 | CU19: 1783.22
A20: =IFERROR(__xludf.DUMMYFUNCTION("""COMPUTED_VALUE"""),"ANDERSON FERREIRA SANTANA") -> ANDERSON FERREIRA SANTANA | C20: =IF(COUNTIF(A:A, H20)>0, "OK", "Incompleto") -> OK | D20: =AN20+BY20 -> 3665.8117 | E20: 45809 | F20: 20.258.413/0001-88 | G20: 13 | H20: ANTONIO DIOGO DA SILVA TEIXEIRA | I20: TECNICO DE MANUTENCAC | J20: 43592 | K20: 2562.79 | L20: Férias | M20: 1964.81 | AC20: 0 | AD20: 0 | AE20: 0 | AF20: 0 | AM20: 0.83 | AN20: =SUM(M20:AM20) -> 1965.64 | AP20: -6.65 | AQ20: -117.89 | AR20: 0 | AT20: -0.72 | AV20: -14 | BB20: -52.64 | BC20: -2.24 | BD20: -452.47 | BG20: -166.03 | BH20: 0 | BL20: =SUM(AO20:BK20) -> -812.64 | BM20: =AN20+BL20 -> 1153 | BN20: =K20/12*1 -> 213.56583 | BO20: =K20/12*1 -> 213.56583 | BP20: =BO20/3 -> 71.188611 | BQ20: =CQ20*CR20% -> 160.72146 | BR20: =CT20 -> 157.18 | BS20: =-(-CD20-AP20) -> 658.35 | BT20: =IF(CE20+AQ20<0, 0, CE20+AQ20) -> 207.01 | BU20: =CB20+CC20 -> 0 | BV20: =SUMIFS('SEGURO DE VIDA'!E:E, 'SEGURO DE VIDA'!D:D, H20, 'SEGURO DE VIDA'!G:G, E20) -> 18.59 | BW20: =SUMIFS(TREINAMENTOS!E:E, TREINAMENTOS!D:D, H20, TREINAMENTOS!G:G, E20) -> 0 | BX20: =SUMIFS(EXAMES!E:E, EXAMES!D:D, H20, EXAMES!G:G, E20) -> 0 | BY20: =SUM(BN20:BU20)+SUM(BV20:BX20) -> 1700.1717 | CA20: ANTONIO DIOGO DA SILVA TEIXEIRA | CB20: =IF(SUM(BB20:BD20)+CF20<0, 0, SUM(BB20:BD20)+CF20) -> 0 | CC20: =IF(SUM(AV20:AW20)+CG20<0, 0, SUM(AV20:AW20)+CG20) -> 0 | CD20: =SUMIFS(ALIMENTAÇÃO!E:E, ALIMENTAÇÃO!D:D, H20, ALIMENTAÇÃO!G:G, E20) -> 665 | CE20: =SUMIFS(TRANSPORTE!E:E, TRANSPORTE!D:D, H20, TRANSPORTE!G:G, E20) -> 324.9 | CF20: =SUMIFS('PLANO DE SAÚDE'!E:E, 'PLANO DE SAÚDE'!D:D, H20, 'PLANO DE SAÚDE'!G:G, E20) -> 458.61 | CG20: =SUMIFS('PLANO ODONTO'!E:E, 'PLANO ODONTO'!D:D, H20, 'PLANO ODONTO'!G:G, E20) -> 14 | CH20: =BB20+BC20+BD20 -> -507.35 | CI20: =BI20+BJ20 -> 0 | CJ20: =AA20+AB20 -> 0 | CM20: =AV20+AW20 -> -14 | CN20: 1965.64 | CO20: -812.64 | CP20: 1153 | CQ20: 1964.81 | CR20: 8.18 | CS20: 1964.81 | CT20: 157.18 | CU20: 1357.61
A21: =IFERROR(__xludf.DUMMYFUNCTION("""COMPUTED_VALUE"""),"ANDERSON PACHECO LOULA SALES") -> ANDERSON PACHECO LOULA SALES | C21: =IF(COUNTIF(A:A, H21)>0, "OK", "Incompleto") -> OK | D21: =AN21+BY21 -> 4134.5646 | E21: 45809 | F21: 07.391.921/0001-71 | G21: 3526 | H21: ARTHUR CASSILHAS DA MATA | I21: INSTALADOR JUNIOR | J21: 45761 | K21: 1700 | L21: Atestado | M21: 1700 | O21: 0 | P21: 510 | W21: 0 | AB21: 0 | AD21: 259.68 | AE21: 182.33 | AF21: 110.5 | AM21: 0.94 | AN21: =SUM(M21:AM21) -> 2763.45 | AQ21: 0 | AT21: -0.6 | AV21: 0 | AW21: 0 | BB21: 0 | BC21: 0 | BD21: 0 | BG21: -225.85 | BH21: 0 | BI21: 0 | BL21: =SUM(AO21:BK21) -> -226.45 | BM21: =AN21+BL21 -> 2537 | BN21: =K21/12*1 -> 141.66667 | BO21: =K21/12*1 -> 141.66667 | BP21: =BO21/3 -> 47.222222 | BQ21: =CQ21*CR21% -> 225.84901 | BR21: =CT21 -> 221 | BS21: =-(-CD21-AP21) -> 570 | BT21: =IF(CE21+AQ21<0, 0, CE21+AQ21) -> 0 | BU21: =CB21+CC21 -> 0 | BV21: =SUMIFS('SEGURO DE VIDA'!E:E, 'SEGURO DE VIDA'!D:D, H21, 'SEGURO DE VIDA'!G:G, E21) -> 13.71 | BW21: =SUMIFS(TREINAMENTOS!E:E, TREINAMENTOS!D:D, H21, TREINAMENTOS!G:G, E21) -> 0 | BX21: =SUMIFS(EXAMES!E:E, EXAMES!D:D, H21, EXAMES!G:G, E21) -> 10 | BY21: =SUM(BN21:BU21)+SUM(BV21:BX21) -> 1371.1146 | CA21: ARTHUR CASSILHAS DA ΜΑΤΑ | CB21: =IF(SUM(BB21:BD21)+CF21<0, 0, SUM(BB21:BD21)+CF21) -> 0 | CC21: =IF(SUM(AV21:AW21)+CG21<0, 0, SUM(AV21:AW21)+CG21) -> 0 | CD21: =SUMIFS(ALIMENTAÇÃO!E:E, ALIMENTAÇÃO!D:D, H21, ALIMENTAÇÃO!G:G, E21) -> 570 | CE21: =SUMIFS(TRANSPORTE!E:E, TRANSPORTE!D:D, H21, TRANSPORTE!G:G, E21) -> 0 | CF21: =SUMIFS('PLANO DE SAÚDE'!E:E, 'PLANO DE SAÚDE'!D:D, H21, 'PLANO DE SAÚDE'!G:G, E21) -> 0 | CG21: =SUMIFS('PLANO ODONTO'!E:E, 'PLANO ODONTO'!D:D, H21, 'PLANO ODONTO'!G:G, E21) -> 0 | CH21: =BB21+BC21+BD21 -> 0 | CI21: =BI21+BJ21 -> 0 | CJ21: =AA21+AB21 -> 0 | CM21: =AV21+AW21 -> 0 | CN21: 2763.45 | CO21: -226.45 | CP21: 2537 | CQ21: 2762.51 | CR21: 8.1755 | CS21: 2762.51 | CT21: 221 | CU21: 2155.31
A22: =IFERROR(__xludf.DUMMYFUNCTION("""COMPUTED_VALUE"""),"ANDERSON SANTOS PROMMERCHENKEL") -> ANDERSON SANTOS PROMMERCHENKEL | C22: =IF(COUNTIF(A:A, H22)>0, "OK", "Incompleto") -> OK | D22: =AN22+BY22 -> 1737.5433 | E22: 45809 | F22: 07.391.921/0001-71 | G22: 3541 | H22: ARTHUR RODRIGUES RANGEL | I22: ESTAGIARIO EM TELECOM | J22: 45810 | K22: 750 | M22: 725 | O22: 0 | P22: 0 | W22: 0 | AB22: 0 | AD22: 0 | AE22: 0 | AF22: 0 | AM22: 0 | AN22: =SUM(M22:AM22) -> 725 | AQ22: 0 | AT22: 0 | AV22: 0 | AW22: 0 | BB22: 0 | BC22: 0 | BD22: 0 | BG22: 0 | BH22: 0 | BI22: 0 | BL22: =SUM(AO22:BK22) -> 0 | BM22: =AN22+BL22 -> 725 | BN22: =K22/12*1 -> 62.5 | BO22: =K22/12*1 -> 62.5 | BP22: =BO22/3 -> 20.833333 | BQ22: =CQ22*CR22% -> 0 | BR22: =CT22 -> 0 | BS22: =-(-CD22-AP22) -> 665 | BT22: =IF(CE22+AQ22<0, 0, CE22+AQ22) -> 188 | BU22: =CB22+CC22 -> 0 | BV22: =SUMIFS('SEGURO DE VIDA'!E:E, 'SEGURO DE VIDA'!D:D, H22, 'SEGURO DE VIDA'!G:G, E22) -> 13.71 | BW22: =SUMIFS(TREINAMENTOS!E:E, TREINAMENTOS!D:D, H22, TREINAMENTOS!G:G, E22) -> 0 | BX22: =SUMIFS(EXAMES!E:E, EXAMES!D:D, H22, EXAMES!G:G, E22) -> 0 | BY22: =SUM(BN22:BU22)+SUM(BV22:BX22) -> 1012.5433 | CA22: ARTHUR RODRIGUES RANGEL | CB22: =IF(SUM(BB22:BD22)+CF22<0, 0, SUM(BB22:BD22)+CF22) -> 0 | CC22: =IF(SUM(AV22:AW22)+CG22<0, 0, SUM(AV22:AW22)+CG22) -> 0 | CD22: =SUMIFS(ALIMENTAÇÃO!E:E, ALIMENTAÇÃO!D:D, H22, ALIMENTAÇÃO!G:G, E22) -> 665 | CE22: =SUMIFS(TRANSPORTE!E:E, TRANSPORTE!D:D, H22, TRANSPORTE!G:G, E22) -> 188 | CF22: =SUMIFS('PLANO DE SAÚDE'!E:E, 'PLANO DE SAÚDE'!D:D, H22, 'PLANO DE SAÚDE'!G:G, E22) -> 0 | CG22: =SUMIFS('PLANO ODONTO'!E:E, 'PLANO ODONTO'!D:D, H22, 'PLANO ODONTO'!G:G, E22) -> 0 | CH22: =BB22+BC22+BD22 -> 0 | CI22: =BI22+BJ22 -> 0 | CJ22: =AA22+AB22 -> 0 | CM22: =AV22+AW22 -> 0 | CN22: 725 | CO22: 0 | CP22: 725 | CQ22: 0 | CR22: 0 | CS22: 0 | CT22: 0 | CU22: 117.8
A23: =IFERROR(__xludf.DUMMYFUNCTION("""COMPUTED_VALUE"""),"ANDERSON VIEIRA BARBOZA") -> ANDERSON VIEIRA BARBOZA | C23: =IF(COUNTIF(A:A, H23)>0, "OK", "Incompleto") -> OK | D23: =AN23+BY23 -> 4870.5208 | E23: 45809 | F23: 07.391.921/0001-71 | G23: 347 | H23: ARTHUR SOUZA LEMOS PINHEIRO | I23: ANALISTA DE TELECOMUN | J23: 44713 | K23: 3034.3 | M23: 3034.3 | O23: 0 | P23: 0 | W23: 0 | AB23: 0 | AD23: 0 | AE23: 0 | AF23: 0 | AM23: 0.13 | AN23: =SUM(M23:AM23) -> 3034.43 | AQ23: 0 | AT23: -0.91 | AV23: 0 | AW23: 0 | BB23: 0 | BC23: 0 | BD23: 0 | BG23: -257.52 | BH23: 0 | BI23: 0 | BL23: =SUM(AO23:BK23) -> -258.43 | BM23: =AN23+BL23 -> 2776 | BN23: =K23/12*1 -> 252.85833 | BO23: =K23/12*1 -> 252.85833 | BP23: =BO23/3 -> 84.286111 | BQ23: =CQ23*CR23% -> 257.51801 | BR23: =CT23 -> 242.74 | BS23: =-(-CD23-AP23) -> 630 | BT23: =IF(CE23+AQ23<0, 0, CE23+AQ23) -> 0 | BU23: =CB23+CC23 -> 0 | BV23: =SUMIFS('SEGURO DE VIDA'!E:E, 'SEGURO DE VIDA'!D:D, H23, 'SEGURO DE VIDA'!G:G, E23) -> 13.71 | BW23: =SUMIFS(TREINAMENTOS!E:E, TREINAMENTOS!D:D, H23, TREINAMENTOS!G:G, E23) -> 0 | BX23: =SUMIFS(EXAMES!E:E, EXAMES!D:D, H23, EXAMES!G:G, E23) -> 102.12 | BY23: =SUM(BN23:BU23)+SUM(BV23:BX23) -> 1836.0908 | CA23: ARTHUR SOUZA LEMOS PINHEIRO | CB23: =IF(SUM(BB23:BD23)+CF23<0, 0, SUM(BB23:BD23)+CF23) -> 0 | CC23: =IF(SUM(AV23:AW23)+CG23<0, 0, SUM(AV23:AW23)+CG23) -> 0 | CD23: =SUMIFS(ALIMENTAÇÃO!E:E, ALIMENTAÇÃO!D:D, H23, ALIMENTAÇÃO!G:G, E23) -> 630 | CE23: =SUMIFS(TRANSPORTE!E:E, TRANSPORTE!D:D, H23, TRANSPORTE!G:G, E23) -> 0 | CF23: =SUMIFS('PLANO DE SAÚDE'!E:E, 'PLANO DE SAÚDE'!D:D, H23, 'PLANO DE SAÚDE'!G:G, E23) -> 0 | CG23: =SUMIFS('PLANO ODONTO'!E:E, 'PLANO ODONTO'!D:D, H23, 'PLANO ODONTO'!G:G, E23) -> 0 | CH23: =BB23+BC23+BD23 -> 0 | CI23: =BI23+BJ23 -> 0 | CJ23: =AA23+AB23 -> 0 | CM23: =AV23+AW23 -> 0 | CN23: 3034.43 | CO23: -258.43 | CP23: 2776 | CQ23: 3034.3 | CR23: 8.4869 | CS23: 3034.3 | CT23: 242.74 | CU23: 2427.1
A24: =IFERROR(__xludf.DUMMYFUNCTION("""COMPUTED_VALUE"""),"ANDRE LUIZ PEREIRA COSTA") -> ANDRE LUIZ PEREIRA COSTA | C24: =IF(COUNTIF(A:A, H24)>0, "OK", "Incompleto") -> OK | D24: =AN24+BY24 -> 3460.9 | E24: 45809 | F24: 07.391.921/0001-71 | G24: 3514 | H24: ARTUR OLIVEIRA CABRAL | I24: INSTALADOR | J24: 45726 | K24: 1800 | M24: 1800 | O24: 0 | P24: 0 | W24: 0 | AB24: 0 | AD24: 0 | AE24: 0 | AF24: 0 | AM24: 0.66 | AN24: =SUM(M24:AM24) -> 1800.66 | AQ24: -108 | AT24: -0.97 | AV24: -14 | AW24: 0 | BB24: -21.45 | BC24: -2.01 | BD24: 0 | BG24: -139.23 | BH24: 0 | BI24: 0 | BL24: =SUM(AO24:BK24) -> -285.66 | BM24: =AN24+BL24 -> 1515 | BN24: =K24/12*1 -> 150 | BO24: =K24/12*1 -> 150 | BP24: =BO24/3 -> 50 | BQ24: =CQ24*CR24% -> 139.23 | BR24: =CT24 -> 144 | BS24: =-(-CD24-AP24) -> 630 | BT24: =IF(CE24+AQ24<0, 0, CE24+AQ24) -> 4.8 | BU24: =CB24+CC24 -> 118.4 | BV24: =SUMIFS('SEGURO DE VIDA'!E:E, 'SEGURO DE VIDA'!D:D, H24, 'SEGURO DE VIDA'!G:G, E24) -> 13.71 | BW24: =SUMIFS(TREINAMENTOS!E:E, TREINAMENTOS!D:D, H24, TREINAMENTOS!G:G, E24) -> 260.1 | BX24: =SUMIFS(EXAMES!E:E, EXAMES!D:D, H24, EXAMES!G:G, E24) -> 0 | BY24: =SUM(BN24:BU24)+SUM(BV24:BX24) -> 1660.24 | CA24: ARTUR OLIVEIRA CABRAL | CB24: =IF(SUM(BB24:BD24)+CF24<0, 0, SUM(BB24:BD24)+CF24) -> 118.4 | CC24: =IF(SUM(AV24:AW24)+CG24<0, 0, SUM(AV24:AW24)+CG24) -> 0 | CD24: =SUMIFS(ALIMENTAÇÃO!E:E, ALIMENTAÇÃO!D:D, H24, ALIMENTAÇÃO!G:G, E24) -> 630 | CE24: =SUMIFS(TRANSPORTE!E:E, TRANSPORTE!D:D, H24, TRANSPORTE!G:G, E24) -> 112.8 | CF24: =SUMIFS('PLANO DE SAÚDE'!E:E, 'PLANO DE SAÚDE'!D:D, H24, 'PLANO DE SAÚDE'!G:G, E24) -> 141.86 | CG24: =SUMIFS('PLANO ODONTO'!E:E, 'PLANO ODONTO'!D:D, H24, 'PLANO ODONTO'!G:G, E24) -> 14 | CH24: =BB24+BC24+BD24 -> -23.46 | CI24: =BI24+BJ24 -> 0 | CJ24: =AA24+AB24 -> 0 | CM24: =AV24+AW24 -> -14 | CN24: 1800.66 | CO24: -285.66 | CP24: 1515 | CQ24: 1800 | CR24: 7.735 | CS24: 1800 | CT24: 144 | CU24: 1192.8
A25: =IFERROR(__xludf.DUMMYFUNCTION("""COMPUTED_VALUE"""),"ANGÉLICA DE FRANÇA RAMOS") -> ANGÉLICA DE FRANÇA RAMOS | C25: =IF(COUNTIF(A:A, H25)>0, "OK", "Incompleto") -> OK | D25: =AN25+BY25 -> 5987.3264 | E25: 45809 | F25: 07.391.921/0001-71 | G25: 180 | H25: AUREA CRISTINA DE OLIVEIRA BERNARDES | I25: ANALISTA DE TELECOMUN | J25: 42248 | K25: 3741.16 | M25: 3741.16 | O25: 0 | P25: 0 | T25: 0 | Y25: 0 | AA25: 0 | AB25: 0 | AD25: 0 | AE25: 0 | AF25: 0 | AJ25: 0 | AM25: 0.69 | AN25: =SUM(M25:AM25) -> 3741.85 | AP25: 0 | AQ25: -224.47 | AT25: -0.46 | AV25: 0 | AY25: -37.41 | BB25: 0 | BC25: -2.24 | BF25: 0 | BG25: -342.34 | BH25: -75.93 | BI25: 0 | BL25: =SUM(AO25:BK25) -> -682.85 | BM25: =AN25+BL25 -> 3059 | BN25: =K25/12*1 -> 311.76333 | BO25: =K25/12*1 -> 311.76333 | BP25: =BO25/3 -> 103.92111 | BQ25: =CQ25*CR25% -> 342.33859 | BR25: =CT25 -> 299.29 | BS25: =-(-CD25-AP25) -> 630 | BT25: =IF(CE25+AQ25<0, 0, CE25+AQ25) -> 100.43 | BU25: =CB25+CC25 -> 132.26 | BV25: =SUMIFS('SEGURO DE VIDA'!E:E, 'SEGURO DE VIDA'!D:D, H25, 'SEGURO DE VIDA'!G:G, E25) -> 13.71 | BW25: =SUMIFS(TREINAMENTOS!E:E, TREINAMENTOS!D:D, H25, TREINAMENTOS!G:G, E25) -> 0 | BX25: =SUMIFS(EXAMES!E:E, EXAMES!D:D, H25, EXAMES!G:G, E25) -> 0 | BY25: =SUM(BN25:BU25)+SUM(BV25:BX25) -> 2245.4764 | CA25: AUREA CRISTINA DE OLIVEIRA BER | CB25: =IF(SUM(BB25:BD25)+CF25<0, 0, SUM(BB25:BD25)+CF25) -> 132.26 | CC25: =IF(SUM(AV25:AW25)+CG25<0, 0, SUM(AV25:AW25)+CG25) -> 0 | CD25: =SUMIFS(ALIMENTAÇÃO!E:E, ALIMENTAÇÃO!D:D, H25, ALIMENTAÇÃO!G:G, E25) -> 630 | CE25: =SUMIFS(TRANSPORTE!E:E, TRANSPORTE!D:D, H25, TRANSPORTE!G:G, E25) -> 324.9 | CF25: =SUMIFS('PLANO DE SAÚDE'!E:E, 'PLANO DE SAÚDE'!D:D, H25, 'PLANO DE SAÚDE'!G:G, E25) -> 134.5 | CG25: =SUMIFS('PLANO ODONTO'!E:E, 'PLANO ODONTO'!D:D, H25, 'PLANO ODONTO'!G:G, E25) -> 0 | CH25: =BB25+BC25+BD25 -> -2.24 | CI25: =BI25+BJ25 -> 0 | CJ25: =AA25+AB25 -> 0 | CM25: =AV25+AW25 -> 0 | CN25: 3741.85 | CO25: -682.85 | CP25: 3059 | CQ25: 3741.16 | CR25: 9.1506 | CS25: 3741.16 | CT25: 299.29 | CU25: 3133.96
A26: =IFERROR(__xludf.DUMMYFUNCTION("""COMPUTED_VALUE"""),"ANNA BEATRIZ DOS SANTOS CARNEIRO SILVA") -> ANNA BEATRIZ DOS SANTOS CARNEIRO SILVA | C26: =IF(COUNTIF(A:A, H26)>0, "OK", "Incompleto") -> OK | D26: =AN26+BY26 -> 4579.7325 | E26: 45809 | F26: 20.258.413/0001-88 | G26: 21 | H26: BIANCA RODRIGUES DA SILVEIRA | I26: ASSISTENTE ADMINISTRAT | J26: 44200 | K26: 3200 | M26: 3200 | AC26: 0 | AD26: 0 | AE26: 0 | AF26: 0 | AM26: 0.31 | AN26: =SUM(M26:AM26) -> 3200.31 | AP26: -5.6 | AQ26: 0 | AR26: 0 | AT26: -0.01 | AV26: -14 | BB26: 0 | BC26: 0 | BD26: 0 | BG26: -277.4 | BH26: -12.3 | BL26: =SUM(AO26:BK26) -> -309.31 | BM26: =AN26+BL26 -> 2891 | BN26: =K26/12*1 -> 266.66667 | BO26: =K26/12*1 -> 266.66667 | BP26: =BO26/3 -> 88.888889 | BQ26: =CQ26*CR26% -> 98.880309 | BR26: =CT26 -> 85.33 | BS26: =-(-CD26-AP26) -> 554.4 | BT26: =IF(CE26+AQ26<0, 0, CE26+AQ26) -> 0 | BU26: =CB26+CC26 -> 0 | BV26: =SUMIFS('SEGURO DE VIDA'!E:E, 'SEGURO DE VIDA'!D:D, H26, 'SEGURO DE VIDA'!G:G, E26) -> 18.59 | BW26: =SUMIFS(TREINAMENTOS!E:E, TREINAMENTOS!D:D, H26, TREINAMENTOS!G:G, E26) -> 0 | BX26: =SUMIFS(EXAMES!E:E, EXAMES!D:D, H26, EXAMES!G:G, E26) -> 0 | BY26: =SUM(BN26:BU26)+SUM(BV26:BX26) -> 1379.4225 | CA26: BIANCA RODRIGUES DA SILVEIRA | CB26: =IF(SUM(BB26:BD26)+CF26<0, 0, SUM(BB26:BD26)+CF26) -> 0 | CC26: =IF(SUM(AV26:AW26)+CG26<0, 0, SUM(AV26:AW26)+CG26) -> 0 | CD26: =SUMIFS(ALIMENTAÇÃO!E:E, ALIMENTAÇÃO!D:D, H26, ALIMENTAÇÃO!G:G, E26) -> 560 | CE26: =SUMIFS(TRANSPORTE!E:E, TRANSPORTE!D:D, H26, TRANSPORTE!G:G, E26) -> 0 | CF26: =SUMIFS('PLANO DE SAÚDE'!E:E, 'PLANO DE SAÚDE'!D:D, H26, 'PLANO DE SAÚDE'!G:G, E26) -> 0 | CG26: =SUMIFS('PLANO ODONTO'!E:E, 'PLANO ODONTO'!D:D, H26, 'PLANO ODONTO'!G:G, E26) -> 14 | CH26: =BB26+BC26+BD26 -> 0 | CI26: =BI26+BJ26 -> 0 | CJ26: =AA26+AB26 -> 0 | CM26: =AV26+AW26 -> -14 | CN26: 1066.81 | CO26: -145.81 | CP26: 921 | CQ26: 1066.67 | CR26: 9.27 | CS26: 1066.67 | CT26: 85.33 | CU26: 459.47
A27: =IFERROR(__xludf.DUMMYFUNCTION("""COMPUTED_VALUE"""),"ANTONIO DIOGO DA SILVA TEIXEIRA") -> ANTONIO DIOGO DA SILVA TEIXEIRA | C27: =IF(COUNTIF(A:A, H27)>0, "OK", "Incompleto") -> OK | D27: =AN27+BY27 -> 3568.4689 | E27: 45809 | F27: 07.391.921/0001-71 | G27: 3416 | H27: BRUNA DE JESUS DA SILVA | I27: ASSISTENTE ADMINISTRAT | J27: 45292 | K27: 2000 | M27: 2000 | O27: 0 | P27: 0 | T27: 0 | Y27: 0 | AA27: 0 | AB27: 0 | AD27: 0 | AE27: 0 | AF27: 0 | AJ27: 0 | AM27: 0.34 | AN27: =SUM(M27:AM27) -> 2000.34 | AP27: 0 | AQ27: -120 | AT27: -0.1 | AV27: -14 | AY27: 0 | BB27: 0 | BC27: -2.01 | BF27: 0 | BG27: -157.23 | BH27: 0 | BI27: 0 | BL27: =SUM(AO27:BK27) -> -293.34 | BM27: =AN27+BL27 -> 1707 | BN27: =K27/12*1 -> 166.66667 | BO27: =K27/12*1 -> 166.66667 | BP27: =BO27/3 -> 55.555556 | BQ27: =CQ27*CR27% -> 157.23 | BR27: =CT27 -> 160 | BS27: =-(-CD27-AP27) -> 525 | BT27: =IF(CE27+AQ27<0, 0, CE27+AQ27) -> 204.9 | BU27: =CB27+CC27 -> 118.4 | BV27: =SUMIFS('SEGURO DE VIDA'!E:E, 'SEGURO DE VIDA'!D:D, H27, 'SEGURO DE VIDA'!G:G, E27) -> 13.71 | BW27: =SUMIFS(TREINAMENTOS!E:E, TREINAMENTOS!D:D, H27, TREINAMENTOS!G:G, E27) -> 0 | BX27: =SUMIFS(EXAMES!E:E, EXAMES!D:D, H27, EXAMES!G:G, E27) -> 0 | BY27: =SUM(BN27:BU27)+SUM(BV27:BX27) -> 1568.1289 | CA27: BRUNA DE JESUS DA SILVA | CB27: =IF(SUM(BB27:BD27)+CF27<0, 0, SUM(BB27:BD27)+CF27) -> 118.4 | CC27: =IF(SUM(AV27:AW27)+CG27<0, 0, SUM(AV27:AW27)+CG27) -> 0 | CD27: =SUMIFS(ALIMENTAÇÃO!E:E, ALIMENTAÇÃO!D:D, H27, ALIMENTAÇÃO!G:G, E27) -> 525 | CE27: =SUMIFS(TRANSPORTE!E:E, TRANSPORTE!D:D, H27, TRANSPORTE!G:G, E27) -> 324.9 | CF27: =SUMIFS('PLANO DE SAÚDE'!E:E, 'PLANO DE SAÚDE'!D:D, H27, 'PLANO DE SAÚDE'!G:G, E27) -> 120.41 | CG27: =SUMIFS('PLANO ODONTO'!E:E, 'PLANO ODONTO'!D:D, H27, 'PLANO ODONTO'!G:G, E27) -> 14 | CH27: =BB27+BC27+BD27 -> -2.01 | CI27: =BI27+BJ27 -> 0 | CJ27: =AA27+AB27 -> 0 | CM27: =AV27+AW27 -> -14 | CN27: 2000.34 | CO27: -293.34 | CP27: 1707 | CQ27: 2000 | CR27: 7.8615 | CS27: 2000 | CT27: 160 | CU27: 1392.8
A28: =IFERROR(__xludf.DUMMYFUNCTION("""COMPUTED_VALUE"""),"ARTHUR CASSILHAS DA MATA") -> ARTHUR CASSILHAS DA MATA | C28: =IF(COUNTIF(A:A, H28)>0, "OK", "Incompleto") -> OK | D28: =AN28+BY28 -> 1256.5867 | E28: 45809 | F28: 07.391.921/0001-71 | G28: 3550 | H28: BRUNNO MARQUES ESPOSITO | I28: AUX TEC TELECOMUNICAC | J28: 45831 | K28: 1518 | M28: 404.8 | O28: 0 | P28: 0 | T28: 0 | Y28: 0 | AA28: 0 | AB28: 0 | AD28: 0 | AE28: 0 | AF28: 0 | AJ28: 0 | AM28: 0.85 | AN28: =SUM(M28:AM28) -> 405.65 | AP28: 0 | AQ28: -24.29 | AT28: 0 | AV28: 0 | AY28: 0 | BB28: 0 | BC28: 0 | BF28: 0 | BG28: -30.36 | BH28: 0 | BI28: 0 | BL28: =SUM(AO28:BK28) -> -54.65 | BM28: =AN28+BL28 -> 351 | BN28: =K28/12*1 -> 126.5 | BO28: =K28/12*1 -> 126.5 | BP28: =BO28/3 -> 42.166667 | BQ28: =CQ28*CR28% -> 30.36 | BR28: =CT28 -> 32.38 | BS28: =-(-CD28-AP28) -> 210 | BT28: =IF(CE28+AQ28<0, 0, CE28+AQ28) -> 180.91 | BU28: =CB28+CC28 -> 0 | BV28: =SUMIFS('SEGURO DE VIDA'!E:E, 'SEGURO DE VIDA'!D:D, H28, 'SEGURO DE VIDA'!G:G, E28) -> 0 | BW28: =SUMIFS(TREINAMENTOS!E:E, TREINAMENTOS!D:D, H28, TREINAMENTOS!G:G, E28) -> 0 | BX28: =SUMIFS(EXAMES!E:E, EXAMES!D:D, H28, EXAMES!G:G, E28) -> 102.12 | BY28: =SUM(BN28:BU28)+SUM(BV28:BX28) -> 850.93667 | CA28: BRUNNO MARQUES ESPOSITO | CB28: =IF(SUM(BB28:BD28)+CF28<0, 0, SUM(BB28:BD28)+CF28) -> 0 | CC28: =IF(SUM(AV28:AW28)+CG28<0, 0, SUM(AV28:AW28)+CG28) -> 0 | CD28: =SUMIFS(ALIMENTAÇÃO!E:E, ALIMENTAÇÃO!D:D, H28, ALIMENTAÇÃO!G:G, E28) -> 210 | CE28: =SUMIFS(TRANSPORTE!E:E, TRANSPORTE!D:D, H28, TRANSPORTE!G:G, E28) -> 205.2 | CF28: =SUMIFS('PLANO DE SAÚDE'!E:E, 'PLANO DE SAÚDE'!D:D, H28, 'PLANO DE SAÚDE'!G:G, E28) -> 0 | CG28: =SUMIFS('PLANO ODONTO'!E:E, 'PLANO ODONTO'!D:D, H28, 'PLANO ODONTO'!G:G, E28) -> 0 | CH28: =BB28+BC28+BD28 -> 0 | CI28: =BI28+BJ28 -> 0 | CJ28: =AA28+AB28 -> 0 | CM28: =AV28+AW28 -> 0 | CN28: 405.65 | CO28: -54.65 | CP28: 351 | CQ28: 404.8 | CR28: 7.5 | CS28: 404.8 | CT28: 32.38 | CU28: 0
A29: =IFERROR(__xludf.DUMMYFUNCTION("""COMPUTED_VALUE"""),"ARTHUR RODRIGUES RANGEL") -> ARTHUR RODRIGUES RANGEL | C29: =IF(COUNTIF(A:A, H29)>0, "OK", "Incompleto") -> OK | D29: =AN29+BY29 -> 4368.7405 | E29: 45809 | F29: 07.391.921/0001-71 | G29: 288 | H29: CARLOS DA SILVA SANTOS | I29: INST REDES TELEMATICAS | J29: 44256 | K29: 2495.63 | M29: 2495.63 | O29: 0 | P29: 0 | T29: 0 | Y29: 0 | AA29: 0 | AB29: 0 | AD29: 0 | AE29: 0 | AF29: 0 | AJ29: 0 | AM29: 0.24 | AN29: =SUM(M29:AM29) -> 2495.87 | AP29: 0 | AQ29: -149.74 | AT29: -0.06 | AV29: 0 | AY29: 0 | BB29: 0 | BC29: -2.24 | BF29: 0 | BG29: -201.83 | BH29: 0 | BI29: 0 | BL29: =SUM(AO29:BK29) -> -353.87 | BM29: =AN29+BL29 -> 2142 | BN29: =K29/12*1 -> 207.96917 | BO29: =K29/12*1 -> 207.96917 | BP29: =BO29/3 -> 69.323056 | BQ29: =CQ29*CR29% -> 201.82908 | BR29: =CT29 -> 199.65 | BS29: =-(-CD29-AP29) -> 665 | BT29: =IF(CE29+AQ29<0, 0, CE29+AQ29) -> 175.16 | BU29: =CB29+CC29 -> 132.26 | BV29: =SUMIFS('SEGURO DE VIDA'!E:E, 'SEGURO DE VIDA'!D:D, H29, 'SEGURO DE VIDA'!G:G, E29) -> 13.71 | BW29: =SUMIFS(TREINAMENTOS!E:E, TREINAMENTOS!D:D, H29, TREINAMENTOS!G:G, E29) -> 0 | BX29: =SUMIFS(EXAMES!E:E, EXAMES!D:D, H29, EXAMES!G:G, E29) -> 0 | BY29: =SUM(BN29:BU29)+SUM(BV29:BX29) -> 1872.8705 | CA29: CARLOS DA SILVA SANTOS | CB29: =IF(SUM(BB29:BD29)+CF29<0, 0, SUM(BB29:BD29)+CF29) -> 132.26 | CC29: =IF(SUM(AV29:AW29)+CG29<0, 0, SUM(AV29:AW29)+CG29) -> 0 | CD29: =SUMIFS(ALIMENTAÇÃO!E:E, ALIMENTAÇÃO!D:D, H29, ALIMENTAÇÃO!G:G, E29) -> 665 | CE29: =SUMIFS(TRANSPORTE!E:E, TRANSPORTE!D:D, H29, TRANSPORTE!G:G, E29) -> 324.9 | CF29: =SUMIFS('PLANO DE SAÚDE'!E:E, 'PLANO DE SAÚDE'!D:D, H29, 'PLANO DE SAÚDE'!G:G, E29) -> 134.5 | CG29: =SUMIFS('PLANO ODONTO'!E:E, 'PLANO ODONTO'!D:D, H29, 'PLANO ODONTO'!G:G, E29) -> 0 | CH29: =BB29+BC29+BD29 -> -2.24 | CI29: =BI29+BJ29 -> 0 | CJ29: =AA29+AB29 -> 0 | CM29: =AV29+AW29 -> 0 | CN29: 2495.87 | CO29: -353.87 | CP29: 2142 | CQ29: 2495.63 | CR29: 8.0873 | CS29: 2495.63 | CT29: 199.65 | CU29: 1888.43
A30: =IFERROR(__xludf.DUMMYFUNCTION("""COMPUTED_VALUE"""),"ARTHUR SOUZA LEMOS PINHEIRO") -> ARTHUR SOUZA LEMOS PINHEIRO | C30: =IF(COUNTIF(A:A, H30)>0, "OK", "Incompleto") -> OK | D30: =AN30+BY30 -> 3519.45 | E30: 45809 | F30: 07.391.921/0001-71 | G30: 3493 | H30: CARLOS EDUARDO DE MORAIS RODRIGUES JUNIOR | I30: INSTALADOR | J30: 45635 | K30: 1800 | M30: 1800 | O30: 0 | P30: 0 | T30: 0 | Y30: 0 | AA30: 0 | AB30: 0 | AD30: 0 | AE30: 0 | AF30: 0 | AJ30: 0 | AM30: 0.51 | AN30: =SUM(M30:AM30) -> 1800.51 | AP30: 0 | AQ30: -108 | AT30: -0.28 | AV30: -14 | AY30: 0 | BB30: 0 | BC30: 0 | BF30: 0 | BG30: -139.23 | BH30: 0 | BI30: 0 | BL30: =SUM(AO30:BK30) -> -261.51 | BM30: =AN30+BL30 -> 1539 | BN30: =K30/12*1 -> 150 | BO30: =K30/12*1 -> 150 | BP30: =BO30/3 -> 50 | BQ30: =CQ30*CR30% -> 139.23 | BR30: =CT30 -> 144 | BS30: =-(-CD30-AP30) -> 595 | BT30: =IF(CE30+AQ30<0, 0, CE30+AQ30) -> 216.9 | BU30: =CB30+CC30 -> 0 | BV30: =SUMIFS('SEGURO DE VIDA'!E:E, 'SEGURO DE VIDA'!D:D, H30, 'SEGURO DE VIDA'!G:G, E30) -> 13.71 | BW30: =SUMIFS(TREINAMENTOS!E:E, TREINAMENTOS!D:D, H30, TREINAMENTOS!G:G, E30) -> 260.1 | BX30: =SUMIFS(EXAMES!E:E, EXAMES!D:D, H30, EXAMES!G:G, E30) -> 0 | BY30: =SUM(BN30:BU30)+SUM(BV30:BX30) -> 1718.94 | CA30: CARLOS EDUARDO DE MORAIS ROL | CB30: =IF(SUM(BB30:BD30)+CF30<0, 0, SUM(BB30:BD30)+CF30) -> 0 | CC30: =IF(SUM(AV30:AW30)+CG30<0, 0, SUM(AV30:AW30)+CG30) -> 0 | CD30: =SUMIFS(ALIMENTAÇÃO!E:E, ALIMENTAÇÃO!D:D, H30, ALIMENTAÇÃO!G:G, E30) -> 595 | CE30: =SUMIFS(TRANSPORTE!E:E, TRANSPORTE!D:D, H30, TRANSPORTE!G:G, E30) -> 324.9 | CF30: =SUMIFS('PLANO DE SAÚDE'!E:E, 'PLANO DE SAÚDE'!D:D, H30, 'PLANO DE SAÚDE'!G:G, E30) -> 0 | CG30: =SUMIFS('PLANO ODONTO'!E:E, 'PLANO ODONTO'!D:D, H30, 'PLANO ODONTO'!G:G, E30) -> 14 | CH30: =BB30+BC30+BD30 -> 0 | CI30: =BI30+BJ30 -> 0 | CJ30: =AA30+AB30 -> 0 | CM30: =AV30+AW30 -> -14 | CN30: 1800.51 | CO30: -261.51 | CP30: 1539 | CQ30: 1800 | CR30: 7.735 | CS30: 1800 | CT30: 144 | CU30: 1192.8
A31: =IFERROR(__xludf.DUMMYFUNCTION("""COMPUTED_VALUE"""),"ARTHUR TELES SILVA DE ANDRADE") -> ARTHUR TELES SILVA DE ANDRADE | C31: =IF(COUNTIF(A:A, H31)>0, "OK", "Incompleto") -> OK | D31: =AN31+BY31 -> 3048.227 | E31: 45809 | F31: 07.391.921/0001-71 | G31: 182 | H31: CARLOS EDUARDO SILVA DE SOUZA | I31: COORDENADOR DE TELEC | J31: 42248 | K31: 4336.05 | L31: Férias | M31: 1445.35 | O31: 0 | P31: 0 | T31: 0 | Y31: 0 | AA31: 0 | AB31: 0 | AD31: 0 | AE31: 0 | AF31: 0 | AJ31: 0 | AM31: 0.63 | AN31: =SUM(M31:AM31) -> 1445.98 | AP31: 0 | AQ31: 0 | AT31: -0.85 | AV31: -14 | AY31: 0 | BB31: -65.27 | BC31: -2.24 | BF31: 0 | BG31: -195.62 | BH31: 0 | BI31: 0 | BL31: =SUM(AO31:BK31) -> -277.98 | BM31: =AN31+BL31 -> 1168 | BN31: =K31/12*1 -> 361.3375 | BO31: =K31/12*1 -> 361.3375 | BP31: =BO31/3 -> 120.44583 | BQ31: =CQ31*CR31% -> 150.41613 | BR31: =CT31 -> 115.62 | BS31: =-(-CD31-AP31) -> 245 | BT31: =IF(CE31+AQ31<0, 0, CE31+AQ31) -> 0 | BU31: =CB31+CC31 -> 132.26 | BV31: =SUMIFS('SEGURO DE VIDA'!E:E, 'SEGURO DE VIDA'!D:D, H31, 'SEGURO DE VIDA'!G:G, E31) -> 13.71 | BW31: =SUMIFS(TREINAMENTOS!E:E, TREINAMENTOS!D:D, H31, TREINAMENTOS!G:G, E31) -> 0 | BX31: =SUMIFS(EXAMES!E:E, EXAMES!D:D, H31, EXAMES!G:G, E31) -> 102.12 | BY31: =SUM(BN31:BU31)+SUM(BV31:BX31) -> 1602.247 | CA31: CARLOS EDUARDO SILVA DE SOUZ | CB31: =IF(SUM(BB31:BD31)+CF31<0, 0, SUM(BB31:BD31)+CF31) -> 132.26 | CC31: =IF(SUM(AV31:AW31)+CG31<0, 0, SUM(AV31:AW31)+CG31) -> 0 | CD31: =SUMIFS(ALIMENTAÇÃO!E:E, ALIMENTAÇÃO!D:D, H31, ALIMENTAÇÃO!G:G, E31) -> 245 | CE31: =SUMIFS(TRANSPORTE!E:E, TRANSPORTE!D:D, H31, TRANSPORTE!G:G, E31) -> 0 | CF31: =SUMIFS('PLANO DE SAÚDE'!E:E, 'PLANO DE SAÚDE'!D:D, H31, 'PLANO DE SAÚDE'!G:G, E31) -> 199.77 | CG31: =SUMIFS('PLANO ODONTO'!E:E, 'PLANO ODONTO'!D:D, H31, 'PLANO ODONTO'!G:G, E31) -> 14 | CH31: =BB31+BC31+BD31 -> -67.51 | CI31: =BI31+BJ31 -> 0 | CJ31: =AA31+AB31 -> 0 | CM31: =AV31+AW31 -> -14 | CN31: 1445.98 | CO31: -277.98 | CP31: 1168 | CQ31: 1445.35 | CR31: 10.4069 | CS31: 1445.35 | CT31: 115.62 | CU31: 838.15
A32: =IFERROR(__xludf.DUMMYFUNCTION("""COMPUTED_VALUE"""),"ARTUR OLIVEIRA CABRAL") -> ARTUR OLIVEIRA CABRAL | C32: =IF(COUNTIF(A:A, H32)>0, "OK", "Incompleto") -> OK | D32: =AN32+BY32 -> 2926.9267 | E32: 45809 | F32: 07.391.921/0001-71 | G32: 3478 | H32: CARLOS GOMES DA SILVA | I32: AUX. DE INSTALACAO DE R | J32: 45597 | K32: 1518 | L32: Atestado | M32: 1518 | O32: 0 | P32: 0 | T32: 0 | Y32: 0 | AA32: 0 | AB32: 0 | AD32: 0 | AE32: 0 | AF32: 0 | AJ32: 0 | AM32: 0.94 | AN32: =SUM(M32:AM32) -> 1518.94 | AP32: 0 | AQ32: -91.08 | AT32: -0.01 | AV32: 0 | AY32: 0 | BB32: 0 | BC32: 0 | BF32: 0 | BG32: -113.85 | BH32: 0 | BI32: 0 | BL32: =SUM(AO32:BK32) -> -204.94 | BM32: =AN32+BL32 -> 1314 | BN32: =K32/12*1 -> 126.5 | BO32: =K32/12*1 -> 126.5 | BP32: =BO32/3 -> 42.166667 | BQ32: =CQ32*CR32% -> 113.85 | BR32: =CT32 -> 121.44 | BS32: =-(-CD32-AP32) -> 630 | BT32: =IF(CE32+AQ32<0, 0, CE32+AQ32) -> 233.82 | BU32: =CB32+CC32 -> 0 | BV32: =SUMIFS('SEGURO DE VIDA'!E:E, 'SEGURO DE VIDA'!D:D, H32, 'SEGURO DE VIDA'!G:G, E32) -> 13.71 | BW32: =SUMIFS(TREINAMENTOS!E:E, TREINAMENTOS!D:D, H32, TREINAMENTOS!G:G, E32) -> 0 | BX32: =SUMIFS(EXAMES!E:E, EXAMES!D:D, H32, EXAMES!G:G, E32) -> 0 | BY32: =SUM(BN32:BU32)+SUM(BV32:BX32) -> 1407.9867 | CA32: CARLOS GOMES DA SILVA | CB32: =IF(SUM(BB32:BD32)+CF32<0, 0, SUM(BB32:BD32)+CF32) -> 0 | CC32: =IF(SUM(AV32:AW32)+CG32<0, 0, SUM(AV32:AW32)+CG32) -> 0 | CD32: =SUMIFS(ALIMENTAÇÃO!E:E, ALIMENTAÇÃO!D:D, H32, ALIMENTAÇÃO!G:G, E32) -> 630 | CE32: =SUMIFS(TRANSPORTE!E:E, TRANSPORTE!D:D, H32, TRANSPORTE!G:G, E32) -> 324.9 | CF32: =SUMIFS('PLANO DE SAÚDE'!E:E, 'PLANO DE SAÚDE'!D:D, H32, 'PLANO DE SAÚDE'!G:G, E32) -> 0 | CG32: =SUMIFS('PLANO ODONTO'!E:E, 'PLANO ODONTO'!D:D, H32, 'PLANO ODONTO'!G:G, E32) -> 0 | CH32: =BB32+BC32+BD32 -> 0 | CI32: =BI32+BJ32 -> 0 | CJ32: =AA32+AB32 -> 0 | CM32: =AV32+AW32 -> 0 | CN32: 1518.94 | CO32: -204.94 | CP32: 1314 | CQ32: 1518 | CR32: 7.5 | CS32: 1518 | CT32: 121.44 | CU32: 910.8
A33: =IFERROR(__xludf.DUMMYFUNCTION("""COMPUTED_VALUE"""),"AUREA CRISTINA DE OLIVEIRA BERNARDES") -> AUREA CRISTINA DE OLIVEIRA BERNARDES | C33: =IF(COUNTIF(A:A, H33)>0, "OK", "Incompleto") -> OK | D33: =AN33+BY33 -> 6286.2317 | E33: 45809 | F33: 07.391.921/0001-71 | G33: 67 | H33: CARLOS ROBERTO MESQUITA | I33: TECNICO DE TELECOMUNI | J33: 41078 | K33: 3159.37 | L33: Atestado | M33: 3159.37 | O33: 0 | P33: 947.81 | T33: 0 | Y33: 0 | AA33: 0 | AB33: 0 | AD33: 0 | AE33: 0 | AF33: 0 | AJ33: 0 | AM33: 0.19 | AN33: =SUM(M33:AM33) -> 4107.37 | AP33: 0 | AQ33: 0 | AT33: -0.07 | AV33: -14 | AY33: 0 | BB33: -28.5 | BC33: -478.7 | BF33: 0 | BG33: -386.26 | BH33: -130.84 | BI33: 0 | BL33: =SUM(AO33:BK33) -> -1038.37 | BM33: =AN33+BL33 -> 3069 | BN33: =K33/12*1 -> 263.28083 | BO33: =K33/12*1 -> 263.28083 | BP33: =BO33/3 -> 87.760278 | BQ33: =CQ33*CR33% -> 386.25974 | BR33: =CT33 -> 328.57 | BS33: =-(-CD33-AP33) -> 665 | BT33: =IF(CE33+AQ33<0, 0, CE33+AQ33) -> 171 | BU33: =CB33+CC33 -> 0 | BV33: =SUMIFS('SEGURO DE VIDA'!E:E, 'SEGURO DE VIDA'!D:D, H33, 'SEGURO DE VIDA'!G:G, E33) -> 13.71 | BW33: =SUMIFS(TREINAMENTOS!E:E, TREINAMENTOS!D:D, H33, TREINAMENTOS!G:G, E33) -> 0 | BX33: =SUMIFS(EXAMES!E:E, EXAMES!D:D, H33, EXAMES!G:G, E33) -> 0 | BY33: =SUM(BN33:BU33)+SUM(BV33:BX33) -> 2178.8617 | CA33: CARLOS ROBERTO MESQUITA | CB33: =IF(SUM(BB33:BD33)+CF33<0, 0, SUM(BB33:BD33)+CF33) -> 0 | CC33: =IF(SUM(AV33:AW33)+CG33<0, 0, SUM(AV33:AW33)+CG33) -> 0 | CD33: =SUMIFS(ALIMENTAÇÃO!E:E, ALIMENTAÇÃO!D:D, H33, ALIMENTAÇÃO!G:G, E33) -> 665 | CE33: =SUMIFS(TRANSPORTE!E:E, TRANSPORTE!D:D, H33, TRANSPORTE!G:G, E33) -> 171 | CF33: =SUMIFS('PLANO DE SAÚDE'!E:E, 'PLANO DE SAÚDE'!D:D, H33, 'PLANO DE SAÚDE'!G:G, E33) -> 480.73 | CG33: =SUMIFS('PLANO ODONTO'!E:E, 'PLANO ODONTO'!D:D, H33, 'PLANO ODONTO'!G:G, E33) -> 14 | CH33: =BB33+BC33+BD33 -> -507.2 | CI33: =BI33+BJ33 -> 0 | CJ33: =AA33+AB33 -> 0 | CM33: =AV33+AW33 -> -14 | CN33: 4107.37 | CO33: -1038.37 | CP33: 3069 | CQ33: 4107.18 | CR33: 9.4045 | CS33: 4107.18 | CT33: 328.57 | CU33: 3499.98
A34: =IFERROR(__xludf.DUMMYFUNCTION("""COMPUTED_VALUE"""),"BEATRIZ MEIRA CUNHA") -> BEATRIZ MEIRA CUNHA | C34: =IF(COUNTIF(A:A, H34)>0, "OK", "Incompleto") -> OK | D34: =AN34+BY34 -> 1467.4433 | E34: 45809 | F34: 07.391.921/0001-71 | G34: 3552 | H34: CAUÃ BARBOSA DE CARVALHO | I34: ESTAGIARIO EM TELECOM | J34: 45831 | K34: 750 | M34: 200 | O34: 0 | P34: 0 | T34: 0 | Y34: 0 | AA34: 0 | AB34: 0 | AD34: 0 | AE34: 0 | AF34: 0 | AJ34: 0 | AM34: 0 | AN34: =SUM(M34:AM34) -> 200 | AP34: 0 | AQ34: 0 | AT34: 0 | AV34: 0 | AY34: 0 | BB34: 0 | BC34: 0 | BF34: 0 | BG34: 0 | BH34: 0 | BI34: 0 | BL34: =SUM(AO34:BK34) -> 0 | BM34: =AN34+BL34 -> 200 | BN34: =K34/12*1 -> 62.5 | BO34: =K34/12*1 -> 62.5 | BP34: =BO34/3 -> 20.833333 | BQ34: =CQ34*CR34% -> 0 | BR34: =CT34 -> 0 | BS34: =-(-CD34-AP34) -> 420 | BT34: =IF(CE34+AQ34<0, 0, CE34+AQ34) -> 102.6 | BU34: =CB34+CC34 -> 0 | BV34: =SUMIFS('SEGURO DE VIDA'!E:E, 'SEGURO DE VIDA'!D:D, H34, 'SEGURO DE VIDA'!G:G, E34) -> 0 | BW34: =SUMIFS(TREINAMENTOS!E:E, TREINAMENTOS!D:D, H34, TREINAMENTOS!G:G, E34) -> 0 | BX34: =SUMIFS(EXAMES!E:E, EXAMES!D:D, H34, EXAMES!G:G, E34) -> 599.01 | BY34: =SUM(BN34:BU34)+SUM(BV34:BX34) -> 1267.4433 | CA34: CAUA BARBOSA DE CARVALHO | CB34: =IF(SUM(BB34:BD34)+CF34<0, 0, SUM(BB34:BD34)+CF34) -> 0 | CC34: =IF(SUM(AV34:AW34)+CG34<0, 0, SUM(AV34:AW34)+CG34) -> 0 | CD34: =SUMIFS(ALIMENTAÇÃO!E:E, ALIMENTAÇÃO!D:D, H34, ALIMENTAÇÃO!G:G, E34) -> 420 | CE34: =SUMIFS(TRANSPORTE!E:E, TRANSPORTE!D:D, H34, TRANSPORTE!G:G, E34) -> 102.6 | CF34: =SUMIFS('PLANO DE SAÚDE'!E:E, 'PLANO DE SAÚDE'!D:D, H34, 'PLANO DE SAÚDE'!G:G, E34) -> 0 | CG34: =SUMIFS('PLANO ODONTO'!E:E, 'PLANO ODONTO'!D:D, H34, 'PLANO ODONTO'!G:G, E34) -> 0 | CH34: =BB34+BC34+BD34 -> 0 | CI34: =BI34+BJ34 -> 0 | CJ34: =AA34+AB34 -> 0 | CM34: =AV34+AW34 -> 0 | CN34: 200 | CO34: 0 | CP34: 200 | CQ34: 0 | CR34: 0 | CS34: 0 | CT34: 0 | CU34: 0
A35: =IFERROR(__xludf.DUMMYFUNCTION("""COMPUTED_VALUE"""),"BIANCA RODRIGUES DA SILVEIRA") -> BIANCA RODRIGUES DA SILVEIRA | C35: =IF(COUNTIF(A:A, H35)>0, "OK", "Incompleto") -> OK | D35: =AN35+BY35 -> 4723.5144 | E35: 45809 | F35: 07.391.921/0001-71 | G35: 3353 | H35: CAUA VIEIRA LORENCINI ZANONI | I35: INSTALADOR JUNIOR | J35: 45019 | K35: 1700 | M35: 1700 | O35: 0 | P35: 510 | T35: 0 | Y35: 150 | AA35: 0 | AB35: 0 | AD35: 436.75 | AE35: 188.96 | AF35: 156.43 | AJ35: 0 | AM35: 0.21 | AN35: =SUM(M35:AM35) -> 3142.35 | AP35: 0 | AQ35: -102 | AT35: -0.81 | AV35: -14 | AY35: 0 | BB35: 0 | BC35: -100.08 | BF35: 0 | BG35: -252.46 | BH35: 0 | BI35: 0 | BL35: =SUM(AO35:BK35) -> -469.35 | BM35: =AN35+BL35 -> 2673 | BN35: =K35/12*1 -> 141.66667 | BO35: =K35/12*1 -> 141.66667 | BP35: =BO35/3 -> 47.222222 | BQ35: =CQ35*CR35% -> 252.45882 | BR35: =CT35 -> 239.37 | BS35: =-(-CD35-AP35) -> 480 | BT35: =IF(CE35+AQ35<0, 0, CE35+AQ35) -> 0 | BU35: =CB35+CC35 -> 225.07 | BV35: =SUMIFS('SEGURO DE VIDA'!E:E, 'SEGURO DE VIDA'!D:D, H35, 'SEGURO DE VIDA'!G:G, E35) -> 13.71 | BW35: =SUMIFS(TREINAMENTOS!E:E, TREINAMENTOS!D:D, H35, TREINAMENTOS!G:G, E35) -> 0 | BX35: =SUMIFS(EXAMES!E:E, EXAMES!D:D, H35, EXAMES!G:G, E35) -> 40 | BY35: =SUM(BN35:BU35)+SUM(BV35:BX35) -> 1581.1644 | CA35: CAUA VIEIRA LORENCINI ZANONI | CB35: =IF(SUM(BB35:BD35)+CF35<0, 0, SUM(BB35:BD35)+CF35) -> 225.07 | CC35: =IF(SUM(AV35:AW35)+CG35<0, 0, SUM(AV35:AW35)+CG35) -> 0 | CD35: =SUMIFS(ALIMENTAÇÃO!E:E, ALIMENTAÇÃO!D:D, H35, ALIMENTAÇÃO!G:G, E35) -> 480 | CE35: =SUMIFS(TRANSPORTE!E:E, TRANSPORTE!D:D, H35, TRANSPORTE!G:G, E35) -> 43.5 | CF35: =SUMIFS('PLANO DE SAÚDE'!E:E, 'PLANO DE SAÚDE'!D:D, H35, 'PLANO DE SAÚDE'!G:G, E35) -> 325.15 | CG35: =SUMIFS('PLANO ODONTO'!E:E, 'PLANO ODONTO'!D:D, H35, 'PLANO ODONTO'!G:G, E35) -> 14 | CH35: =BB35+BC35+BD35 -> -100.08 | CI35: =BI35+BJ35 -> 0 | CJ35: =AA35+AB35 -> 0 | CM35: =AV35+AW35 -> -14 | CN35: 3142.35 | CO35: -469.35 | CP35: 2673 | CQ35: 2992.14 | CR35: 8.4374 | CS35: 2992.14 | CT35: 239.37 | CU35: 2534.94
A36: =IFERROR(__xludf.DUMMYFUNCTION("""COMPUTED_VALUE"""),"BRUNA DE JESUS DA SILVA") -> BRUNA DE JESUS DA SILVA | C36: =IF(COUNTIF(A:A, H36)>0, "OK", "Incompleto") -> OK | D36: =AN36+BY36 -> 2386.0954 | E36: 45809 | F36: 07.391.921/0001-71 | G36: 3513 | H36: CLARA GABRIELLE NASCIMENTO FIEL | I36: Jovem Aprendiz em Op de St | J36: 45726 | K36: 1069.48 | M36: 1069.48 | O36: 0 | P36: 0 | T36: 0 | Y36: 0 | AA36: 0 | AB36: 0 | AD36: 0 | AE36: 0 | AF36: 0 | AJ36: 0 | AM36: 0.96 | AN36: =SUM(M36:AM36) -> 1070.44 | AP36: 0 | AQ36: -64.17 | AT36: -0.35 | AV36: -14 | AY36: 0 | BB36: 0 | BC36: -1.71 | BF36: 0 | BG36: -80.21 | BH36: 0 | BI36: 0 | BL36: =SUM(AO36:BK36) -> -160.44 | BM36: =AN36+BL36 -> 910 | BN36: =K36/12*1 -> 89.123333 | BO36: =K36/12*1 -> 89.123333 | BP36: =BO36/3 -> 29.707778 | BQ36: =CQ36*CR36% -> 80.211 | BR36: =CT36 -> 21.38 | BS36: =-(-CD36-AP36) -> 665 | BT36: =IF(CE36+AQ36<0, 0, CE36+AQ36) -> 226.53 | BU36: =CB36+CC36 -> 100.87 | BV36: =SUMIFS('SEGURO DE VIDA'!E:E, 'SEGURO DE VIDA'!D:D, H36, 'SEGURO DE VIDA'!G:G, E36) -> 13.71 | BW36: =SUMIFS(TREINAMENTOS!E:E, TREINAMENTOS!D:D, H36, TREINAMENTOS!G:G, E36) -> 0 | BX36: =SUMIFS(EXAMES!E:E, EXAMES!D:D, H36, EXAMES!G:G, E36) -> 0 | BY36: =SUM(BN36:BU36)+SUM(BV36:BX36) -> 1315.6554 | CA36: CLARA GABRIELLE NASCIMENTO FI | CB36: =IF(SUM(BB36:BD36)+CF36<0, 0, SUM(BB36:BD36)+CF36) -> 100.87 | CC36: =IF(SUM(AV36:AW36)+CG36<0, 0, SUM(AV36:AW36)+CG36) -> 0 | CD36: =SUMIFS(ALIMENTAÇÃO!E:E, ALIMENTAÇÃO!D:D, H36, ALIMENTAÇÃO!G:G, E36) -> 665 | CE36: =SUMIFS(TRANSPORTE!E:E, TRANSPORTE!D:D, H36, TRANSPORTE!G:G, E36) -> 290.7 | CF36: =SUMIFS('PLANO DE SAÚDE'!E:E, 'PLANO DE SAÚDE'!D:D, H36, 'PLANO DE SAÚDE'!G:G, E36) -> 102.58 | CG36: =SUMIFS('PLANO ODONTO'!E:E, 'PLANO ODONTO'!D:D, H36, 'PLANO ODONTO'!G:G, E36) -> 14 | CH36: =BB36+BC36+BD36 -> -1.71 | CI36: =BI36+BJ36 -> 0 | CJ36: =AA36+AB36 -> 0 | CM36: =AV36+AW36 -> -14 | CN36: 1070.44 | CO36: -160.44 | CP36: 910 | CQ36: 1069.48 | CR36: 7.5 | CS36: 1069.48 | CT36: 21.38 | CU36: 462.28
A37: =IFERROR(__xludf.DUMMYFUNCTION("""COMPUTED_VALUE"""),"BRUNNO MARQUES ESPOSITO") -> BRUNNO MARQUES ESPOSITO | C37: =IF(COUNTIF(A:A, H37)>0, "OK", "Incompleto") -> OK | D37: =AN37+BY37 -> 3898.5996 | E37: 45809 | F37: 07.391.921/0001-71 | G37: 283 | H37: CLERISTON CLEDSON GOMES DA SILVA | I37: INST REDES TELEMATICAS | J37: 44228 | K37: 2495.63 | L37: Férias | M37: 2246.07 | O37: 0 | P37: 0 | T37: 0 | Y37: 0 | AA37: 0 | AB37: 0 | AD37: 0 | AE37: 0 | AF37: 0 | AJ37: 0 | AM37: 0.67 | AN37: =SUM(M37:AM37) -> 2246.74 | AP37: 0 | AQ37: -134.76 | AT37: -1.37 | AV37: 0 | AY37: 0 | BB37: 0 | BC37: -2.24 | BF37: 0 | BG37: -184.37 | BH37: 0 | BI37: 0 | BL37: =SUM(AO37:BK37) -> -322.74 | BM37: =AN37+BL37 -> 1924 | BN37: =K37/12*1 -> 207.96917 | BO37: =K37/12*1 -> 207.96917 | BP37: =BO37/3 -> 69.323056 | BQ37: =CQ37*CR37% -> 182.3082 | BR37: =CT37 -> 179.68 | BS37: =-(-CD37-AP37) -> 630 | BT37: =IF(CE37+AQ37<0, 0, CE37+AQ37) -> 28.64 | BU37: =CB37+CC37 -> 132.26 | BV37: =SUMIFS('SEGURO DE VIDA'!E:E, 'SEGURO DE VIDA'!D:D, H37, 'SEGURO DE VIDA'!G:G, E37) -> 13.71 | BW37: =SUMIFS(TREINAMENTOS!E:E, TREINAMENTOS!D:D, H37, TREINAMENTOS!G:G, E37) -> 0 | BX37: =SUMIFS(EXAMES!E:E, EXAMES!D:D, H37, EXAMES!G:G, E37) -> 0 | BY37: =SUM(BN37:BU37)+SUM(BV37:BX37) -> 1651.8596 | CA37: CLERISTON CLEDSON GOMES DA S | CB37: =IF(SUM(BB37:BD37)+CF37<0, 0, SUM(BB37:BD37)+CF37) -> 132.26 | CC37: =IF(SUM(AV37:AW37)+CG37<0, 0, SUM(AV37:AW37)+CG37) -> 0 | CD37: =SUMIFS(ALIMENTAÇÃO!E:E, ALIMENTAÇÃO!D:D, H37, ALIMENTAÇÃO!G:G, E37) -> 630 | CE37: =SUMIFS(TRANSPORTE!E:E, TRANSPORTE!D:D, H37, TRANSPORTE!G:G, E37) -> 163.4 | CF37: =SUMIFS('PLANO DE SAÚDE'!E:E, 'PLANO DE SAÚDE'!D:D, H37, 'PLANO DE SAÚDE'!G:G, E37) -> 134.5 | CG37: =SUMIFS('PLANO ODONTO'!E:E, 'PLANO ODONTO'!D:D, H37, 'PLANO ODONTO'!G:G, E37) -> 0 | CH37: =BB37+BC37+BD37 -> -2.24 | CI37: =BI37+BJ37 -> 0 | CJ37: =AA37+AB37 -> 0 | CM37: =AV37+AW37 -> 0 | CN37: 2246.74 | CO37: -322.74 | CP37: 1924 | CQ37: 2246.06 | CR37: 8.1168 | CS37: 2246.07 | CT37: 179.68 | CU37: 1638.87
A38: =IFERROR(__xludf.DUMMYFUNCTION("""COMPUTED_VALUE"""),"BRUNO DE MORAES LIMA") -> BRUNO DE MORAES LIMA | C38: =IF(COUNTIF(A:A, H38)>0, "OK", "Incompleto") -> OK | D38: =AN38+BY38 -> 3155.9641 | E38: 45809 | F38: 07.391.921/0001-71 | G38: 3474 | H38: CLEVERSON BHERING CLARE JUNIOR | I38: ASSIST. SERVICE DESK | J38: 45586 | K38: 1700 | M38: 1700 | O38: 0 | P38: 0 | T38: 0 | Y38: 0 | AA38: 0 | AB38: 0 | AD38: 0 | AE38: 0 | AF38: 0 | AJ38: 0 | AM38: 0.67 | AN38: =SUM(M38:AM38) -> 1700.67 | AP38: 0 | AQ38: -102 | AT38: -0.43 | AV38: -14 | AY38: 0 | BB38: 0 | BC38: -2.01 | BF38: 0 | BG38: -130.23 | BH38: 0 | BI38: 0 | BL38: =SUM(AO38:BK38) -> -248.67 | BM38: =AN38+BL38 -> 1452 | BN38: =K38/12*1 -> 141.66667 | BO38: =K38/12*1 -> 141.66667 | BP38: =BO38/3 -> 47.222222 | BQ38: =CQ38*CR38% -> 130.2285 | BR38: =CT38 -> 136 | BS38: =-(-CD38-AP38) -> 665 | BT38: =IF(CE38+AQ38<0, 0, CE38+AQ38) -> 61.4 | BU38: =CB38+CC38 -> 118.4 | BV38: =SUMIFS('SEGURO DE VIDA'!E:E, 'SEGURO DE VIDA'!D:D, H38, 'SEGURO DE VIDA'!G:G, E38) -> 13.71 | BW38: =SUMIFS(TREINAMENTOS!E:E, TREINAMENTOS!D:D, H38, TREINAMENTOS!G:G, E38) -> 0 | BX38: =SUMIFS(EXAMES!E:E, EXAMES!D:D, H38, EXAMES!G:G, E38) -> 0 | BY38: =SUM(BN38:BU38)+SUM(BV38:BX38) -> 1455.2941 | CA38: CLEVERSON BHERING CLARE JUNIO | CB38: =IF(SUM(BB38:BD38)+CF38<0, 0, SUM(BB38:BD38)+CF38) -> 118.4 | CC38: =IF(SUM(AV38:AW38)+CG38<0, 0, SUM(AV38:AW38)+CG38) -> 0 | CD38: =SUMIFS(ALIMENTAÇÃO!E:E, ALIMENTAÇÃO!D:D, H38, ALIMENTAÇÃO!G:G, E38) -> 665 | CE38: =SUMIFS(TRANSPORTE!E:E, TRANSPORTE!D:D, H38, TRANSPORTE!G:G, E38) -> 163.4 | CF38: =SUMIFS('PLANO DE SAÚDE'!E:E, 'PLANO DE SAÚDE'!D:D, H38, 'PLANO DE SAÚDE'!G:G, E38) -> 120.41 | CG38: =SUMIFS('PLANO ODONTO'!E:E, 'PLANO ODONTO'!D:D, H38, 'PLANO ODONTO'!G:G, E38) -> 14 | CH38: =BB38+BC38+BD38 -> -2.01 | CI38: =BI38+BJ38 -> 0 | CJ38: =AA38+AB38 -> 0 | CM38: =AV38+AW38 -> -14 | CN38: 1700.67 | CO38: -248.67 | CP38: 1452 | CQ38: 1700 | CR38: 7.6605 | CS38: 1700 | CT38: 136 | CU38: 1092.8
A39: =IFERROR(__xludf.DUMMYFUNCTION("""COMPUTED_VALUE"""),"BRUNO DUTRA DE MACEDO") -> BRUNO DUTRA DE MACEDO | C39: =IF(COUNTIF(A:A, H39)>0, "OK", "Incompleto") -> OK | D39: =AN39+BY39 -> 3194.7959 | E39: 45809 | F39: 07.391.921/0001-71 | G39: 3536 | H39: DANIEL ANCHIETA BRAZIEL PETZOLD | I39: AUX. DE INSTALACAO DE R | J39: 45790 | K39: 1518 | M39: 1518 | O39: 93.53 | P39: 0 | T39: 0 | Y39: 0 | AA39: 0 | AB39: 0 | AD39: 0 | AE39: 0 | AF39: 23.38 | AJ39: 0 | AM39: 0.08 | AN39: =SUM(M39:AM39) -> 1634.99 | AP39: 0 | AQ39: 0 | AT39: -0.36 | AV39: -14 | AY39: 0 | BB39: 0 | BC39: -1.26 | BF39: 0 | BG39: -124.37 | BH39: 0 | BI39: 0 | BL39: =SUM(AO39:BK39) -> -139.99 | BM39: =AN39+BL39 -> 1495 | BN39: =K39/12*1 -> 126.5 | BO39: =K39/12*1 -> 126.5 | BP39: =BO39/3 -> 42.166667 | BQ39: =CQ39*CR39% -> 124.36924 | BR39: =CT39 -> 130.79 | BS39: =-(-CD39-AP39) -> 665 | BT39: =IF(CE39+AQ39<0, 0, CE39+AQ39) -> 256.5 | BU39: =CB39+CC39 -> 74.27 | BV39: =SUMIFS('SEGURO DE VIDA'!E:E, 'SEGURO DE VIDA'!D:D, H39, 'SEGURO DE VIDA'!G:G, E39) -> 13.71 | BW39: =SUMIFS(TREINAMENTOS!E:E, TREINAMENTOS!D:D, H39, TREINAMENTOS!G:G, E39) -> 0 | BX39: =SUMIFS(EXAMES!E:E, EXAMES!D:D, H39, EXAMES!G:G, E39) -> 0 | BY39: =SUM(BN39:BU39)+SUM(BV39:BX39) -> 1559.8059 | CA39: DANIEL ANCHIETA BRAZIEL PETZOL | CB39: =IF(SUM(BB39:BD39)+CF39<0, 0, SUM(BB39:BD39)+CF39) -> 74.27 | CC39: =IF(SUM(AV39:AW39)+CG39<0, 0, SUM(AV39:AW39)+CG39) -> 0 | CD39: =SUMIFS(ALIMENTAÇÃO!E:E, ALIMENTAÇÃO!D:D, H39, ALIMENTAÇÃO!G:G, E39) -> 665 | CE39: =SUMIFS(TRANSPORTE!E:E, TRANSPORTE!D:D, H39, TRANSPORTE!G:G, E39) -> 256.5 | CF39: =SUMIFS('PLANO DE SAÚDE'!E:E, 'PLANO DE SAÚDE'!D:D, H39, 'PLANO DE SAÚDE'!G:G, E39) -> 75.53 | CG39: =SUMIFS('PLANO ODONTO'!E:E, 'PLANO ODONTO'!D:D, H39, 'PLANO ODONTO'!G:G, E39) -> 14 | CH39: =BB39+BC39+BD39 -> -1.26 | CI39: =BI39+BJ39 -> 0 | CJ39: =AA39+AB39 -> 0 | CM39: =AV39+AW39 -> -14 | CN39: 1634.99 | CO39: -139.99 | CP39: 1495 | CQ39: 1634.91 | CR39: 7.6071 | CS39: 1634.91 | CT39: 130.79 | CU39: 1027.71
A40: =IFERROR(__xludf.DUMMYFUNCTION("""COMPUTED_VALUE"""),"CARLOS DA SILVA SANTOS") -> CARLOS DA SILVA SANTOS | C40: =IF(COUNTIF(A:A, H40)>0, "OK", "Incompleto") -> OK | D40: =AN40+BY40 -> 2789.3367 | E40: 45809 | F40: 07.391.921/0001-71 | G40: 3438 | H40: DANIEL DUARTE ALVES | I40: AUX. DE INSTALACAO DE R | J40: 45397 | K40: 1518 | M40: 1518 | O40: 0 | P40: 0 | T40: 0 | Y40: 0 | AA40: 0 | AB40: 0 | AD40: 0 | AE40: 0 | AF40: 0 | AJ40: 0 | AM40: 0.95 | AN40: =SUM(M40:AM40) -> 1518.95 | AP40: 0 | AQ40: -91.08 | AT40: -0.02 | AV40: 0 | AY40: 0 | BB40: 0 | BC40: 0 | BF40: 0 | BG40: -113.85 | BH40: 0 | BI40: 0 | BL40: =SUM(AO40:BK40) -> -204.95 | BM40: =AN40+BL40 -> 1314 | BN40: =K40/12*1 -> 126.5 | BO40: =K40/12*1 -> 126.5 | BP40: =BO40/3 -> 42.166667 | BQ40: =CQ40*CR40% -> 113.85 | BR40: =CT40 -> 121.44 | BS40: =-(-CD40-AP40) -> 595 | BT40: =IF(CE40+AQ40<0, 0, CE40+AQ40) -> 131.22 | BU40: =CB40+CC40 -> 0 | BV40: =SUMIFS('SEGURO DE VIDA'!E:E, 'SEGURO DE VIDA'!D:D, H40, 'SEGURO DE VIDA'!G:G, E40) -> 13.71 | BW40: =SUMIFS(TREINAMENTOS!E:E, TREINAMENTOS!D:D, H40, TREINAMENTOS!G:G, E40) -> 0 | BX40: =SUMIFS(EXAMES!E:E, EXAMES!D:D, H40, EXAMES!G:G, E40) -> 0 | BY40: =SUM(BN40:BU40)+SUM(BV40:BX40) -> 1270.3867 | CA40: DANIEL DUARTE ALVES | CB40: =IF(SUM(BB40:BD40)+CF40<0, 0, SUM(BB40:BD40)+CF40) -> 0 | CC40: =IF(SUM(AV40:AW40)+CG40<0, 0, SUM(AV40:AW40)+CG40) -> 0 | CD40: =SUMIFS(ALIMENTAÇÃO!E:E, ALIMENTAÇÃO!D:D, H40, ALIMENTAÇÃO!G:G, E40) -> 595 | CE40: =SUMIFS(TRANSPORTE!E:E, TRANSPORTE!D:D, H40, TRANSPORTE!G:G, E40) -> 222.3 | CF40: =SUMIFS('PLANO DE SAÚDE'!E:E, 'PLANO DE SAÚDE'!D:D, H40, 'PLANO DE SAÚDE'!G:G, E40) -> 0 | CG40: =SUMIFS('PLANO ODONTO'!E:E, 'PLANO ODONTO'!D:D, H40, 'PLANO ODONTO'!G:G, E40) -> 0 | CH40: =BB40+BC40+BD40 -> 0 | CI40: =BI40+BJ40 -> 0 | CJ40: =AA40+AB40 -> 0 | CM40: =AV40+AW40 -> 0 | CN40: 1518.95 | CO40: -204.95 | CP40: 1314 | CQ40: 1518 | CR40: 7.5 | CS40: 1518 | CT40: 121.44 | CU40: 910.8
A41: =IFERROR(__xludf.DUMMYFUNCTION("""COMPUTED_VALUE"""),"CARLOS EDUARDO DE MORAIS RODRIGUES JUNIOR") -> CARLOS EDUARDO DE MORAIS RODRIGUES JUNIOR | C41: =IF(COUNTIF(A:A, H41)>0, "OK", "Incompleto") -> OK | D41: =AN41+BY41 -> 1165.6433 | E41: 45809 | F41: 07.391.921/0001-71 | G41: 3555 | H41: DAVI VASCONCELLOS MACEDO | I41: ESTAGIARIO EM TELECOM | J41: 45831 | K41: 750 | M41: 200 | O41: 0 | P41: 0 | T41: 0 | Y41: 0 | AA41: 0 | AB41: 0 | AD41: 0 | AE41: 0 | AF41: 0 | AJ41: 0 | AM41: 0 | AN41: =SUM(M41:AM41) -> 200 | AP41: 0 | AQ41: 0 | AT41: 0 | AV41: 0 | AY41: 0 | BB41: 0 | BC41: 0 | BF41: 0 | BG41: 0 | BH41: 0 | BI41: 0 | BL41: =SUM(AO41:BK41) -> 0 | BM41: =AN41+BL41 -> 200 | BN41: =K41/12*1 -> 62.5 | BO41: =K41/12*1 -> 62.5 | BP41: =BO41/3 -> 20.833333 | BQ41: =CQ41*CR41% -> 0 | BR41: =CT41 -> 0 | BS41: =-(-CD41-AP41) -> 210 | BT41: =IF(CE41+AQ41<0, 0, CE41+AQ41) -> 65.8 | BU41: =CB41+CC41 -> 0 | BV41: =SUMIFS('SEGURO DE VIDA'!E:E, 'SEGURO DE VIDA'!D:D, H41, 'SEGURO DE VIDA'!G:G, E41) -> 0 | BW41: =SUMIFS(TREINAMENTOS!E:E, TREINAMENTOS!D:D, H41, TREINAMENTOS!G:G, E41) -> 0 | BX41: =SUMIFS(EXAMES!E:E, EXAMES!D:D, H41, EXAMES!G:G, E41) -> 544.01 | BY41: =SUM(BN41:BU41)+SUM(BV41:BX41) -> 965.64333 | CA41: DAVI VASCONCELLOS MACEDO | CB41: =IF(SUM(BB41:BD41)+CF41<0, 0, SUM(BB41:BD41)+CF41) -> 0 | CC41: =IF(SUM(AV41:AW41)+CG41<0, 0, SUM(AV41:AW41)+CG41) -> 0 | CD41: =SUMIFS(ALIMENTAÇÃO!E:E, ALIMENTAÇÃO!D:D, H41, ALIMENTAÇÃO!G:G, E41) -> 210 | CE41: =SUMIFS(TRANSPORTE!E:E, TRANSPORTE!D:D, H41, TRANSPORTE!G:G, E41) -> 65.8 | CF41: =SUMIFS('PLANO DE SAÚDE'!E:E, 'PLANO DE SAÚDE'!D:D, H41, 'PLANO DE SAÚDE'!G:G, E41) -> 0 | CG41: =SUMIFS('PLANO ODONTO'!E:E, 'PLANO ODONTO'!D:D, H41, 'PLANO ODONTO'!G:G, E41) -> 0 | CH41: =BB41+BC41+BD41 -> 0 | CI41: =BI41+BJ41 -> 0 | CJ41: =AA41+AB41 -> 0 | CM41: =AV41+AW41 -> 0 | CN41: 200 | CO41: 0 | CP41: 200 | CQ41: 0 | CR41: 0 | CS41: 0 | CT41: 0 | CU41: 0
A42: =IFERROR(__xludf.DUMMYFUNCTION("""COMPUTED_VALUE"""),"CARLOS EDUARDO SILVA DE SOUZA") -> CARLOS EDUARDO SILVA DE SOUZA | C42: =IF(COUNTIF(A:A, H42)>0, "OK", "Incompleto") -> OK | D42: =AN42+BY42 -> 3359.04 | E42: 45809 | F42: 07.391.921/0001-71 | G42: 352 | H42: DIEGO CARLOS DA SILVA SANTOS | I42: INSTALADOR JUNIOR | J42: 44746 | K42: 1800 | M42: 1800 | O42: 0 | P42: 0 | T42: 0 | Y42: 0 | AA42: 0 | AB42: 0 | AD42: 0 | AE42: 0 | AF42: 0 | AJ42: 65 | AM42: 0.2 | AN42: =SUM(M42:AM42) -> 1865.2 | AP42: 0 | AQ42: -108 | AT42: -0.97 | AV42: 0 | AY42: 0 | BB42: 0 | BC42: 0 | BF42: 0 | BG42: -139.23 | BH42: 0 | BI42: 0 | BL42: =SUM(AO42:BK42) -> -248.2 | BM42: =AN42+BL42 -> 1617 | BN42: =K42/12*1 -> 150 | BO42: =K42/12*1 -> 150 | BP42: =BO42/3 -> 50 | BQ42: =CQ42*CR42% -> 139.23 | BR42: =CT42 -> 144 | BS42: =-(-CD42-AP42) -> 630 | BT42: =IF(CE42+AQ42<0, 0, CE42+AQ42) -> 216.9 | BU42: =CB42+CC42 -> 0 | BV42: =SUMIFS('SEGURO DE VIDA'!E:E, 'SEGURO DE VIDA'!D:D, H42, 'SEGURO DE VIDA'!G:G, E42) -> 13.71 | BW42: =SUMIFS(TREINAMENTOS!E:E, TREINAMENTOS!D:D, H42, TREINAMENTOS!G:G, E42) -> 0 | BX42: =SUMIFS(EXAMES!E:E, EXAMES!D:D, H42, EXAMES!G:G, E42) -> 0 | BY42: =SUM(BN42:BU42)+SUM(BV42:BX42) -> 1493.84 | CA42: DIEGO CARLOS DA SILVA SANTOS | CB42: =IF(SUM(BB42:BD42)+CF42<0, 0, SUM(BB42:BD42)+CF42) -> 0 | CC42: =IF(SUM(AV42:AW42)+CG42<0, 0, SUM(AV42:AW42)+CG42) -> 0 | CD42: =SUMIFS(ALIMENTAÇÃO!E:E, ALIMENTAÇÃO!D:D, H42, ALIMENTAÇÃO!G:G, E42) -> 630 | CE42: =SUMIFS(TRANSPORTE!E:E, TRANSPORTE!D:D, H42, TRANSPORTE!G:G, E42) -> 324.9 | CF42: =SUMIFS('PLANO DE SAÚDE'!E:E, 'PLANO DE SAÚDE'!D:D, H42, 'PLANO DE SAÚDE'!G:G, E42) -> 0 | CG42: =SUMIFS('PLANO ODONTO'!E:E, 'PLANO ODONTO'!D:D, H42, 'PLANO ODONTO'!G:G, E42) -> 0 | CH42: =BB42+BC42+BD42 -> 0 | CI42: =BI42+BJ42 -> 0 | CJ42: =AA42+AB42 -> 0 | CM42: =AV42+AW42 -> 0 | CN42: 1865.2 | CO42: -248.2 | CP42: 1617 | CQ42: 1800 | CR42: 7.735 | CS42: 1800 | CT42: 144 | CU42: 1092
A43: =IFERROR(__xludf.DUMMYFUNCTION("""COMPUTED_VALUE"""),"CARLOS GOMES DA SILVA") -> CARLOS GOMES DA SILVA | C43: =IF(COUNTIF(A:A, H43)>0, "OK", "Incompleto") -> OK | D43: =AN43+BY43 -> 4718.7025 | E43: 45809 | F43: 20.258.413/0001-88 | G43: 10 | H43: DIEGO FERNANDES ALVES MARTINS | I43: ASSISTENTE COMERCIAL | J43: 43558 | K43: 3045.48 | L43: Férias | M43: 1928.8 | AC43: 597.69 | AD43: 0 | AE43: 0 | AF43: 88.55 | AM43: 0.17 | AN43: =SUM(M43:AM43) -> 2615.21 | AP43: -7.35 | AQ43: -182.73 | AR43: 0 | AT43: -0.98 | AV43: 0 | BB43: 0 | BC43: 0 | BD43: 0 | BG43: -258.86 | BH43: 0 | BL43: =SUM(AO43:BK43) -> -449.92 | BM43: =AN43+BL43 -> 2165.29 | BN43: =K43/12*1 -> 253.79 | BO43: =K43/12*1 -> 253.79 | BP43: =BO43/3 -> 84.596667 | BQ43: =CQ43*CR43% -> 258.8658 | BR43: =CT43 -> 243.63 | BS43: =-(-CD43-AP43) -> 727.65 | BT43: =IF(CE43+AQ43<0, 0, CE43+AQ43) -> 142.17 | BU43: =CB43+CC43 -> 120.41 | BV43: =SUMIFS('SEGURO DE VIDA'!E:E, 'SEGURO DE VIDA'!D:D, H43, 'SEGURO DE VIDA'!G:G, E43) -> 18.59 | BW43: =SUMIFS(TREINAMENTOS!E:E, TREINAMENTOS!D:D, H43, TREINAMENTOS!G:G, E43) -> 0 | BX43: =SUMIFS(EXAMES!E:E, EXAMES!D:D, H43, EXAMES!G:G, E43) -> 0 | BY43: =SUM(BN43:BU43)+SUM(BV43:BX43) -> 2103.4925 | CA43: DIEGO FERNANDES ALVES MARTIN | CB43: =IF(SUM(BB43:BD43)+CF43<0, 0, SUM(BB43:BD43)+CF43) -> 120.41 | CC43: =IF(SUM(AV43:AW43)+CG43<0, 0, SUM(AV43:AW43)+CG43) -> 0 | CD43: =SUMIFS(ALIMENTAÇÃO!E:E, ALIMENTAÇÃO!D:D, H43, ALIMENTAÇÃO!G:G, E43) -> 735 | CE43: =SUMIFS(TRANSPORTE!E:E, TRANSPORTE!D:D, H43, TRANSPORTE!G:G, E43) -> 324.9 | CF43: =SUMIFS('PLANO DE SAÚDE'!E:E, 'PLANO DE SAÚDE'!D:D, H43, 'PLANO DE SAÚDE'!G:G, E43) -> 120.41 | CG43: =SUMIFS('PLANO ODONTO'!E:E, 'PLANO ODONTO'!D:D, H43, 'PLANO ODONTO'!G:G, E43) -> 0 | CH43: =BB43+BC43+BD43 -> 0 | CI43: =BI43+BJ43 -> 0 | CJ43: =AA43+AB43 -> 0 | CM43: =AV43+AW43 -> 0 | CN43: 2615.21 | CO43: -449.92 | CP43: 2165.29 | CQ43: 3045.48 | CR43: 8.5 | CS43: 3045.48 | CT43: 243.63 | CU43: 2438.28
A44: =IFERROR(__xludf.DUMMYFUNCTION("""COMPUTED_VALUE"""),"CARLOS ROBERTO MESQUITA") -> CARLOS ROBERTO MESQUITA | C44: =IF(COUNTIF(A:A, H44)>0, "OK", "Incompleto") -> OK | D44: =AN44+BY44 -> 3462.31 | E44: 45809 | F44: 07.391.921/0001-71 | G44: 3358 | H44: DOUGLAS DE SOUZA PAULO | I44: INSTALADOR JUNIOR | J44: 45033 | K44: 1800 | M44: 1800 | O44: 0 | P44: 0 | T44: 0 | Y44: 0 | AA44: 0 | AB44: 0 | AD44: 0 | AE44: 0 | AF44: 0 | AJ44: 0 | AM44: 0.48 | AN44: =SUM(M44:AM44) -> 1800.48 | AP44: 0 | AQ44: -108 | AT44: -0.09 | AV44: -14 | AY44: 0 | BB44: -21.45 | BC44: -1.71 | BF44: 0 | BG44: -139.23 | BH44: 0 | BI44: 0 | BL44: =SUM(AO44:BK44) -> -284.48 | BM44: =AN44+BL44 -> 1516 | BN44: =K44/12*1 -> 150 | BO44: =K44/12*1 -> 150 | BP44: =BO44/3 -> 50 | BQ44: =CQ44*CR44% -> 139.23 | BR44: =CT44 -> 144 | BS44: =-(-CD44-AP44) -> 595 | BT44: =IF(CE44+AQ44<0, 0, CE44+AQ44) -> 216.9 | BU44: =CB44+CC44 -> 100.87 | BV44: =SUMIFS('SEGURO DE VIDA'!E:E, 'SEGURO DE VIDA'!D:D, H44, 'SEGURO DE VIDA'!G:G, E44) -> 13.71 | BW44: =SUMIFS(TREINAMENTOS!E:E, TREINAMENTOS!D:D, H44, TREINAMENTOS!G:G, E44) -> 0 | BX44: =SUMIFS(EXAMES!E:E, EXAMES!D:D, H44, EXAMES!G:G, E44) -> 102.12 | BY44: =SUM(BN44:BU44)+SUM(BV44:BX44) -> 1661.83 | CA44: DOUGLAS DE SOUZA PAULO | CB44: =IF(SUM(BB44:BD44)+CF44<0, 0, SUM(BB44:BD44)+CF44) -> 100.87 | CC44: =IF(SUM(AV44:AW44)+CG44<0, 0, SUM(AV44:AW44)+CG44) -> 0 | CD44: =SUMIFS(ALIMENTAÇÃO!E:E, ALIMENTAÇÃO!D:D, H44, ALIMENTAÇÃO!G:G, E44) -> 595 | CE44: =SUMIFS(TRANSPORTE!E:E, TRANSPORTE!D:D, H44, TRANSPORTE!G:G, E44) -> 324.9 | CF44: =SUMIFS('PLANO DE SAÚDE'!E:E, 'PLANO DE SAÚDE'!D:D, H44, 'PLANO DE SAÚDE'!G:G, E44) -> 124.03 | CG44: =SUMIFS('PLANO ODONTO'!E:E, 'PLANO ODONTO'!D:D, H44, 'PLANO ODONTO'!G:G, E44) -> 14 | CH44: =BB44+BC44+BD44 -> -23.16 | CI44: =BI44+BJ44 -> 0 | CJ44: =AA44+AB44 -> 0 | CM44: =AV44+AW44 -> -14 | CN44: 1800.48 | CO44: -284.48 | CP44: 1516 | CQ44: 1800 | CR44: 7.735 | CS44: 1800 | CT44: 144 | CU44: 1192.8
A45: =IFERROR(__xludf.DUMMYFUNCTION("""COMPUTED_VALUE"""),"CASSIANO FERREIRA MORAES") -> CASSIANO FERREIRA MORAES | C45: =IF(COUNTIF(A:A, H45)>0, "OK", "Incompleto") -> OK | D45: =AN45+BY45 -> 970.72451 | E45: 45809 | F45: 07.391.921/0001-71 | G45: 3357 | H45: EDILEI SANTOS SILVA | I45: INST REDES TELEMATICAS | J45: 45033 | K45: 2002.59 | L45: Férias | M45: 66.75 | O45: 0 | P45: 0 | T45: 0 | Y45: 0 | AA45: 0 | AB45: 0 | AD45: 0 | AE45: 0 | AF45: 0 | AJ45: 0 | AM45: 0.89 | AN45: =SUM(M45:AM45) -> 67.64 | AP45: 0 | AQ45: 0 | AT45: -0.63 | AV45: 0 | AY45: 0 | BB45: 0 | BC45: 0 | BF45: 0 | BG45: -8.01 | BH45: 0 | BI45: 0 | BL45: =SUM(AO45:BK45) -> -8.64 | BM45: =AN45+BL45 -> 59 | BN45: =K45/12*1 -> 166.8825 | BO45: =K45/12*1 -> 166.8825 | BP45: =BO45/3 -> 55.6275 | BQ45: =CQ45*CR45% -> 6.2520072 | BR45: =CT45 -> 5.34 | BS45: =-(-CD45-AP45) -> 0 | BT45: =IF(CE45+AQ45<0, 0, CE45+AQ45) -> 0 | BU45: =CB45+CC45 -> 488.39 | BV45: =SUMIFS('SEGURO DE VIDA'!E:E, 'SEGURO DE VIDA'!D:D, H45, 'SEGURO DE VIDA'!G:G, E45) -> 13.71 | BW45: =SUMIFS(TREINAMENTOS!E:E, TREINAMENTOS!D:D, H45, TREINAMENTOS!G:G, E45) -> 0 | BX45: =SUMIFS(EXAMES!E:E, EXAMES!D:D, H45, EXAMES!G:G, E45) -> 0 | BY45: =SUM(BN45:BU45)+SUM(BV45:BX45) -> 903.08451 | CA45: EDILEI SANTOS SILVA | CB45: =IF(SUM(BB45:BD45)+CF45<0, 0, SUM(BB45:BD45)+CF45) -> 488.39 | CC45: =IF(SUM(AV45:AW45)+CG45<0, 0, SUM(AV45:AW45)+CG45) -> 0 | CD45: =SUMIFS(ALIMENTAÇÃO!E:E, ALIMENTAÇÃO!D:D, H45, ALIMENTAÇÃO!G:G, E45) -> 0 | CE45: =SUMIFS(TRANSPORTE!E:E, TRANSPORTE!D:D, H45, TRANSPORTE!G:G, E45) -> 0 | CF45: =SUMIFS('PLANO DE SAÚDE'!E:E, 'PLANO DE SAÚDE'!D:D, H45, 'PLANO DE SAÚDE'!G:G, E45) -> 488.39 | CG45: =SUMIFS('PLANO ODONTO'!E:E, 'PLANO ODONTO'!D:D, H45, 'PLANO ODONTO'!G:G, E45) -> 0 | CH45: =BB45+BC45+BD45 -> 0 | CI45: =BI45+BJ45 -> 0 | CJ45: =AA45+AB45 -> 0 | CM45: =AV45+AW45 -> 0 | CN45: 67.64 | CO45: -8.64 | CP45: 59 | CQ45: 66.76 | CR45: 9.3649 | CS45: 66.75 | CT45: 5.34 | CU45: 0
A46: =IFERROR(__xludf.DUMMYFUNCTION("""COMPUTED_VALUE"""),"CAUÃ BARBOSA DE CARVALHO") -> CAUÃ BARBOSA DE CARVALHO | C46: =IF(COUNTIF(A:A, H46)>0, "OK", "Incompleto") -> OK | D46: =AN46+BY46 -> 5751.42 | E46: 45809 | F46: 07.391.921/0001-71 | G46: 3462 | H46: EDMILSON MENDES DE SOUZA | I46: TECNICO SEGURANÇA DO | J46: 45523 | K46: 2315.33 | M46: 2315.33 | O46: 0 | P46: 694.6 | T46: 0 | Y46: 0 | AA46: 0 | AB46: 0 | AD46: 541.79 | AE46: 0 | AF46: 135.45 | AJ46: 0 | AM46: 0.13 | AN46: =SUM(M46:AM46) -> 3687.3 | AP46: 0 | AQ46: -138.92 | AT46: -0.08 | AV46: 0 | AY46: 0 | BB46: 0 | BC46: -2.01 | BF46: -679.59 | BG46: -335.86 | BH46: -67.84 | BI46: 0 | BL46: =SUM(AO46:BK46) -> -1224.3 | BM46: =AN46+BL46 -> 2463 | BN46: =K46/12*1 -> 192.94417 | BO46: =K46/12*1 -> 192.94417 | BP46: =BO46/3 -> 64.314722 | BQ46: =CQ46*CR46% -> 335.85694 | BR46: =CT46 -> 294.97 | BS46: =-(-CD46-AP46) -> 665 | BT46: =IF(CE46+AQ46<0, 0, CE46+AQ46) -> 185.98 | BU46: =CB46+CC46 -> 118.4 | BV46: =SUMIFS('SEGURO DE VIDA'!E:E, 'SEGURO DE VIDA'!D:D, H46, 'SEGURO DE VIDA'!G:G, E46) -> 13.71 | BW46: =SUMIFS(TREINAMENTOS!E:E, TREINAMENTOS!D:D, H46, TREINAMENTOS!G:G, E46) -> 0 | BX46: =SUMIFS(EXAMES!E:E, EXAMES!D:D, H46, EXAMES!G:G, E46) -> 0 | BY46: =SUM(BN46:BU46)+SUM(BV46:BX46) -> 2064.12 | CA46: EDMILSON MENDES DE SOUZA | CB46: =IF(SUM(BB46:BD46)+CF46<0, 0, SUM(BB46:BD46)+CF46) -> 118.4 | CC46: =IF(SUM(AV46:AW46)+CG46<0, 0, SUM(AV46:AW46)+CG46) -> 0 | CD46: =SUMIFS(ALIMENTAÇÃO!E:E, ALIMENTAÇÃO!D:D, H46, ALIMENTAÇÃO!G:G, E46) -> 665 | CE46: =SUMIFS(TRANSPORTE!E:E, TRANSPORTE!D:D, H46, TRANSPORTE!G:G, E46) -> 324.9 | CF46: =SUMIFS('PLANO DE SAÚDE'!E:E, 'PLANO DE SAÚDE'!D:D, H46, 'PLANO DE SAÚDE'!G:G, E46) -> 120.41 | CG46: =SUMIFS('PLANO ODONTO'!E:E, 'PLANO ODONTO'!D:D, H46, 'PLANO ODONTO'!G:G, E46) -> 0 | CH46: =BB46+BC46+BD46 -> -2.01 | CI46: =BI46+BJ46 -> 0 | CJ46: =AA46+AB46 -> 0 | CM46: =AV46+AW46 -> 0 | CN46: 3687.3 | CO46: -1224.3 | CP46: 2463 | CQ46: 3687.17 | CR46: 9.1088 | CS46: 3687.17 | CT46: 294.97 | CU46: 3079.97
A47: =IFERROR(__xludf.DUMMYFUNCTION("""COMPUTED_VALUE"""),"CAUÃ DE FREITAS LEITE") -> CAUÃ DE FREITAS LEITE | C47: =IF(COUNTIF(A:A, H47)>0, "OK", "Incompleto") -> OK | D47: =AN47+BY47 -> 3919.3597 | E47: 45809 | F47: 07.391.921/0001-71 | G47: 3475 | H47: EDRIZIO SANTANA DA SILVA | I47: INSTALADOR PLENO | J47: 45587 | K47: 1980 | M47: 1980 | P47: 303.6 | Q47: 0 | T47: 0 | Y47: 0 | Z47: 0 | AB47: 0 | AD47: 0 | AE47: 0 | AF47: 0 | AJ47: 0 | AM47: 0.52 | AN47: =SUM(M47:AM47) -> 2284.12 | AP47: 0 | AQ47: -118.8 | AT47: -0.4 | AV47: -14 | AW47: 0 | BB47: 0 | BC47: 0 | BD47: 0 | BF47: 0 | BG47: -182.75 | BH47: 0 | BI47: -420.17 | BL47: =SUM(AO47:BK47) -> -736.12 | BM47: =AN47+BL47 -> 1548 | BN47: =K47/12*1 -> 165 | BO47: =K47/12*1 -> 165 | BP47: =BO47/3 -> 55 | BQ47: =CQ47*CR47% -> 182.74966 | BR47: =CT47 -> 182.68 | BS47: =-(-CD47-AP47) -> 665 | BT47: =IF(CE47+AQ47<0, 0, CE47+AQ47) -> 206.1 | BU47: =CB47+CC47 -> 0 | BV47: =SUMIFS('SEGURO DE VIDA'!E:E, 'SEGURO DE VIDA'!D:D, H47, 'SEGURO DE VIDA'!G:G, E47) -> 13.71 | BW47: =SUMIFS(TREINAMENTOS!E:E, TREINAMENTOS!D:D, H47, TREINAMENTOS!G:G, E47) -> 0 | BX47: =SUMIFS(EXAMES!E:E, EXAMES!D:D, H47, EXAMES!G:G, E47) -> 0 | BY47: =SUM(BN47:BU47)+SUM(BV47:BX47) -> 1635.2397 | CA47: EDRIZIO SANTANA DA SILVA | CB47: =IF(SUM(BB47:BD47)+CF47<0, 0, SUM(BB47:BD47)+CF47) -> 0 | CC47: =IF(SUM(AV47:AW47)+CG47<0, 0, SUM(AV47:AW47)+CG47) -> 0 | CD47: =SUMIFS(ALIMENTAÇÃO!E:E, ALIMENTAÇÃO!D:D, H47, ALIMENTAÇÃO!G:G, E47) -> 665 | CE47: =SUMIFS(TRANSPORTE!E:E, TRANSPORTE!D:D, H47, TRANSPORTE!G:G, E47) -> 324.9 | CF47: =SUMIFS('PLANO DE SAÚDE'!E:E, 'PLANO DE SAÚDE'!D:D, H47, 'PLANO DE SAÚDE'!G:G, E47) -> 0 | CG47: =SUMIFS('PLANO ODONTO'!E:E, 'PLANO ODONTO'!D:D, H47, 'PLANO ODONTO'!G:G, E47) -> 14 | CH47: =BB47+BC47+BD47 -> 0 | CI47: =BI47+BJ47 -> -420.17 | CJ47: =AA47+AB47 -> 0 | CM47: =AV47+AW47 -> -14 | CN47: 2284.12 | CO47: -736.12 | CP47: 1548 | CQ47: 2283.6 | CR47: 8.0027 | CS47: 2283.6 | CT47: 182.68 | CU47: 1676.4
A48: =IFERROR(__xludf.DUMMYFUNCTION("""COMPUTED_VALUE"""),"CAUA VIEIRA LORENCINI ZANONI") -> CAUA VIEIRA LORENCINI ZANONI | C48: =IF(COUNTIF(A:A, H48)>0, "OK", "Incompleto") -> OK | D48: =AN48+BY48 -> 6564.409 | E48: 45809 | F48: 07.391.921/0001-71 | G48: 137 | H48: EDUARDO FERREIRA DA MOTTA | I48: TECNICO DE TELECOMUNI | J48: 41962 | K48: 3159.37 | M48: 3159.37 | P48: 0 | Q48: 0 | T48: 0 | Y48: 0 | Z48: 1263.75 | AB48: 0 | AD48: 0 | AE48: 0 | AF48: 0 | AJ48: 0 | AM48: 0.26 | AN48: =SUM(M48:AM48) -> 4423.38 | AP48: 0 | AQ48: -189.56 | AS48: 0 | AT48: -0.13 | AV48: -14 | AW48: -14 | BA48: -39.05 | BB48: -122.7 | BC48: -478.7 | BD48: -170.96 | BF48: -1041.37 | BG48: -428.82 | BH48: -183.09 | BI48: 0 | BL48: =SUM(AO48:BK48) -> -2682.38 | BM48: =AN48+BL48 -> 1741 | BN48: =K48/12*1 -> 263.28083 | BO48: =K48/12*1 -> 263.28083 | BP48: =BO48/3 -> 87.760278 | BQ48: =CQ48*CR48% -> 428.81706 | BR48: =CT48 -> 353.84 | BS48: =-(-CD48-AP48) -> 595 | BT48: =IF(CE48+AQ48<0, 0, CE48+AQ48) -> 135.34 | BU48: =CB48+CC48 -> 0 | BV48: =SUMIFS('SEGURO DE VIDA'!E:E, 'SEGURO DE VIDA'!D:D, H48, 'SEGURO DE VIDA'!G:G, E48) -> 13.71 | BW48: =SUMIFS(TREINAMENTOS!E:E, TREINAMENTOS!D:D, H48, TREINAMENTOS!G:G, E48) -> 0 | BX48: =SUMIFS(EXAMES!E:E, EXAMES!D:D, H48, EXAMES!G:G, E48) -> 0 | BY48: =SUM(BN48:BU48)+SUM(BV48:BX48) -> 2141.029 | CA48: EDUARDO FERREIRA DA MOTTA | CB48: =IF(SUM(BB48:BD48)+CF48<0, 0, SUM(BB48:BD48)+CF48) -> 0 | CC48: =IF(SUM(AV48:AW48)+CG48<0, 0, SUM(AV48:AW48)+CG48) -> 0 | CD48: =SUMIFS(ALIMENTAÇÃO!E:E, ALIMENTAÇÃO!D:D, H48, ALIMENTAÇÃO!G:G, E48) -> 595 | CE48: =SUMIFS(TRANSPORTE!E:E, TRANSPORTE!D:D, H48, TRANSPORTE!G:G, E48) -> 324.9 | CF48: =SUMIFS('PLANO DE SAÚDE'!E:E, 'PLANO DE SAÚDE'!D:D, H48, 'PLANO DE SAÚDE'!G:G, E48) -> 677.51 | CG48: =SUMIFS('PLANO ODONTO'!E:E, 'PLANO ODONTO'!D:D, H48, 'PLANO ODONTO'!G:G, E48) -> 28 | CH48: =BB48+BC48+BD48 -> -772.36 | CI48: =BI48+BJ48 -> 0 | CJ48: =AA48+AB48 -> 0 | CM48: =AV48+AW48 -> -28 | CN48: 4423.38 | CO48: -2682.38 | CP48: 1741 | CQ48: 4423.12 | CR48: 9.6949 | CS48: 4423.12 | CT48: 353.84 | CU48: 3815.92
A49: =IFERROR(__xludf.DUMMYFUNCTION("""COMPUTED_VALUE"""),"CLARA GABRIELLE NASCIMENTO FIEL") -> CLARA GABRIELLE NASCIMENTO FIEL | C49: =IF(COUNTIF(A:A, H49)>0, "OK", "Incompleto") -> OK | D49: =AN49+BY49 -> 5235.4545 | E49: 45809 | F49: 07.391.921/0001-71 | G49: 3432 | H49: EDUARDO MENDES AVILA | I49: TECNICO DE MANUTENCAC | J49: 45362 | K49: 2636.11 | M49: 2636.11 | P49: 790.83 | Q49: 0 | T49: 0 | Y49: 0 | Z49: 0 | AB49: 0 | AD49: 0 | AE49: 0 | AF49: 0 | AJ49: 0 | AM49: 0.33 | AN49: =SUM(M49:AM49) -> 3427.27 | AP49: 0 | AQ49: 0 | AS49: -120.04 | AT49: 0 | AV49: -14 | AW49: -14 | BA49: 0 | BB49: -41.58 | BC49: -2.01 | BD49: -200.69 | BF49: 0 | BG49: -304.63 | BH49: -29.32 | BI49: 0 | BL49: =SUM(AO49:BK49) -> -726.27 | BM49: =AN49+BL49 -> 2701 | BN49: =K49/12*1 -> 219.67583 | BO49: =K49/12*1 -> 219.67583 | BP49: =BO49/3 -> 73.225278 | BQ49: =CQ49*CR49% -> 304.62755 | BR49: =CT49 -> 274.15 | BS49: =-(-CD49-AP49) -> 665 | BT49: =IF(CE49+AQ49<0, 0, CE49+AQ49) -> 0 | BU49: =CB49+CC49 -> 38.12 | BV49: =SUMIFS('SEGURO DE VIDA'!E:E, 'SEGURO DE VIDA'!D:D, H49, 'SEGURO DE VIDA'!G:G, E49) -> 13.71 | BW49: =SUMIFS(TREINAMENTOS!E:E, TREINAMENTOS!D:D, H49, TREINAMENTOS!G:G, E49) -> 0 | BX49: =SUMIFS(EXAMES!E:E, EXAMES!D:D, H49, EXAMES!G:G, E49) -> 0 | BY49: =SUM(BN49:BU49)+SUM(BV49:BX49) -> 1808.1845 | CA49: EDUARDO MENDES ÁVILA | CB49: =IF(SUM(BB49:BD49)+CF49<0, 0, SUM(BB49:BD49)+CF49) -> 38.12 | CC49: =IF(SUM(AV49:AW49)+CG49<0, 0, SUM(AV49:AW49)+CG49) -> 0 | CD49: =SUMIFS(ALIMENTAÇÃO!E:E, ALIMENTAÇÃO!D:D, H49, ALIMENTAÇÃO!G:G, E49) -> 665 | CE49: =SUMIFS(TRANSPORTE!E:E, TRANSPORTE!D:D, H49, TRANSPORTE!G:G, E49) -> 0 | CF49: =SUMIFS('PLANO DE SAÚDE'!E:E, 'PLANO DE SAÚDE'!D:D, H49, 'PLANO DE SAÚDE'!G:G, E49) -> 282.4 | CG49: =SUMIFS('PLANO ODONTO'!E:E, 'PLANO ODONTO'!D:D, H49, 'PLANO ODONTO'!G:G, E49) -> 28 | CH49: =BB49+BC49+BD49 -> -244.28 | CI49: =BI49+BJ49 -> 0 | CJ49: =AA49+AB49 -> 0 | CM49: =AV49+AW49 -> -28 | CN49: 3427.27 | CO49: -726.27 | CP49: 2701 | CQ49: 3426.94 | CR49: 8.8892 | CS49: 3426.94 | CT49: 274.15 | CU49: 2819.74
A50: =IFERROR(__xludf.DUMMYFUNCTION("""COMPUTED_VALUE"""),"CLERISTON CLEDSON GOMES DA SILVA") -> CLERISTON CLEDSON GOMES DA SILVA | C50: =IF(COUNTIF(A:A, H50)>0, "OK", "Incompleto") -> OK | D50: =AN50+BY50 -> 6824.2402 | E50: 45809 | F50: 07.391.921/0001-71 | G50: 3525 | H50: EMERSON ADAUTO DA SILVA | I50: COORDENADOR DE TELEC | J50: 45754 | K50: 4336.05 | M50: 4336.05 | P50: 0 | Q50: 0 | T50: 0 | Y50: 0 | Z50: 0 | AB50: 0 | AD50: 0 | AE50: 0 | AF50: 0 | AJ50: 0 | AM50: 0.15 | AN50: =SUM(M50:AM50) -> 4336.2 | AP50: 0 | AQ50: 0 | AT50: -0.79 | AV50: 0 | AW50: 0 | BB50: 0 | BC50: -94.61 | BD50: 0 | BF50: 0 | BG50: -416.63 | BH50: -165.17 | BI50: 0 | BL50: =SUM(AO50:BK50) -> -677.2 | BM50: =AN50+BL50 -> 3659 | BN50: =K50/12*1 -> 361.3375 | BO50: =K50/12*1 -> 361.3375 | BP50: =BO50/3 -> 120.44583 | BQ50: =CQ50*CR50% -> 416.62936 | BR50: =CT50 -> 346.88 | BS50: =-(-CD50-AP50) -> 665 | BT50: =IF(CE50+AQ50<0, 0, CE50+AQ50) -> 0 | BU50: =CB50+CC50 -> 202.7 | BV50: =SUMIFS('SEGURO DE VIDA'!E:E, 'SEGURO DE VIDA'!D:D, H50, 'SEGURO DE VIDA'!G:G, E50) -> 13.71 | BW50: =SUMIFS(TREINAMENTOS!E:E, TREINAMENTOS!D:D, H50, TREINAMENTOS!G:G, E50) -> 0 | BX50: =SUMIFS(EXAMES!E:E, EXAMES!D:D, H50, EXAMES!G:G, E50) -> 0 | BY50: =SUM(BN50:BU50)+SUM(BV50:BX50) -> 2488.0402 | CA50: EMERSON ADAUTO DA SILVA | CB50: =IF(SUM(BB50:BD50)+CF50<0, 0, SUM(BB50:BD50)+CF50) -> 202.7 | CC50: =IF(SUM(AV50:AW50)+CG50<0, 0, SUM(AV50:AW50)+CG50) -> 0 | CD50: =SUMIFS(ALIMENTAÇÃO!E:E, ALIMENTAÇÃO!D:D, H50, ALIMENTAÇÃO!G:G, E50) -> 665 | CE50: =SUMIFS(TRANSPORTE!E:E, TRANSPORTE!D:D, H50, TRANSPORTE!G:G, E50) -> 0 | CF50: =SUMIFS('PLANO DE SAÚDE'!E:E, 'PLANO DE SAÚDE'!D:D, H50, 'PLANO DE SAÚDE'!G:G, E50) -> 297.31 | CG50: =SUMIFS('PLANO ODONTO'!E:E, 'PLANO ODONTO'!D:D, H50, 'PLANO ODONTO'!G:G, E50) -> 0 | CH50: =BB50+BC50+BD50 -> -94.61 | CI50: =BI50+BJ50 -> 0 | CJ50: =AA50+AB50 -> 0 | CM50: =AV50+AW50 -> 0 | CN50: 4336.2 | CO50: -677.2 | CP50: 3659 | CQ50: 4336.05 | CR50: 9.6085 | CS50: 4336.05 | CT50: 346.88 | CU50: 3728.85
A51: =IFERROR(__xludf.DUMMYFUNCTION("""COMPUTED_VALUE"""),"CLEVERSON BHERING CLARE JUNIOR") -> CLEVERSON BHERING CLARE JUNIOR | C51: =IF(COUNTIF(A:A, H51)>0, "OK", "Incompleto") -> OK | D51: =AN51+BY51 -> 8050.0948 | E51: 45809 | F51: 07.391.921/0001-71 | G51: 355 | H51: EMERSON DA SILVA GOMES | I51: ANALISTA DE SISTEMAS | J51: 44774 | K51: 4057.59 | L51: Atestado | M51: 4057.59 | P51: 1217.28 | Q51: 0 | T51: 0 | Y51: 0 | Z51: 0 | AB51: 0 | AD51: 0 | AE51: 0 | AF51: 0 | AJ51: 0 | AM51: 0.58 | AN51: =SUM(M51:AM51) -> 5275.45 | AP51: 0 | AQ51: 0 | AT51: -0.48 | AV51: 0 | AW51: 0 | BB51: -66.62 | BC51: -34.56 | BD51: 0 | BF51: 0 | BG51: -548.06 | BH51: -302.73 | BI51: 0 | BL51: =SUM(AO51:BK51) -> -952.45 | BM51: =AN51+BL51 -> 4323 | BN51: =K51/12*1 -> 338.1325 | BO51: =K51/12*1 -> 338.1325 | BP51: =BO51/3 -> 112.71083 | BQ51: =CQ51*CR51% -> 548.05899 | BR51: =CT51 -> 421.98 | BS51: =-(-CD51-AP51) -> 665 | BT51: =IF(CE51+AQ51<0, 0, CE51+AQ51) -> 0 | BU51: =CB51+CC51 -> 336.92 | BV51: =SUMIFS('SEGURO DE VIDA'!E:E, 'SEGURO DE VIDA'!D:D, H51, 'SEGURO DE VIDA'!G:G, E51) -> 13.71 | BW51: =SUMIFS(TREINAMENTOS!E:E, TREINAMENTOS!D:D, H51, TREINAMENTOS!G:G, E51) -> 0 | BX51: =SUMIFS(EXAMES!E:E, EXAMES!D:D, H51, EXAMES!G:G, E51) -> 0 | BY51: =SUM(BN51:BU51)+SUM(BV51:BX51) -> 2774.6448 | CA51: EMERSON DA SILVA GOMES | CB51: =IF(SUM(BB51:BD51)+CF51<0, 0, SUM(BB51:BD51)+CF51) -> 336.92 | CC51: =IF(SUM(AV51:AW51)+CG51<0, 0, SUM(AV51:AW51)+CG51) -> 0 | CD51: =SUMIFS(ALIMENTAÇÃO!E:E, ALIMENTAÇÃO!D:D, H51, ALIMENTAÇÃO!G:G, E51) -> 665 | CE51: =SUMIFS(TRANSPORTE!E:E, TRANSPORTE!D:D, H51, TRANSPORTE!G:G, E51) -> 0 | CF51: =SUMIFS('PLANO DE SAÚDE'!E:E, 'PLANO DE SAÚDE'!D:D, H51, 'PLANO DE SAÚDE'!G:G, E51) -> 438.1 | CG51: =SUMIFS('PLANO ODONTO'!E:E, 'PLANO ODONTO'!D:D, H51, 'PLANO ODONTO'!G:G, E51) -> 0 | CH51: =BB51+BC51+BD51 -> -101.18 | CI51: =BI51+BJ51 -> 0 | CJ51: =AA51+AB51 -> 0 | CM51: =AV51+AW51 -> 0 | CN51: 5275.45 | CO51: -952.45 | CP51: 4323 | CQ51: 5274.87 | CR51: 10.39 | CS51: 5274.87 | CT51: 421.98 | CU51: 4347.63
A52: =IFERROR(__xludf.DUMMYFUNCTION("""COMPUTED_VALUE"""),"DANIEL ANCHIETA BRAZIEL PETZOLD") -> DANIEL ANCHIETA BRAZIEL PETZOLD | C52: =IF(COUNTIF(A:A, H52)>0, "OK", "Incompleto") -> OK | D52: =AN52+BY52 -> 1511.8433 | E52: 45809 | F52: 07.391.921/0001-71 | G52: 3517 | H52: EMILLY VITORIA CABRAL DANTAS | I52: ESTAGIÁRIO (A) TEC SEG T | J52: 45733 | K52: 750 | M52: 750 | P52: 0 | Q52: 0 | T52: 0 | Y52: 0 | Z52: 0 | AB52: 0 | AD52: 0 | AE52: 0 | AF52: 0 | AJ52: 0 | AM52: 0.4 | AN52: =SUM(M52:AM52) -> 750.4 | AP52: 0 | AQ52: 0 | AT52: -0.4 | AV52: -14 | AW52: 0 | BB52: 0 | BC52: 0 | BD52: 0 | BF52: 0 | BG52: 0 | BH52: 0 | BI52: 0 | BL52: =SUM(AO52:BK52) -> -14.4 | BM52: =AN52+BL52 -> 736 | BN52: =K52/12*1 -> 62.5 | BO52: =K52/12*1 -> 62.5 | BP52: =BO52/3 -> 20.833333 | BQ52: =CQ52*CR52% -> 0 | BR52: =CT52 -> 0 | BS52: =-(-CD52-AP52) -> 450 | BT52: =IF(CE52+AQ52<0, 0, CE52+AQ52) -> 151.9 | BU52: =CB52+CC52 -> 0 | BV52: =SUMIFS('SEGURO DE VIDA'!E:E, 'SEGURO DE VIDA'!D:D, H52, 'SEGURO DE VIDA'!G:G, E52) -> 13.71 | BW52: =SUMIFS(TREINAMENTOS!E:E, TREINAMENTOS!D:D, H52, TREINAMENTOS!G:G, E52) -> 0 | BX52: =SUMIFS(EXAMES!E:E, EXAMES!D:D, H52, EXAMES!G:G, E52) -> 0 | BY52: =SUM(BN52:BU52)+SUM(BV52:BX52) -> 761.44333 | CA52: EMILLY VITORIA CABRAL DANTAS | CB52: =IF(SUM(BB52:BD52)+CF52<0, 0, SUM(BB52:BD52)+CF52) -> 0 | CC52: =IF(SUM(AV52:AW52)+CG52<0, 0, SUM(AV52:AW52)+CG52) -> 0 | CD52: =SUMIFS(ALIMENTAÇÃO!E:E, ALIMENTAÇÃO!D:D, H52, ALIMENTAÇÃO!G:G, E52) -> 450 | CE52: =SUMIFS(TRANSPORTE!E:E, TRANSPORTE!D:D, H52, TRANSPORTE!G:G, E52) -> 151.9 | CF52: =SUMIFS('PLANO DE SAÚDE'!E:E, 'PLANO DE SAÚDE'!D:D, H52, 'PLANO DE SAÚDE'!G:G, E52) -> 0 | CG52: =SUMIFS('PLANO ODONTO'!E:E, 'PLANO ODONTO'!D:D, H52, 'PLANO ODONTO'!G:G, E52) -> 14 | CH52: =BB52+BC52+BD52 -> 0 | CI52: =BI52+BJ52 -> 0 | CJ52: =AA52+AB52 -> 0 | CM52: =AV52+AW52 -> -14 | CN52: 750.4 | CO52: -14.4 | CP52: 736 | CQ52: 0 | CR52: 0 | CS52: 0 | CT52: 0 | CU52: 142.8
A53: =IFERROR(__xludf.DUMMYFUNCTION("""COMPUTED_VALUE"""),"DANIEL DUARTE ALVES") -> DANIEL DUARTE ALVES | C53: =IF(COUNTIF(A:A, H53)>0, "OK", "Incompleto") -> OK | D53: =AN53+BY53 -> 3812.9292 | E53: 45809 | F53: 07.391.921/0001-71 | G53: 3530 | H53: ENZO ALCÂNTARA CABRAL | I53: Operador de Audio e Video | J53: 45782 | K53: 2239.36 | M53: 2239.36 | P53: 0 | Q53: 0 | T53: 0 | Y53: 0 | Z53: 0 | AB53: 0 | AD53: 0 | AE53: 0 | AF53: 0 | AJ53: 0 | AM53: 0.65 | AN53: =SUM(M53:AM53) -> 2240.01 | AP53: 0 | AQ53: 0 | AT53: -0.53 | AV53: 0 | AW53: 0 | BB53: 0 | BC53: -1.71 | BD53: 0 | BF53: 0 | BG53: -178.77 | BH53: 0 | BI53: 0 | BL53: =SUM(AO53:BK53) -> -181.01 | BM53: =AN53+BL53 -> 2059 | BN53: =K53/12*1 -> 186.61333 | BO53: =K53/12*1 -> 186.61333 | BP53: =BO53/3 -> 62.204444 | BQ53: =CQ53*CR53% -> 178.76811 | BR53: =CT53 -> 179.14 | BS53: =-(-CD53-AP53) -> 665 | BT53: =IF(CE53+AQ53<0, 0, CE53+AQ53) -> 0 | BU53: =CB53+CC53 -> 100.87 | BV53: =SUMIFS('SEGURO DE VIDA'!E:E, 'SEGURO DE VIDA'!D:D, H53, 'SEGURO DE VIDA'!G:G, E53) -> 13.71 | BW53: =SUMIFS(TREINAMENTOS!E:E, TREINAMENTOS!D:D, H53, TREINAMENTOS!G:G, E53) -> 0 | BX53: =SUMIFS(EXAMES!E:E, EXAMES!D:D, H53, EXAMES!G:G, E53) -> 0 | BY53: =SUM(BN53:BU53)+SUM(BV53:BX53) -> 1572.9192 | CA53: ENZO ALCANTARA CABRAL | CB53: =IF(SUM(BB53:BD53)+CF53<0, 0, SUM(BB53:BD53)+CF53) -> 100.87 | CC53: =IF(SUM(AV53:AW53)+CG53<0, 0, SUM(AV53:AW53)+CG53) -> 0 | CD53: =SUMIFS(ALIMENTAÇÃO!E:E, ALIMENTAÇÃO!D:D, H53, ALIMENTAÇÃO!G:G, E53) -> 665 | CE53: =SUMIFS(TRANSPORTE!E:E, TRANSPORTE!D:D, H53, TRANSPORTE!G:G, E53) -> 0 | CF53: =SUMIFS('PLANO DE SAÚDE'!E:E, 'PLANO DE SAÚDE'!D:D, H53, 'PLANO DE SAÚDE'!G:G, E53) -> 102.58 | CG53: =SUMIFS('PLANO ODONTO'!E:E, 'PLANO ODONTO'!D:D, H53, 'PLANO ODONTO'!G:G, E53) -> 0 | CH53: =BB53+BC53+BD53 -> -1.71 | CI53: =BI53+BJ53 -> 0 | CJ53: =AA53+AB53 -> 0 | CM53: =AV53+AW53 -> 0 | CN53: 2240.01 | CO53: -181.01 | CP53: 2059 | CQ53: 2239.36 | CR53: 7.983 | CS53: 2239.36 | CT53: 179.14 | CU53: 1632.16
A54: =IFERROR(__xludf.DUMMYFUNCTION("""COMPUTED_VALUE"""),"DANIEL VICTOR TEODORO MOREIRA") -> DANIEL VICTOR TEODORO MOREIRA | C54: =IF(COUNTIF(A:A, H54)>0, "OK", "Incompleto") -> OK | D54: =AN54+BY54 -> 4137.4192 | E54: 45809 | F54: 07.391.921/0001-71 | G54: 3535 | H54: ESTHER VICTÓRIA DOS SANTOS FARIA | I54: Operador de Audio e Video | J54: 45789 | K54: 2239.36 | M54: 2239.36 | P54: 0 | Q54: 0 | T54: 0 | Y54: 0 | Z54: 0 | AB54: 0 | AD54: 0 | AE54: 0 | AF54: 0 | AJ54: 0 | AM54: 0.98 | AN54: =SUM(M54:AM54) -> 2240.34 | AP54: 0 | AQ54: -134.36 | AT54: -0.2 | AV54: -14 | AW54: 0 | BB54: 0 | BC54: -2.01 | BD54: 0 | BF54: 0 | BG54: -178.77 | BH54: 0 | BI54: 0 | BL54: =SUM(AO54:BK54) -> -329.34 | BM54: =AN54+BL54 -> 1911 | BN54: =K54/12*1 -> 186.61333 | BO54: =K54/12*1 -> 186.61333 | BP54: =BO54/3 -> 62.204444 | BQ54: =CQ54*CR54% -> 178.76811 | BR54: =CT54 -> 179.14 | BS54: =-(-CD54-AP54) -> 665 | BT54: =IF(CE54+AQ54<0, 0, CE54+AQ54) -> 190.54 | BU54: =CB54+CC54 -> 234.49 | BV54: =SUMIFS('SEGURO DE VIDA'!E:E, 'SEGURO DE VIDA'!D:D, H54, 'SEGURO DE VIDA'!G:G, E54) -> 13.71 | BW54: =SUMIFS(TREINAMENTOS!E:E, TREINAMENTOS!D:D, H54, TREINAMENTOS!G:G, E54) -> 0 | BX54: =SUMIFS(EXAMES!E:E, EXAMES!D:D, H54, EXAMES!G:G, E54) -> 0 | BY54: =SUM(BN54:BU54)+SUM(BV54:BX54) -> 1897.0792 | CA54: ESTHER VICTORIA DOS SANTOS FA | CB54: =IF(SUM(BB54:BD54)+CF54<0, 0, SUM(BB54:BD54)+CF54) -> 221.9 | CC54: =IF(SUM(AV54:AW54)+CG54<0, 0, SUM(AV54:AW54)+CG54) -> 12.59 | CD54: =SUMIFS(ALIMENTAÇÃO!E:E, ALIMENTAÇÃO!D:D, H54, ALIMENTAÇÃO!G:G, E54) -> 665 | CE54: =SUMIFS(TRANSPORTE!E:E, TRANSPORTE!D:D, H54, TRANSPORTE!G:G, E54) -> 324.9 | CF54: =SUMIFS('PLANO DE SAÚDE'!E:E, 'PLANO DE SAÚDE'!D:D, H54, 'PLANO DE SAÚDE'!G:G, E54) -> 223.91 | CG54: =SUMIFS('PLANO ODONTO'!E:E, 'PLANO ODONTO'!D:D, H54, 'PLANO ODONTO'!G:G, E54) -> 26.59 | CH54: =BB54+BC54+BD54 -> -2.01 | CI54: =BI54+BJ54 -> 0 | CJ54: =AA54+AB54 -> 0 | CM54: =AV54+AW54 -> -14 | CN54: 2240.34 | CO54: -329.34 | CP54: 1911 | CQ54: 2239.36 | CR54: 7.983 | CS54: 2239.36 | CT54: 179.14 | CU54: 1632.16
A55: =IFERROR(__xludf.DUMMYFUNCTION("""COMPUTED_VALUE"""),"DAVI DOUGLAS BATISTA DOS SANTOS") -> DAVI DOUGLAS BATISTA DOS SANTOS | C55: =IF(COUNTIF(A:A, H55)>0, "OK", "Incompleto") -> OK | D55: =AN55+BY55 -> 9475.2387 | E55: 45809 | F55: 07.391.921/0001-71 | G55: 375 | H55: FABIANO DE OLIVEIRA MACHADO | I55: COORDENADOR DE SERVI | J55: 44928 | K55: 5336.03 | M55: 5336.03 | P55: 0 | Q55: 0 | T55: 0 | Y55: 0 | Z55: 0 | AB55: 0 | AD55: 0 | AE55: 0 | AF55: 0 | AJ55: 0 | AM55: 0.77 | AN55: =SUM(M55:AM55) -> 5336.8 | AP55: -13.65 | AQ55: -243 | AT55: -0.83 | AV55: -14 | AW55: -14 | BB55: 0 | BC55: 0 | BD55: 0 | BF55: 0 | BG55: -556.62 | BH55: -391.7 | BI55: 0 | BL55: =SUM(AO55:BK55) -> -1233.8 | BM55: =AN55+BL55 -> 4103 | BN55: =K55/12*1 -> 444.66917 | BO55: =K55/12*1 -> 444.66917 | BP55: =BO55/3 -> 148.22306 | BQ55: =CQ55*CR55% -> 556.6173 | BR55: =CT55 -> 426.88 | BS55: =-(-CD55-AP55) -> 1351.35 | BT55: =IF(CE55+AQ55<0, 0, CE55+AQ55) -> 330.8 | BU55: =CB55+CC55 -> 272.28 | BV55: =SUMIFS('SEGURO DE VIDA'!E:E, 'SEGURO DE VIDA'!D:D, H55, 'SEGURO DE VIDA'!G:G, E55) -> 13.71 | BW55: =SUMIFS(TREINAMENTOS!E:E, TREINAMENTOS!D:D, H55, TREINAMENTOS!G:G, E55) -> 0 | BX55: =SUMIFS(EXAMES!E:E, EXAMES!D:D, H55, EXAMES!G:G, E55) -> 149.24 | BY55: =SUM(BN55:BU55)+SUM(BV55:BX55) -> 4138.4387 | CA55: FABIANO DE OLIVEIRA MACHADO | CB55: =IF(SUM(BB55:BD55)+CF55<0, 0, SUM(BB55:BD55)+CF55) -> 272.28 | CC55: =IF(SUM(AV55:AW55)+CG55<0, 0, SUM(AV55:AW55)+CG55) -> 0 | CD55: =SUMIFS(ALIMENTAÇÃO!E:E, ALIMENTAÇÃO!D:D, H55, ALIMENTAÇÃO!G:G, E55) -> 1365 | CE55: =SUMIFS(TRANSPORTE!E:E, TRANSPORTE!D:D, H55, TRANSPORTE!G:G, E55) -> 573.8 | CF55: =SUMIFS('PLANO DE SAÚDE'!E:E, 'PLANO DE SAÚDE'!D:D, H55, 'PLANO DE SAÚDE'!G:G, E55) -> 272.28 | CG55: =SUMIFS('PLANO ODONTO'!E:E, 'PLANO ODONTO'!D:D, H55, 'PLANO ODONTO'!G:G, E55) -> 28 | CH55: =BB55+BC55+BD55 -> 0 | CI55: =BI55+BJ55 -> 0 | CJ55: =AA55+AB55 -> 0 | CM55: =AV55+AW55 -> -28 | CN55: 5336.8 | CO55: -1233.8 | CP55: 4103 | CQ55: 5336.03 | CR55: 10.4313 | CS55: 5336.03 | CT55: 426.88 | CU55: 4728.83
A56: =IFERROR(__xludf.DUMMYFUNCTION("""COMPUTED_VALUE"""),"DAVI ELIAS DA SILVA CARVALHO") -> DAVI ELIAS DA SILVA CARVALHO | C56: =IF(COUNTIF(A:A, H56)>0, "OK", "Incompleto") -> OK | D56: =AN56+BY56 -> 6893.5159 | E56: 45809 | F56: 07.391.921/0001-71 | G56: 285 | H56: FABRICIO LORENCINI ZANONI | I56: Inst emendador de redes tele | J56: 44236 | K56: 2202.84 | M56: 2202.84 | P56: 660.85 | Q56: 0 | T56: 0 | Y56: 150 | Z56: 0 | AB56: 500.64 | AD56: 1052.05 | AE56: 0 | AF56: 263.01 | AJ56: 0 | AM56: 0.12 | AN56: =SUM(M56:AM56) -> 4829.51 | AP56: -5.7 | AQ56: -132.17 | AS56: 0 | AT56: -0.38 | AV56: -14 | AW56: -14 | BA56: -117.14 | BB56: 0 | BC56: -244.2 | BD56: 0 | BF56: 0 | BG56: -394.85 | BH56: -164.07 | BI56: 0 | BL56: =SUM(AO56:BK56) -> -1086.51 | BM56: =AN56+BL56 -> 3743 | BN56: =K56/12*1 -> 183.57 | BO56: =K56/12*1 -> 183.57 | BP56: =BO56/3 -> 61.19 | BQ56: =CQ56*CR56% -> 394.84591 | BR56: =CT56 -> 334.3 | BS56: =-(-CD56-AP56) -> 564.3 | BT56: =IF(CE56+AQ56<0, 0, CE56+AQ56) -> 39.33 | BU56: =CB56+CC56 -> 289.19 | BV56: =SUMIFS('SEGURO DE VIDA'!E:E, 'SEGURO DE VIDA'!D:D, H56, 'SEGURO DE VIDA'!G:G, E56) -> 13.71 | BW56: =SUMIFS(TREINAMENTOS!E:E, TREINAMENTOS!D:D, H56, TREINAMENTOS!G:G, E56) -> 0 | BX56: =SUMIFS(EXAMES!E:E, EXAMES!D:D, H56, EXAMES!G:G, E56) -> 0 | BY56: =SUM(BN56:BU56)+SUM(BV56:BX56) -> 2064.0059 | CA56: FABRICIO LORENCINI ZANONI | CB56: =IF(SUM(BB56:BD56)+CF56<0, 0, SUM(BB56:BD56)+CF56) -> 289.19 | CC56: =IF(SUM(AV56:AW56)+CG56<0, 0, SUM(AV56:AW56)+CG56) -> 0 | CD56: =SUMIFS(ALIMENTAÇÃO!E:E, ALIMENTAÇÃO!D:D, H56, ALIMENTAÇÃO!G:G, E56) -> 570 | CE56: =SUMIFS(TRANSPORTE!E:E, TRANSPORTE!D:D, H56, TRANSPORTE!G:G, E56) -> 171.5 | CF56: =SUMIFS('PLANO DE SAÚDE'!E:E, 'PLANO DE SAÚDE'!D:D, H56, 'PLANO DE SAÚDE'!G:G, E56) -> 533.39 | CG56: =SUMIFS('PLANO ODONTO'!E:E, 'PLANO ODONTO'!D:D, H56, 'PLANO ODONTO'!G:G, E56) -> 28 | CH56: =BB56+BC56+BD56 -> -244.2 | CI56: =BI56+BJ56 -> 0 | CJ56: =AA56+AB56 -> 500.64 | CM56: =AV56+AW56 -> -28 | CN56: 4829.51 | CO56: -1086.51 | CP56: 3743 | CQ56: 4178.75 | CR56: 9.4489 | CS56: 4178.75 | CT56: 334.3 | CU56: 3721.55
A57: =IFERROR(__xludf.DUMMYFUNCTION("""COMPUTED_VALUE"""),"DAVI VASCONCELLOS MACEDO") -> DAVI VASCONCELLOS MACEDO | C57: =IF(COUNTIF(A:A, H57)>0, "OK", "Incompleto") -> OK | D57: =AN57+BY57 -> 3083.85 | E57: 45809 | F57: 07.391.921/0001-71 | G57: 3433 | H57: FELIPE CORREA CONCEIÇÃO | I57: INSTALADOR JUNIOR | J57: 45362 | K57: 1800 | M57: 1800 | P57: 0 | Q57: 0 | T57: 0 | Y57: 0 | Z57: 0 | AB57: 0 | AD57: 0 | AE57: 0 | AF57: 0 | AJ57: 0 | AM57: 0.74 | AN57: =SUM(M57:AM57) -> 1800.74 | AP57: -5.95 | AQ57: 0 | AT57: -0.56 | AV57: 0 | AW57: 0 | BB57: 0 | BC57: 0 | BD57: 0 | BF57: 0 | BG57: -139.23 | BH57: 0 | BI57: 0 | BL57: =SUM(AO57:BK57) -> -145.74 | BM57: =AN57+BL57 -> 1655 | BN57: =K57/12*1 -> 150 | BO57: =K57/12*1 -> 150 | BP57: =BO57/3 -> 50 | BQ57: =CQ57*CR57% -> 139.23 | BR57: =CT57 -> 144 | BS57: =-(-CD57-AP57) -> 589.05 | BT57: =IF(CE57+AQ57<0, 0, CE57+AQ57) -> 0 | BU57: =CB57+CC57 -> 0 | BV57: =SUMIFS('SEGURO DE VIDA'!E:E, 'SEGURO DE VIDA'!D:D, H57, 'SEGURO DE VIDA'!G:G, E57) -> 13.71 | BW57: =SUMIFS(TREINAMENTOS!E:E, TREINAMENTOS!D:D, H57, TREINAMENTOS!G:G, E57) -> 0 | BX57: =SUMIFS(EXAMES!E:E, EXAMES!D:D, H57, EXAMES!G:G, E57) -> 47.12 | BY57: =SUM(BN57:BU57)+SUM(BV57:BX57) -> 1283.11 | CA57: FELIPE CORREA CONCEIÇÃO | CB57: =IF(SUM(BB57:BD57)+CF57<0, 0, SUM(BB57:BD57)+CF57) -> 0 | CC57: =IF(SUM(AV57:AW57)+CG57<0, 0, SUM(AV57:AW57)+CG57) -> 0 | CD57: =SUMIFS(ALIMENTAÇÃO!E:E, ALIMENTAÇÃO!D:D, H57, ALIMENTAÇÃO!G:G, E57) -> 595 | CE57: =SUMIFS(TRANSPORTE!E:E, TRANSPORTE!D:D, H57, TRANSPORTE!G:G, E57) -> 0 | CF57: =SUMIFS('PLANO DE SAÚDE'!E:E, 'PLANO DE SAÚDE'!D:D, H57, 'PLANO DE SAÚDE'!G:G, E57) -> 0 | CG57: =SUMIFS('PLANO ODONTO'!E:E, 'PLANO ODONTO'!D:D, H57, 'PLANO ODONTO'!G:G, E57) -> 0 | CH57: =BB57+BC57+BD57 -> 0 | CI57: =BI57+BJ57 -> 0 | CJ57: =AA57+AB57 -> 0 | CM57: =AV57+AW57 -> 0 | CN57: 1800.74 | CO57: -145.74 | CP57: 1655 | CQ57: 1800 | CR57: 7.735 | CS57: 1800 | CT57: 144 | CU57: 1192.8
A58: =IFERROR(__xludf.DUMMYFUNCTION("""COMPUTED_VALUE"""),"DIEGO CARLOS DA SILVA SANTOS") -> DIEGO CARLOS DA SILVA SANTOS | C58: =IF(COUNTIF(A:A, H58)>0, "OK", "Incompleto") -> OK | D58: =AN58+BY58 -> 4061.4597 | E58: 45809 | F58: 07.391.921/0001-71 | G58: 3489 | H58: FELIPE GOMES SILVA | I58: INSTALADOR PLENO | J58: 45621 | K58: 1800 | M58: 1800 | P58: 540 | Q58: 0 | T58: 0 | Y58: 0 | Z58: 0 | AB58: 0 | AD58: 140.4 | AE58: 0 | AF58: 35.1 | AJ58: 0 | AM58: 0.64 | AN58: =SUM(M58:AM58) -> 2516.14 | AP58: -6.65 | AQ58: 0 | AT58: -0.86 | AV58: -14 | AW58: 0 | BB58: 0 | BC58: -2.01 | BD58: 0 | BF58: 0 | BG58: -203.62 | BH58: 0 | BI58: 0 | BL58: =SUM(AO58:BK58) -> -227.14 | BM58: =AN58+BL58 -> 2289 | BN58: =K58/12*1 -> 150 | BO58: =K58/12*1 -> 150 | BP58: =BO58/3 -> 50 | BQ58: =CQ58*CR58% -> 203.61966 | BR58: =CT58 -> 201.24 | BS58: =-(-CD58-AP58) -> 658.35 | BT58: =IF(CE58+AQ58<0, 0, CE58+AQ58) -> 0 | BU58: =CB58+CC58 -> 118.4 | BV58: =SUMIFS('SEGURO DE VIDA'!E:E, 'SEGURO DE VIDA'!D:D, H58, 'SEGURO DE VIDA'!G:G, E58) -> 13.71 | BW58: =SUMIFS(TREINAMENTOS!E:E, TREINAMENTOS!D:D, H58, TREINAMENTOS!G:G, E58) -> 0 | BX58: =SUMIFS(EXAMES!E:E, EXAMES!D:D, H58, EXAMES!G:G, E58) -> 0 | BY58: =SUM(BN58:BU58)+SUM(BV58:BX58) -> 1545.3197 | CA58: FELIPE GOMES DA SILVA | CB58: =IF(SUM(BB58:BD58)+CF58<0, 0, SUM(BB58:BD58)+CF58) -> 118.4 | CC58: =IF(SUM(AV58:AW58)+CG58<0, 0, SUM(AV58:AW58)+CG58) -> 0 | CD58: =SUMIFS(ALIMENTAÇÃO!E:E, ALIMENTAÇÃO!D:D, H58, ALIMENTAÇÃO!G:G, E58) -> 665 | CE58: =SUMIFS(TRANSPORTE!E:E, TRANSPORTE!D:D, H58, TRANSPORTE!G:G, E58) -> 0 | CF58: =SUMIFS('PLANO DE SAÚDE'!E:E, 'PLANO DE SAÚDE'!D:D, H58, 'PLANO DE SAÚDE'!G:G, E58) -> 120.41 | CG58: =SUMIFS('PLANO ODONTO'!E:E, 'PLANO ODONTO'!D:D, H58, 'PLANO ODONTO'!G:G, E58) -> 14 | CH58: =BB58+BC58+BD58 -> -2.01 | CI58: =BI58+BJ58 -> 0 | CJ58: =AA58+AB58 -> 0 | CM58: =AV58+AW58 -> -14 | CN58: 2516.14 | CO58: -227.14 | CP58: 2289 | CQ58: 2515.5 | CR58: 8.0946 | CS58: 2515.5 | CT58: 201.24 | CU58: 1908.3
A59: =IFERROR(__xludf.DUMMYFUNCTION("""COMPUTED_VALUE"""),"DIEGO FERNANDES ALVES MARTINS") -> DIEGO FERNANDES ALVES MARTINS | C59: =IF(COUNTIF(A:A, H59)>0, "OK", "Incompleto") -> OK | D59: =AN59+BY59 -> 4532.4755 | E59: 45809 | F59: 07.391.921/0001-71 | G59: 3516 | H59: FELIPE TAVARES ARAUJO | I59: TECNICO DE TELECOMUNI | J59: 45728 | K59: 2049 | M59: 2049 | P59: 614.7 | Q59: 0 | T59: 0 | Y59: 0 | Z59: 0 | AB59: 0 | AD59: 159.82 | AE59: 0 | AF59: 39.96 | AJ59: 0 | AM59: 0.17 | AN59: =SUM(M59:AM59) -> 2863.65 | AP59: -6.65 | AQ59: 0 | AT59: -0.74 | AV59: -14 | AW59: 0 | BB59: 0 | BC59: -2.24 | BD59: 0 | BF59: 0 | BG59: -237.02 | BH59: 0 | BI59: 0 | BL59: =SUM(AO59:BK59) -> -260.65 | BM59: =AN59+BL59 -> 2603 | BN59: =K59/12*1 -> 170.75 | BO59: =K59/12*1 -> 170.75 | BP59: =BO59/3 -> 56.916667 | BQ59: =CQ59*CR59% -> 237.01883 | BR59: =CT59 -> 229.07 | BS59: =-(-CD59-AP59) -> 658.35 | BT59: =IF(CE59+AQ59<0, 0, CE59+AQ59) -> 0 | BU59: =CB59+CC59 -> 132.26 | BV59: =SUMIFS('SEGURO DE VIDA'!E:E, 'SEGURO DE VIDA'!D:D, H59, 'SEGURO DE VIDA'!G:G, E59) -> 13.71 | BW59: =SUMIFS(TREINAMENTOS!E:E, TREINAMENTOS!D:D, H59, TREINAMENTOS!G:G, E59) -> 0 | BX59: =SUMIFS(EXAMES!E:E, EXAMES!D:D, H59, EXAMES!G:G, E59) -> 0 | BY59: =SUM(BN59:BU59)+SUM(BV59:BX59) -> 1668.8255 | CA59: FELIPE TAVARES DE ARAUJO | CB59: =IF(SUM(BB59:BD59)+CF59<0, 0, SUM(BB59:BD59)+CF59) -> 132.26 | CC59: =IF(SUM(AV59:AW59)+CG59<0, 0, SUM(AV59:AW59)+CG59) -> 0 | CD59: =SUMIFS(ALIMENTAÇÃO!E:E, ALIMENTAÇÃO!D:D, H59, ALIMENTAÇÃO!G:G, E59) -> 665 | CE59: =SUMIFS(TRANSPORTE!E:E, TRANSPORTE!D:D, H59, TRANSPORTE!G:G, E59) -> 0 | CF59: =SUMIFS('PLANO DE SAÚDE'!E:E, 'PLANO DE SAÚDE'!D:D, H59, 'PLANO DE SAÚDE'!G:G, E59) -> 134.5 | CG59: =SUMIFS('PLANO ODONTO'!E:E, 'PLANO ODONTO'!D:D, H59, 'PLANO ODONTO'!G:G, E59) -> 14 | CH59: =BB59+BC59+BD59 -> -2.24 | CI59: =BI59+BJ59 -> 0 | CJ59: =AA59+AB59 -> 0 | CM59: =AV59+AW59 -> -14 | CN59: 2863.65 | CO59: -260.65 | CP59: 2603 | CQ59: 2863.48 | CR59: 8.2773 | CS59: 2863.48 | CT59: 229.07 | CU59: 2247.28
A60: =IFERROR(__xludf.DUMMYFUNCTION("""COMPUTED_VALUE"""),"DOUGLAS DE SOUZA PAULO") -> DOUGLAS DE SOUZA PAULO | C60: =IF(COUNTIF(A:A, H60)>0, "OK", "Incompleto") -> OK | D60: =AN60+BY60 -> 4356.1948 | E60: 45809 | F60: 07.391.921/0001-71 | G60: 3347 | H60: FELIPE VARGAS DE SOUZA | I60: INSTALADOR JUNIOR | J60: 45017 | K60: 1988.62 | M60: 1988.62 | P60: 596.59 | Q60: 0 | T60: 0 | Y60: 0 | Z60: 0 | AB60: 0 | AD60: 155.11 | AE60: 0 | AF60: 38.78 | AJ60: 0 | AM60: 0.66 | AN60: =SUM(M60:AM60) -> 2779.76 | AP60: -6.65 | AQ60: 0 | AT60: -0.32 | AV60: -14 | AW60: 0 | BB60: -32.55 | BC60: -2.01 | BD60: -125.89 | BF60: 0 | BG60: -227.34 | BH60: 0 | BI60: 0 | BL60: =SUM(AO60:BK60) -> -408.76 | BM60: =AN60+BL60 -> 2371 | BN60: =K60/12*1 -> 165.71833 | BO60: =K60/12*1 -> 165.71833 | BP60: =BO60/3 -> 55.239444 | BQ60: =CQ60*CR60% -> 227.33872 | BR60: =CT60 -> 222.32 | BS60: =-(-CD60-AP60) -> 658.35 | BT60: =IF(CE60+AQ60<0, 0, CE60+AQ60) -> 0 | BU60: =CB60+CC60 -> 68.04 | BV60: =SUMIFS('SEGURO DE VIDA'!E:E, 'SEGURO DE VIDA'!D:D, H60, 'SEGURO DE VIDA'!G:G, E60) -> 13.71 | BW60: =SUMIFS(TREINAMENTOS!E:E, TREINAMENTOS!D:D, H60, TREINAMENTOS!G:G, E60) -> 0 | BX60: =SUMIFS(EXAMES!E:E, EXAMES!D:D, H60, EXAMES!G:G, E60) -> 0 | BY60: =SUM(BN60:BU60)+SUM(BV60:BX60) -> 1576.4348 | CA60: FELIPE VARGAS DE SOUZA | CB60: =IF(SUM(BB60:BD60)+CF60<0, 0, SUM(BB60:BD60)+CF60) -> 68.04 | CC60: =IF(SUM(AV60:AW60)+CG60<0, 0, SUM(AV60:AW60)+CG60) -> 0 | CD60: =SUMIFS(ALIMENTAÇÃO!E:E, ALIMENTAÇÃO!D:D, H60, ALIMENTAÇÃO!G:G, E60) -> 665 | CE60: =SUMIFS(TRANSPORTE!E:E, TRANSPORTE!D:D, H60, TRANSPORTE!G:G, E60) -> 0 | CF60: =SUMIFS('PLANO DE SAÚDE'!E:E, 'PLANO DE SAÚDE'!D:D, H60, 'PLANO DE SAÚDE'!G:G, E60) -> 228.49 | CG60: =SUMIFS('PLANO ODONTO'!E:E, 'PLANO ODONTO'!D:D, H60, 'PLANO ODONTO'!G:G, E60) -> 14 | CH60: =BB60+BC60+BD60 -> -160.45 | CI60: =BI60+BJ60 -> 0 | CJ60: =AA60+AB60 -> 0 | CM60: =AV60+AW60 -> -14 | CN60: 2779.76 | CO60: -408.76 | CP60: 2371 | CQ60: 2779.1 | CR60: 8.1803 | CS60: 2779.1 | CT60: 222.32 | CU60: 2171.9
A61: =IFERROR(__xludf.DUMMYFUNCTION("""COMPUTED_VALUE"""),"DOUGLAS RODRIGUES DIAS") -> DOUGLAS RODRIGUES DIAS | C61: =IF(COUNTIF(A:A, H61)>0, "OK", "Incompleto") -> OK | D61: =AN61+BY61 -> 4705.32 | E61: 45809 | F61: 20.258.413/0001-88 | G61: 2 | H61: FERNANDO MENDONÇA FERNANDES | I61: PRO LABORE | M61: 2824 | AC61: 0 | AD61: 0 | AE61: 0 | AF61: 0 | AM61: 0 | AN61: =SUM(M61:AM61) -> 2824 | AP61: 0 | AQ61: 0 | AR61: 0 | AT61: 0 | AV61: 0 | BB61: 0 | BC61: 0 | BD61: 0 | BG61: -310.64 | BH61: 0 | BL61: =SUM(AO61:BK61) -> -310.64 | BM61: =AN61+BL61 -> 2513.36 | BN61: =K61/12*1 -> 0 | BO61: =K61/12*1 -> 0 | BP61: =BO61/3 -> 0 | BQ61: =CQ61*CR61% -> 310.64 | BR61: =CT61 -> 0 | BS61: =-(-CD61-AP61) -> 1000 | BT61: =IF(CE61+AQ61<0, 0, CE61+AQ61) -> 0 | BU61: =CB61+CC61 -> 511.01 | BV61: =SUMIFS('SEGURO DE VIDA'!E:E, 'SEGURO DE VIDA'!D:D, H61, 'SEGURO DE VIDA'!G:G, E61) -> 59.67 | BW61: =SUMIFS(TREINAMENTOS!E:E, TREINAMENTOS!D:D, H61, TREINAMENTOS!G:G, E61) -> 0 | BX61: =SUMIFS(EXAMES!E:E, EXAMES!D:D, H61, EXAMES!G:G, E61) -> 0 | BY61: =SUM(BN61:BU61)+SUM(BV61:BX61) -> 1881.32 | CA61: FERNANDO MENDONCA FERNANDES | CB61: =IF(SUM(BB61:BD61)+CF61<0, 0, SUM(BB61:BD61)+CF61) -> 483.01 | CC61: =IF(SUM(AV61:AW61)+CG61<0, 0, SUM(AV61:AW61)+CG61) -> 28 | CD61: =SUMIFS(ALIMENTAÇÃO!E:E, ALIMENTAÇÃO!D:D, H61, ALIMENTAÇÃO!G:G, E61) -> 1000 | CE61: =SUMIFS(TRANSPORTE!E:E, TRANSPORTE!D:D, H61, TRANSPORTE!G:G, E61) -> 0 | CF61: =SUMIFS('PLANO DE SAÚDE'!E:E, 'PLANO DE SAÚDE'!D:D, H61, 'PLANO DE SAÚDE'!G:G, E61) -> 483.01 | CG61: =SUMIFS('PLANO ODONTO'!E:E, 'PLANO ODONTO'!D:D, H61, 'PLANO ODONTO'!G:G, E61) -> 28 | CH61: =BB61+BC61+BD61 -> 0 | CI61: =BI61+BJ61 -> 0 | CJ61: =AA61+AB61 -> 0 | CM61: =AV61+AW61 -> 0 | CN61: 2824 | CO61: -310.64 | CP61: 2513.36 | CQ61: 2824 | CR61: 11 | CS61: 0 | CT61: 0 | CU61: 2216.8
A62: =IFERROR(__xludf.DUMMYFUNCTION("""COMPUTED_VALUE"""),"EDILEI SANTOS SILVA") -> EDILEI SANTOS SILVA | C62: =IF(COUNTIF(A:A, H62)>0, "OK", "Incompleto") -> OK | D62: =AN62+BY62 -> 5268.0913 | E62: 45809 | F62: 07.391.921/0001-71 | G62: 3374 | H62: FERNANDO PAIVA SILVA DE SOUZA | I62: TECNICO DE BROADCAST | J62: 45108 | K62: 3000 | M62: 3000 | P62: 0 | Q62: 0 | T62: 400 | Y62: 0 | Z62: 0 | AB62: 0 | AD62: 0 | AE62: 0 | AF62: 0 | AJ62: 0 | AM62: 0.9 | AN62: =SUM(M62:AM62) -> 3400.9 | AP62: -6.65 | AQ62: 0 | AT62: -0.84 | AV62: -14 | AW62: 0 | BB62: 0 | BC62: -2.01 | BD62: 0 | BF62: 0 | BG62: -253.4 | BH62: 0 | BI62: 0 | BL62: =SUM(AO62:BK62) -> -276.9 | BM62: =AN62+BL62 -> 3124 | BN62: =K62/12*1 -> 250 | BO62: =K62/12*1 -> 250 | BP62: =BO62/3 -> 83.333333 | BQ62: =CQ62*CR62% -> 253.398 | BR62: =CT62 -> 240 | BS62: =-(-CD62-AP62) -> 658.35 | BT62: =IF(CE62+AQ62<0, 0, CE62+AQ62) -> 0 | BU62: =CB62+CC62 -> 118.4 | BV62: =SUMIFS('SEGURO DE VIDA'!E:E, 'SEGURO DE VIDA'!D:D, H62, 'SEGURO DE VIDA'!G:G, E62) -> 13.71 | BW62: =SUMIFS(TREINAMENTOS!E:E, TREINAMENTOS!D:D, H62, TREINAMENTOS!G:G, E62) -> 0 | BX62: =SUMIFS(EXAMES!E:E, EXAMES!D:D, H62, EXAMES!G:G, E62) -> 0 | BY62: =SUM(BN62:BU62)+SUM(BV62:BX62) -> 1867.1913 | CA62: FERNANDO PAIVA SILVA DE SOUZA | CB62: =IF(SUM(BB62:BD62)+CF62<0, 0, SUM(BB62:BD62)+CF62) -> 118.4 | CC62: =IF(SUM(AV62:AW62)+CG62<0, 0, SUM(AV62:AW62)+CG62) -> 0 | CD62: =SUMIFS(ALIMENTAÇÃO!E:E, ALIMENTAÇÃO!D:D, H62, ALIMENTAÇÃO!G:G, E62) -> 665 | CE62: =SUMIFS(TRANSPORTE!E:E, TRANSPORTE!D:D, H62, TRANSPORTE!G:G, E62) -> 0 | CF62: =SUMIFS('PLANO DE SAÚDE'!E:E, 'PLANO DE SAÚDE'!D:D, H62, 'PLANO DE SAÚDE'!G:G, E62) -> 120.41 | CG62: =SUMIFS('PLANO ODONTO'!E:E, 'PLANO ODONTO'!D:D, H62, 'PLANO ODONTO'!G:G, E62) -> 14 | CH62: =BB62+BC62+BD62 -> -2.01 | CI62: =BI62+BJ62 -> 0 | CJ62: =AA62+AB62 -> 0 | CM62: =AV62+AW62 -> -14 | CN62: 3400.9 | CO62: -276.9 | CP62: 3124 | CQ62: 3000 | CR62: 8.4466 | CS62: 3000 | CT62: 240 | CU62: 2392.8
A63: =IFERROR(__xludf.DUMMYFUNCTION("""COMPUTED_VALUE"""),"EDMILSON MENDES DE SOUZA") -> EDMILSON MENDES DE SOUZA | C63: =IF(COUNTIF(A:A, H63)>0, "OK", "Incompleto") -> OK | D63: =AN63+BY63 -> 8017.4443 | E63: 45809 | F63: 07.391.921/0001-71 | G63: 3371 | H63: FILIPE DE SOUSA BOLONINI | I63: Eletricista Pleno | J63: 45062 | K63: 2800 | M63: 2800 | P63: 840 | Q63: 0 | T63: 0 | Y63: 0 | Z63: 0 | AB63: 700 | AD63: 1209.39 | AE63: 0 | AF63: 302.35 | AJ63: 0 | AM63: 0.23 | AN63: =SUM(M63:AM63) -> 5851.97 | AP63: -5.7 | AQ63: 0 | AT63: -0.34 | AV63: -14 | AW63: 0 | BB63: 0 | BC63: -100.08 | BD63: 0 | BF63: 0 | BG63: -530.82 | BH63: -347.03 | BI63: 0 | BL63: =SUM(AO63:BK63) -> -997.97 | BM63: =AN63+BL63 -> 4854 | BN63: =K63/12*1 -> 233.33333 | BO63: =K63/12*1 -> 233.33333 | BP63: =BO63/3 -> 77.777778 | BQ63: =CQ63*CR63% -> 530.81983 | BR63: =CT63 -> 412.13 | BS63: =-(-CD63-AP63) -> 564.3 | BT63: =IF(CE63+AQ63<0, 0, CE63+AQ63) -> 0 | BU63: =CB63+CC63 -> 100.07 | BV63: =SUMIFS('SEGURO DE VIDA'!E:E, 'SEGURO DE VIDA'!D:D, H63, 'SEGURO DE VIDA'!G:G, E63) -> 13.71 | BW63: =SUMIFS(TREINAMENTOS!E:E, TREINAMENTOS!D:D, H63, TREINAMENTOS!G:G, E63) -> 0 | BX63: =SUMIFS(EXAMES!E:E, EXAMES!D:D, H63, EXAMES!G:G, E63) -> 0 | BY63: =SUM(BN63:BU63)+SUM(BV63:BX63) -> 2165.4743 | CA63: FILIPE DE SOUSA BOLONINI | CB63: =IF(SUM(BB63:BD63)+CF63<0, 0, SUM(BB63:BD63)+CF63) -> 100.07 | CC63: =IF(SUM(AV63:AW63)+CG63<0, 0, SUM(AV63:AW63)+CG63) -> 0 | CD63: =SUMIFS(ALIMENTAÇÃO!E:E, ALIMENTAÇÃO!D:D, H63, ALIMENTAÇÃO!G:G, E63) -> 570 | CE63: =SUMIFS(TRANSPORTE!E:E, TRANSPORTE!D:D, H63, TRANSPORTE!G:G, E63) -> 0 | CF63: =SUMIFS('PLANO DE SAÚDE'!E:E, 'PLANO DE SAÚDE'!D:D, H63, 'PLANO DE SAÚDE'!G:G, E63) -> 200.15 | CG63: =SUMIFS('PLANO ODONTO'!E:E, 'PLANO ODONTO'!D:D, H63, 'PLANO ODONTO'!G:G, E63) -> 14 | CH63: =BB63+BC63+BD63 -> -100.08 | CI63: =BI63+BJ63 -> 0 | CJ63: =AA63+AB63 -> 700 | CM63: =AV63+AW63 -> -14 | CN63: 5851.97 | CO63: -997.97 | CP63: 4854 | CQ63: 5151.74 | CR63: 10.3037 | CS63: 5151.74 | CT63: 412.13 | CU63: 4544.54
A64: =IFERROR(__xludf.DUMMYFUNCTION("""COMPUTED_VALUE"""),"EDRIZIO SANTANA DA SILVA") -> EDRIZIO SANTANA DA SILVA | C64: =IF(COUNTIF(A:A, H64)>0, "OK", "Incompleto") -> OK | D64: =AN64+BY64 -> 2620.64 | E64: 45809 | F64: 07.391.921/0001-71 | G64: 3476 | H64: FLAVIANO DE ALMEIDA DOS SANTOS | I64: INSTALADOR PLENO | J64: 45593 | K64: 1800 | L64: Benefício | M64: 1260 | P64: 0 | Q64: 0 | T64: 0 | Y64: 0 | Z64: 0 | AB64: 0 | AD64: 0 | AE64: 0 | AF64: 0 | AJ64: 65 | AM64: 0.88 | AN64: =SUM(M64:AM64) -> 1325.88 | AP64: -5.95 | AQ64: -75.6 | AT64: -0.83 | AV64: 0 | AW64: 0 | BB64: 0 | BC64: 0 | BD64: 0 | BF64: 0 | BG64: -94.5 | BH64: 0 | BI64: 0 | BL64: =SUM(AO64:BK64) -> -176.88 | BM64: =AN64+BL64 -> 1149 | BN64: =K64/12*1 -> 150 | BO64: =K64/12*1 -> 150 | BP64: =BO64/3 -> 50 | BQ64: =CQ64*CR64% -> 94.5 | BR64: =CT64 -> 100.8 | BS64: =-(-CD64-AP64) -> 589.05 | BT64: =IF(CE64+AQ64<0, 0, CE64+AQ64) -> 146.7 | BU64: =CB64+CC64 -> 0 | BV64: =SUMIFS('SEGURO DE VIDA'!E:E, 'SEGURO DE VIDA'!D:D, H64, 'SEGURO DE VIDA'!G:G, E64) -> 13.71 | BW64: =SUMIFS(TREINAMENTOS!E:E, TREINAMENTOS!D:D, H64, TREINAMENTOS!G:G, E64) -> 0 | BX64: =SUMIFS(EXAMES!E:E, EXAMES!D:D, H64, EXAMES!G:G, E64) -> 0 | BY64: =SUM(BN64:BU64)+SUM(BV64:BX64) -> 1294.76 | CA64: FLAVIANO DE ALMEIDA DOS SANTO | CB64: =IF(SUM(BB64:BD64)+CF64<0, 0, SUM(BB64:BD64)+CF64) -> 0 | CC64: =IF(SUM(AV64:AW64)+CG64<0, 0, SUM(AV64:AW64)+CG64) -> 0 | CD64: =SUMIFS(ALIMENTAÇÃO!E:E, ALIMENTAÇÃO!D:D, H64, ALIMENTAÇÃO!G:G, E64) -> 595 | CE64: =SUMIFS(TRANSPORTE!E:E, TRANSPORTE!D:D, H64, TRANSPORTE!G:G, E64) -> 222.3 | CF64: =SUMIFS('PLANO DE SAÚDE'!E:E, 'PLANO DE SAÚDE'!D:D, H64, 'PLANO DE SAÚDE'!G:G, E64) -> 0 | CG64: =SUMIFS('PLANO ODONTO'!E:E, 'PLANO ODONTO'!D:D, H64, 'PLANO ODONTO'!G:G, E64) -> 0 | CH64: =BB64+BC64+BD64 -> 0 | CI64: =BI64+BJ64 -> 0 | CJ64: =AA64+AB64 -> 0 | CM64: =AV64+AW64 -> 0 | CN64: 1325.88 | CO64: -176.88 | CP64: 1149 | CQ64: 1260 | CR64: 7.5 | CS64: 1260 | CT64: 100.8 | CU64: 652.8
A65: =IFERROR(__xludf.DUMMYFUNCTION("""COMPUTED_VALUE"""),"EDUARDO FERREIRA DA MOTTA") -> EDUARDO FERREIRA DA MOTTA | C65: =IF(COUNTIF(A:A, H65)>0, "OK", "Incompleto") -> OK | D65: =AN65+BY65 -> 3957.1709 | E65: 45809 | F65: 07.391.921/0001-71 | G65: 3518 | H65: FRANCISCO DA SILVA ALVES | I65: Operador de Audio e Video | J65: 45733 | K65: 2239.36 | M65: 2239.36 | P65: 0 | Q65: 0 | T65: 0 | Y65: 0 | Z65: 0 | AB65: 0 | AD65: 65.78 | AE65: 0 | AF65: 16.44 | AJ65: 0 | AM65: 0.32 | AN65: =SUM(M65:AM65) -> 2321.9 | AP65: -6.3 | AQ65: -134.36 | AT65: -0.07 | AV65: 0 | AW65: 0 | BB65: 0 | BC65: 0 | BD65: 0 | BF65: 0 | BG65: -186.17 | BH65: 0 | BI65: 0 | BL65: =SUM(AO65:BK65) -> -326.9 | BM65: =AN65+BL65 -> 1995 | BN65: =K65/12*1 -> 186.61333 | BO65: =K65/12*1 -> 186.61333 | BP65: =BO65/3 -> 62.204444 | BQ65: =CQ65*CR65% -> 186.16982 | BR65: =CT65 -> 185.72 | BS65: =-(-CD65-AP65) -> 623.7 | BT65: =IF(CE65+AQ65<0, 0, CE65+AQ65) -> 190.54 | BU65: =CB65+CC65 -> 0 | BV65: =SUMIFS('SEGURO DE VIDA'!E:E, 'SEGURO DE VIDA'!D:D, H65, 'SEGURO DE VIDA'!G:G, E65) -> 13.71 | BW65: =SUMIFS(TREINAMENTOS!E:E, TREINAMENTOS!D:D, H65, TREINAMENTOS!G:G, E65) -> 0 | BX65: =SUMIFS(EXAMES!E:E, EXAMES!D:D, H65, EXAMES!G:G, E65) -> 0 | BY65: =SUM(BN65:BU65)+SUM(BV65:BX65) -> 1635.2709 | CA65: FRANCISCO DA SILVA ALVES | CB65: =IF(SUM(BB65:BD65)+CF65<0, 0, SUM(BB65:BD65)+CF65) -> 0 | CC65: =IF(SUM(AV65:AW65)+CG65<0, 0, SUM(AV65:AW65)+CG65) -> 0 | CD65: =SUMIFS(ALIMENTAÇÃO!E:E, ALIMENTAÇÃO!D:D, H65, ALIMENTAÇÃO!G:G, E65) -> 630 | CE65: =SUMIFS(TRANSPORTE!E:E, TRANSPORTE!D:D, H65, TRANSPORTE!G:G, E65) -> 324.9 | CF65: =SUMIFS('PLANO DE SAÚDE'!E:E, 'PLANO DE SAÚDE'!D:D, H65, 'PLANO DE SAÚDE'!G:G, E65) -> 0 | CG65: =SUMIFS('PLANO ODONTO'!E:E, 'PLANO ODONTO'!D:D, H65, 'PLANO ODONTO'!G:G, E65) -> 0 | CH65: =BB65+BC65+BD65 -> 0 | CI65: =BI65+BJ65 -> 0 | CJ65: =AA65+AB65 -> 0 | CM65: =AV65+AW65 -> 0 | CN65: 2321.9 | CO65: -326.9 | CP65: 1995 | CQ65: 2321.58 | CR65: 8.0191 | CS65: 2321.58 | CT65: 185.72 | CU65: 1714.38
A66: =IFERROR(__xludf.DUMMYFUNCTION("""COMPUTED_VALUE"""),"EDUARDO MARTINS DE LUCENA") -> EDUARDO MARTINS DE LUCENA | C66: =IF(COUNTIF(A:A, H66)>0, "OK", "Incompleto") -> OK | D66: =AN66+BY66 -> 3320.62 | E66: 45809 | F66: 07.391.921/0001-71 | G66: 373 | H66: GABRIEL DE ALMEIDA MONTEIRO | I66: INSTALADOR JUNIOR | J66: 44844 | K66: 1800 | M66: 1800 | P66: 0 | Q66: 0 | T66: 0 | Y66: 0 | Z66: 0 | AB66: 0 | AD66: 0 | AE66: 0 | AF66: 0 | AJ66: 0 | AM66: 0.26 | AN66: =SUM(M66:AM66) -> 1800.26 | AP66: -5.6 | AQ66: -108 | AT66: -0.43 | AV66: 0 | AW66: 0 | BB66: 0 | BC66: 0 | BD66: 0 | BF66: 0 | BG66: -139.23 | BH66: 0 | BI66: 0 | BL66: =SUM(AO66:BK66) -> -253.26 | BM66: =AN66+BL66 -> 1547 | BN66: =K66/12*1 -> 150 | BO66: =K66/12*1 -> 150 | BP66: =BO66/3 -> 50 | BQ66: =CQ66*CR66% -> 139.23 | BR66: =CT66 -> 144 | BS66: =-(-CD66-AP66) -> 554.4 | BT66: =IF(CE66+AQ66<0, 0, CE66+AQ66) -> 216.9 | BU66: =CB66+CC66 -> 0 | BV66: =SUMIFS('SEGURO DE VIDA'!E:E, 'SEGURO DE VIDA'!D:D, H66, 'SEGURO DE VIDA'!G:G, E66) -> 13.71 | BW66: =SUMIFS(TREINAMENTOS!E:E, TREINAMENTOS!D:D, H66, TREINAMENTOS!G:G, E66) -> 0 | BX66: =SUMIFS(EXAMES!E:E, EXAMES!D:D, H66, EXAMES!G:G, E66) -> 102.12 | BY66: =SUM(BN66:BU66)+SUM(BV66:BX66) -> 1520.36 | CA66: GABRIEL DE ALMEIDA MONTEIRO | CB66: =IF(SUM(BB66:BD66)+CF66<0, 0, SUM(BB66:BD66)+CF66) -> 0 | CC66: =IF(SUM(AV66:AW66)+CG66<0, 0, SUM(AV66:AW66)+CG66) -> 0 | CD66: =SUMIFS(ALIMENTAÇÃO!E:E, ALIMENTAÇÃO!D:D, H66, ALIMENTAÇÃO!G:G, E66) -> 560 | CE66: =SUMIFS(TRANSPORTE!E:E, TRANSPORTE!D:D, H66, TRANSPORTE!G:G, E66) -> 324.9 | CF66: =SUMIFS('PLANO DE SAÚDE'!E:E, 'PLANO DE SAÚDE'!D:D, H66, 'PLANO DE SAÚDE'!G:G, E66) -> 0 | CG66: =SUMIFS('PLANO ODONTO'!E:E, 'PLANO ODONTO'!D:D, H66, 'PLANO ODONTO'!G:G, E66) -> 0 | CH66: =BB66+BC66+BD66 -> 0 | CI66: =BI66+BJ66 -> 0 | CJ66: =AA66+AB66 -> 0 | CM66: =AV66+AW66 -> 0 | CN66: 1800.26 | CO66: -253.26 | CP66: 1547 | CQ66: 1800 | CR66: 7.735 | CS66: 1800 | CT66: 144 | CU66: 1192.8
A67: =IFERROR(__xludf.DUMMYFUNCTION("""COMPUTED_VALUE"""),"EDUARDO MENDES AVILA") -> EDUARDO MENDES AVILA | C67: =IF(COUNTIF(A:A, H67)>0, "OK", "Incompleto") -> OK | D67: =AN67+BY67 -> 4097.1392 | E67: 45809 | F67: 07.391.921/0001-71 | G67: 3423 | H67: GABRIEL SAMPAIO DE SOUSA | I67: Operador de Audio e Video | J67: 45323 | K67: 2239.36 | M67: 2239.36 | P67: 0 | Q67: 0 | T67: 0 | Y67: 0 | Z67: 0 | AB67: 0 | AD67: 0 | AE67: 0 | AF67: 0 | AJ67: 0 | AM67: 0.81 | AN67: =SUM(M67:AM67) -> 2240.17 | AP67: -6.65 | AQ67: 0 | AT67: -0.04 | AV67: 0 | AW67: 0 | BB67: 0 | BC67: -1.71 | BD67: 0 | BF67: -245 | BG67: -178.77 | BH67: 0 | BI67: 0 | BL67: =SUM(AO67:BK67) -> -432.17 | BM67: =AN67+BL67 -> 1808 | BN67: =K67/12*1 -> 186.61333 | BO67: =K67/12*1 -> 186.61333 | BP67: =BO67/3 -> 62.204444 | BQ67: =CQ67*CR67% -> 178.76811 | BR67: =CT67 -> 179.14 | BS67: =-(-CD67-AP67) -> 658.35 | BT67: =IF(CE67+AQ67<0, 0, CE67+AQ67) -> 290.7 | BU67: =CB67+CC67 -> 100.87 | BV67: =SUMIFS('SEGURO DE VIDA'!E:E, 'SEGURO DE VIDA'!D:D, H67, 'SEGURO DE VIDA'!G:G, E67) -> 13.71 | BW67: =SUMIFS(TREINAMENTOS!E:E, TREINAMENTOS!D:D, H67, TREINAMENTOS!G:G, E67) -> 0 | BX67: =SUMIFS(EXAMES!E:E, EXAMES!D:D, H67, EXAMES!G:G, E67) -> 0 | BY67: =SUM(BN67:BU67)+SUM(BV67:BX67) -> 1856.9692 | CA67: GABRIEL SAMPAIO DE SOUSA | CB67: =IF(SUM(BB67:BD67)+CF67<0, 0, SUM(BB67:BD67)+CF67) -> 100.87 | CC67: =IF(SUM(AV67:AW67)+CG67<0, 0, SUM(AV67:AW67)+CG67) -> 0 | CD67: =SUMIFS(ALIMENTAÇÃO!E:E, ALIMENTAÇÃO!D:D, H67, ALIMENTAÇÃO!G:G, E67) -> 665 | CE67: =SUMIFS(TRANSPORTE!E:E, TRANSPORTE!D:D, H67, TRANSPORTE!G:G, E67) -> 290.7 | CF67: =SUMIFS('PLANO DE SAÚDE'!E:E, 'PLANO DE SAÚDE'!D:D, H67, 'PLANO DE SAÚDE'!G:G, E67) -> 102.58 | CG67: =SUMIFS('PLANO ODONTO'!E:E, 'PLANO ODONTO'!D:D, H67, 'PLANO ODONTO'!G:G, E67) -> 0 | CH67: =BB67+BC67+BD67 -> -1.71 | CI67: =BI67+BJ67 -> 0 | CJ67: =AA67+AB67 -> 0 | CM67: =AV67+AW67 -> 0 | CN67: 2240.17 | CO67: -432.17 | CP67: 1808 | CQ67: 2239.36 | CR67: 7.983 | CS67: 2239.36 | CT67: 179.14 | CU67: 1632.16
A68: =IFERROR(__xludf.DUMMYFUNCTION("""COMPUTED_VALUE"""),"EMERSON ADAUTO DA SILVA") -> EMERSON ADAUTO DA SILVA | C68: =IF(COUNTIF(A:A, H68)>0, "OK", "Incompleto") -> OK | D68: =AN68+BY68 -> 3166.9354 | E68: 45809 | F68: 07.391.921/0001-71 | G68: 3454 | H68: GEORGIA MARIANA DA SILVA PEREIRA | I68: APRENDIZ ADMINISTRATIV | J68: 45495 | K68: 1069.48 | M68: 1069.48 | O68: 0 | P68: 0 | T68: 0 | Y68: 0 | AD68: 0 | AE68: 0 | AF68: 0 | AM68: 0.9 | AN68: =SUM(M68:AM68) -> 1070.38 | AP68: -6.3 | AQ68: -64.17 | AT68: -0.99 | AV68: 0 | BB68: 0 | BC68: -1.71 | BD68: 0 | BF68: 0 | BG68: -80.21 | BH68: 0 | BJ68: 0 | BL68: =SUM(AO68:BK68) -> -153.38 | BM68: =AN68+BL68 -> 917 | BN68: =K68/12*1 -> 89.123333 | BO68: =K68/12*1 -> 89.123333 | BP68: =BO68/3 -> 29.707778 | BQ68: =CQ68*CR68% -> 80.211 | BR68: =CT68 -> 21.38 | BS68: =-(-CD68-AP68) -> 623.7 | BT68: =IF(CE68+AQ68<0, 0, CE68+AQ68) -> 450.73 | BU68: =CB68+CC68 -> 100.87 | BV68: =SUMIFS('SEGURO DE VIDA'!E:E, 'SEGURO DE VIDA'!D:D, H68, 'SEGURO DE VIDA'!G:G, E68) -> 13.71 | BW68: =SUMIFS(TREINAMENTOS!E:E, TREINAMENTOS!D:D, H68, TREINAMENTOS!G:G, E68) -> 598 | BX68: =SUMIFS(EXAMES!E:E, EXAMES!D:D, H68, EXAMES!G:G, E68) -> 0 | BY68: =SUM(BN68:BU68)+SUM(BV68:BX68) -> 2096.5554 | CA68: GEORGIA MARIANA DA SILVA PERE | CB68: =IF(SUM(BB68:BD68)+CF68<0, 0, SUM(BB68:BD68)+CF68) -> 100.87 | CC68: =IF(SUM(AV68:AW68)+CG68<0, 0, SUM(AV68:AW68)+CG68) -> 0 | CD68: =SUMIFS(ALIMENTAÇÃO!E:E, ALIMENTAÇÃO!D:D, H68, ALIMENTAÇÃO!G:G, E68) -> 630 | CE68: =SUMIFS(TRANSPORTE!E:E, TRANSPORTE!D:D, H68, TRANSPORTE!G:G, E68) -> 514.9 | CF68: =SUMIFS('PLANO DE SAÚDE'!E:E, 'PLANO DE SAÚDE'!D:D, H68, 'PLANO DE SAÚDE'!G:G, E68) -> 102.58 | CG68: =SUMIFS('PLANO ODONTO'!E:E, 'PLANO ODONTO'!D:D, H68, 'PLANO ODONTO'!G:G, E68) -> 0 | CH68: =BB68+BC68+BD68 -> -1.71 | CI68: =BI68+BJ68 -> 0 | CJ68: =AA68+AB68 -> 0 | CM68: =AV68+AW68 -> 0 | CN68: 1070.38 | CO68: -153.38 | CP68: 917 | CQ68: 1069.48 | CR68: 7.5 | CS68: 1069.48 | CT68: 21.38 | CU68: 462.28
A69: =IFERROR(__xludf.DUMMYFUNCTION("""COMPUTED_VALUE"""),"EMERSON DA SILVA GOMES") -> EMERSON DA SILVA GOMES | C69: =IF(COUNTIF(A:A, H69)>0, "OK", "Incompleto") -> OK | D69: =AN69+BY69 -> 5477.2013 | E69: 45809 | F69: 07.391.921/0001-71 | G69: 291 | H69: GLAUBER RODRIGUES GOMES | I69: TECNICO DE BROADCAST | J69: 44264 | K69: 3000 | M69: 3000 | O69: 0 | P69: 0 | T69: 400 | Y69: 0 | AD69: 0 | AE69: 0 | AF69: 0 | AM69: 0.48 | AN69: =SUM(M69:AM69) -> 3400.48 | AP69: -6.3 | AQ69: -180 | AT69: -0.99 | AV69: -14 | AW69: -14 | BB69: 0 | BC69: -2.01 | BD69: -251.78 | BF69: 0 | BG69: -253.4 | BH69: 0 | BJ69: 0 | BL69: =SUM(AO69:BK69) -> -722.48 | BM69: =AN69+BL69 -> 2678 | BN69: =K69/12*1 -> 250 | BO69: =K69/12*1 -> 250 | BP69: =BO69/3 -> 83.333333 | BQ69: =CQ69*CR69% -> 253.398 | BR69: =CT69 -> 240 | BS69: =-(-CD69-AP69) -> 623.7 | BT69: =IF(CE69+AQ69<0, 0, CE69+AQ69) -> 144.9 | BU69: =CB69+CC69 -> 17.68 | BV69: =SUMIFS('SEGURO DE VIDA'!E:E, 'SEGURO DE VIDA'!D:D, H69, 'SEGURO DE VIDA'!G:G, E69) -> 13.71 | BW69: =SUMIFS(TREINAMENTOS!E:E, TREINAMENTOS!D:D, H69, TREINAMENTOS!G:G, E69) -> 200 | BX69: =SUMIFS(EXAMES!E:E, EXAMES!D:D, H69, EXAMES!G:G, E69) -> 0 | BY69: =SUM(BN69:BU69)+SUM(BV69:BX69) -> 2076.7213 | CA69: GLAUBER RODRIGUES GOMES | CB69: =IF(SUM(BB69:BD69)+CF69<0, 0, SUM(BB69:BD69)+CF69) -> 17.68 | CC69: =IF(SUM(AV69:AW69)+CG69<0, 0, SUM(AV69:AW69)+CG69) -> 0 | CD69: =SUMIFS(ALIMENTAÇÃO!E:E, ALIMENTAÇÃO!D:D, H69, ALIMENTAÇÃO!G:G, E69) -> 630 | CE69: =SUMIFS(TRANSPORTE!E:E, TRANSPORTE!D:D, H69, TRANSPORTE!G:G, E69) -> 324.9 | CF69: =SUMIFS('PLANO DE SAÚDE'!E:E, 'PLANO DE SAÚDE'!D:D, H69, 'PLANO DE SAÚDE'!G:G, E69) -> 271.47 | CG69: =SUMIFS('PLANO ODONTO'!E:E, 'PLANO ODONTO'!D:D, H69, 'PLANO ODONTO'!G:G, E69) -> 28 | CH69: =BB69+BC69+BD69 -> -253.79 | CI69: =BI69+BJ69 -> 0 | CJ69: =AA69+AB69 -> 0 | CM69: =AV69+AW69 -> -28 | CN69: 3400.48 | CO69: -722.48 | CP69: 2678 | CQ69: 3000 | CR69: 8.4466 | CS69: 3000 | CT69: 240 | CU69: 2367.42
A70: =IFERROR(__xludf.DUMMYFUNCTION("""COMPUTED_VALUE"""),"EMILLY VITORIA CABRAL DANTAS") -> EMILLY VITORIA CABRAL DANTAS | C70: =IF(COUNTIF(A:A, H70)>0, "OK", "Incompleto") -> OK | D70: =AN70+BY70 -> 5014.6368 | E70: 45809 | F70: 07.391.921/0001-71 | G70: 3381 | H70: GLAUBERT RODRIGUES DE JESUS | I70: PEDREIRO | J70: 45194 | K70: 2000 | M70: 2000 | O70: 0 | P70: 600 | T70: 0 | Y70: 0 | AD70: 317.53 | AE70: 223.6 | AF70: 135.28 | AM70: 0.4 | AN70: =SUM(M70:AM70) -> 3276.81 | AP70: -5.7 | AQ70: -120 | AT70: -0.9 | AV70: 0 | BB70: 0 | BC70: 0 | BD70: 0 | BF70: 0 | BG70: -286.57 | BH70: -13.64 | BJ70: 0 | BL70: =SUM(AO70:BK70) -> -426.81 | BM70: =AN70+BL70 -> 2850 | BN70: =K70/12*1 -> 166.66667 | BO70: =K70/12*1 -> 166.66667 | BP70: =BO70/3 -> 55.555556 | BQ70: =CQ70*CR70% -> 286.56792 | BR70: =CT70 -> 262.11 | BS70: =-(-CD70-AP70) -> 564.3 | BT70: =IF(CE70+AQ70<0, 0, CE70+AQ70) -> 22.1 | BU70: =CB70+CC70 -> 200.15 | BV70: =SUMIFS('SEGURO DE VIDA'!E:E, 'SEGURO DE VIDA'!D:D, H70, 'SEGURO DE VIDA'!G:G, E70) -> 13.71 | BW70: =SUMIFS(TREINAMENTOS!E:E, TREINAMENTOS!D:D, H70, TREINAMENTOS!G:G, E70) -> 0 | BX70: =SUMIFS(EXAMES!E:E, EXAMES!D:D, H70, EXAMES!G:G, E70) -> 0 | BY70: =SUM(BN70:BU70)+SUM(BV70:BX70) -> 1737.8268 | CA70: GLAUBERT RODRIGUES DE JESUS | CB70: =IF(SUM(BB70:BD70)+CF70<0, 0, SUM(BB70:BD70)+CF70) -> 200.15 | CC70: =IF(SUM(AV70:AW70)+CG70<0, 0, SUM(AV70:AW70)+CG70) -> 0 | CD70: =SUMIFS(ALIMENTAÇÃO!E:E, ALIMENTAÇÃO!D:D, H70, ALIMENTAÇÃO!G:G, E70) -> 570 | CE70: =SUMIFS(TRANSPORTE!E:E, TRANSPORTE!D:D, H70, TRANSPORTE!G:G, E70) -> 142.1 | CF70: =SUMIFS('PLANO DE SAÚDE'!E:E, 'PLANO DE SAÚDE'!D:D, H70, 'PLANO DE SAÚDE'!G:G, E70) -> 200.15 | CG70: =SUMIFS('PLANO ODONTO'!E:E, 'PLANO ODONTO'!D:D, H70, 'PLANO ODONTO'!G:G, E70) -> 0 | CH70: =BB70+BC70+BD70 -> 0 | CI70: =BI70+BJ70 -> 0 | CJ70: =AA70+AB70 -> 0 | CM70: =AV70+AW70 -> 0 | CN70: 3276.81 | CO70: -426.81 | CP70: 2850 | CQ70: 3276.41 | CR70: 8.7464 | CS70: 3276.41 | CT70: 262.11 | CU70: 2610.66
A71: =IFERROR(__xludf.DUMMYFUNCTION("""COMPUTED_VALUE"""),"ENNYA GOMES OLIVEIRA CAMPOS") -> ENNYA GOMES OLIVEIRA CAMPOS | C71: =IF(COUNTIF(A:A, H71)>0, "OK", "Incompleto") -> OK | D71: =AN71+BY71 -> 2165.9354 | E71: 45809 | F71: 07.391.921/0001-71 | G71: 3509 | H71: GRAZIELLE VITORIA NEVES GOMES | I71: Jovem Aprendiz em Op de St | J71: 45705 | K71: 1069.48 | M71: 1069.48 | O71: 0 | P71: 0 | T71: 0 | Y71: 0 | AD71: 0 | AE71: 0 | AF71: 0 | AM71: 0.45 | AN71: =SUM(M71:AM71) -> 1069.93 | AP71: -6.65 | AQ71: 0 | AT71: -0.68 | AV71: -14 | BB71: -73.68 | BC71: -1.71 | BD71: 0 | BF71: 0 | BG71: -80.21 | BH71: 0 | BJ71: 0 | BL71: =SUM(AO71:BK71) -> -176.93 | BM71: =AN71+BL71 -> 893 | BN71: =K71/12*1 -> 89.123333 | BO71: =K71/12*1 -> 89.123333 | BP71: =BO71/3 -> 29.707778 | BQ71: =CQ71*CR71% -> 80.211 | BR71: =CT71 -> 21.38 | BS71: =-(-CD71-AP71) -> 658.35 | BT71: =IF(CE71+AQ71<0, 0, CE71+AQ71) -> 0 | BU71: =CB71+CC71 -> 114.4 | BV71: =SUMIFS('SEGURO DE VIDA'!E:E, 'SEGURO DE VIDA'!D:D, H71, 'SEGURO DE VIDA'!G:G, E71) -> 13.71 | BW71: =SUMIFS(TREINAMENTOS!E:E, TREINAMENTOS!D:D, H71, TREINAMENTOS!G:G, E71) -> 0 | BX71: =SUMIFS(EXAMES!E:E, EXAMES!D:D, H71, EXAMES!G:G, E71) -> 0 | BY71: =SUM(BN71:BU71)+SUM(BV71:BX71) -> 1096.0054 | CA71: GRAZIELLE VITORIA NEVES GOMES | CB71: =IF(SUM(BB71:BD71)+CF71<0, 0, SUM(BB71:BD71)+CF71) -> 100.87 | CC71: =IF(SUM(AV71:AW71)+CG71<0, 0, SUM(AV71:AW71)+CG71) -> 13.53 | CD71: =SUMIFS(ALIMENTAÇÃO!E:E, ALIMENTAÇÃO!D:D, H71, ALIMENTAÇÃO!G:G, E71) -> 665 | CE71: =SUMIFS(TRANSPORTE!E:E, TRANSPORTE!D:D, H71, TRANSPORTE!G:G, E71) -> 0 | CF71: =SUMIFS('PLANO DE SAÚDE'!E:E, 'PLANO DE SAÚDE'!D:D, H71, 'PLANO DE SAÚDE'!G:G, E71) -> 176.26 | CG71: =SUMIFS('PLANO ODONTO'!E:E, 'PLANO ODONTO'!D:D, H71, 'PLANO ODONTO'!G:G, E71) -> 27.53 | CH71: =BB71+BC71+BD71 -> -75.39 | CI71: =BI71+BJ71 -> 0 | CJ71: =AA71+AB71 -> 0 | CM71: =AV71+AW71 -> -14 | CN71: 1069.93 | CO71: -176.93 | CP71: 893 | CQ71: 1069.48 | CR71: 7.5 | CS71: 1069.48 | CT71: 21.38 | CU71: 462.28
A72: =IFERROR(__xludf.DUMMYFUNCTION("""COMPUTED_VALUE"""),"ENZO ALCÂNTARA CABRAL") -> ENZO ALCÂNTARA CABRAL | C72: =IF(COUNTIF(A:A, H72)>0, "OK", "Incompleto") -> OK | D72: =AN72+BY72 -> 8008.1624 | E72: 45809 | F72: 07.391.921/0001-71 | G72: 3422 | H72: GUSTAVO MACHADO SOEIRO | I72: TECNICO SEGURANÇA DO | J72: 45323 | K72: 2749.59 | M72: 2749.59 | O72: 0 | P72: 824.88 | T72: 0 | Y72: 0 | AB72: 687.39 | AD72: 1184.94 | AE72: 0 | AF72: 296.24 | AM72: 0.58 | AN72: =SUM(M72:AM72) -> 5743.62 | AP72: -5.7 | AQ72: -164.98 | AT72: -0.08 | AV72: -14 | BB72: 0 | BC72: 0 | BD72: -100.08 | BF72: 0 | BG72: -517.37 | BH72: -325.41 | BJ72: 0 | BL72: =SUM(AO72:BK72) -> -1127.62 | BM72: =AN72+BL72 -> 4616 | BN72: =K72/12*1 -> 229.1325 | BO72: =K72/12*1 -> 229.1325 | BP72: =BO72/3 -> 76.3775 | BQ72: =CQ72*CR72% -> 517.36994 | BR72: =CT72 -> 404.45 | BS72: =-(-CD72-AP72) -> 564.3 | BT72: =IF(CE72+AQ72<0, 0, CE72+AQ72) -> 0 | BU72: =CB72+CC72 -> 100.07 | BV72: =SUMIFS('SEGURO DE VIDA'!E:E, 'SEGURO DE VIDA'!D:D, H72, 'SEGURO DE VIDA'!G:G, E72) -> 13.71 | BW72: =SUMIFS(TREINAMENTOS!E:E, TREINAMENTOS!D:D, H72, TREINAMENTOS!G:G, E72) -> 130 | BX72: =SUMIFS(EXAMES!E:E, EXAMES!D:D, H72, EXAMES!G:G, E72) -> 0 | BY72: =SUM(BN72:BU72)+SUM(BV72:BX72) -> 2264.5424 | CA72: GUSTAVO MACHADO SOEIRO | CB72: =IF(SUM(BB72:BD72)+CF72<0, 0, SUM(BB72:BD72)+CF72) -> 100.07 | CC72: =IF(SUM(AV72:AW72)+CG72<0, 0, SUM(AV72:AW72)+CG72) -> 0 | CD72: =SUMIFS(ALIMENTAÇÃO!E:E, ALIMENTAÇÃO!D:D, H72, ALIMENTAÇÃO!G:G, E72) -> 570 | CE72: =SUMIFS(TRANSPORTE!E:E, TRANSPORTE!D:D, H72, TRANSPORTE!G:G, E72) -> 63.7 | CF72: =SUMIFS('PLANO DE SAÚDE'!E:E, 'PLANO DE SAÚDE'!D:D, H72, 'PLANO DE SAÚDE'!G:G, E72) -> 200.15 | CG72: =SUMIFS('PLANO ODONTO'!E:E, 'PLANO ODONTO'!D:D, H72, 'PLANO ODONTO'!G:G, E72) -> 14 | CH72: =BB72+BC72+BD72 -> -100.08 | CI72: =BI72+BJ72 -> 0 | CJ72: =AA72+AB72 -> 687.39 | CM72: =AV72+AW72 -> -14 | CN72: 5743.62 | CO72: -1127.62 | CP72: 4616 | CQ72: 5055.65 | CR72: 10.2335 | CS72: 5055.65 | CT72: 404.45 | CU72: 4448.45
A73: =IFERROR(__xludf.DUMMYFUNCTION("""COMPUTED_VALUE"""),"ESTHER VICTÓRIA DOS SANTOS FARIA") -> ESTHER VICTÓRIA DOS SANTOS FARIA | C73: =IF(COUNTIF(A:A, H73)>0, "OK", "Incompleto") -> OK | D73: =AN73+BY73 -> 7636.9433 | E73: 45809 | F73: 20.258.413/0001-88 | G73: 3 | H73: HUGO DE AQUINO VOLOTÃO | I73: PRO LABORE | M73: 5336.03 | AC73: 0 | AD73: 0 | AE73: 0 | AF73: 0 | AM73: 0 | AN73: =SUM(M73:AM73) -> 5336.03 | AP73: 0 | AQ73: 0 | AR73: 0 | AT73: 0 | AV73: 0 | BB73: 0 | BC73: 0 | BD73: 0 | BG73: -586.96 | BH73: -391.7 | BL73: =SUM(AO73:BK73) -> -978.66 | BM73: =AN73+BL73 -> 4357.37 | BN73: =K73/12*1 -> 0 | BO73: =K73/12*1 -> 0 | BP73: =BO73/3 -> 0 | BQ73: =CQ73*CR73% -> 586.9633 | BR73: =CT73 -> 0 | BS73: =-(-CD73-AP73) -> 700 | BT73: =IF(CE73+AQ73<0, 0, CE73+AQ73) -> 0 | BU73: =CB73+CC73 -> 954.28 | BV73: =SUMIFS('SEGURO DE VIDA'!E:E, 'SEGURO DE VIDA'!D:D, H73, 'SEGURO DE VIDA'!G:G, E73) -> 59.67 | BW73: =SUMIFS(TREINAMENTOS!E:E, TREINAMENTOS!D:D, H73, TREINAMENTOS!G:G, E73) -> 0 | BX73: =SUMIFS(EXAMES!E:E, EXAMES!D:D, H73, EXAMES!G:G, E73) -> 0 | BY73: =SUM(BN73:BU73)+SUM(BV73:BX73) -> 2300.9133 | CA73: HUGO DE AQUINO VOLOTAO | CB73: =IF(SUM(BB73:BD73)+CF73<0, 0, SUM(BB73:BD73)+CF73) -> 898.28 | CC73: =IF(SUM(AV73:AW73)+CG73<0, 0, SUM(AV73:AW73)+CG73) -> 56 | CD73: =SUMIFS(ALIMENTAÇÃO!E:E, ALIMENTAÇÃO!D:D, H73, ALIMENTAÇÃO!G:G, E73) -> 700 | CE73: =SUMIFS(TRANSPORTE!E:E, TRANSPORTE!D:D, H73, TRANSPORTE!G:G, E73) -> 0 | CF73: =SUMIFS('PLANO DE SAÚDE'!E:E, 'PLANO DE SAÚDE'!D:D, H73, 'PLANO DE SAÚDE'!G:G, E73) -> 898.28 | CG73: =SUMIFS('PLANO ODONTO'!E:E, 'PLANO ODONTO'!D:D, H73, 'PLANO ODONTO'!G:G, E73) -> 56 | CH73: =BB73+BC73+BD73 -> 0 | CI73: =BI73+BJ73 -> 0 | CJ73: =AA73+AB73 -> 0 | CM73: =AV73+AW73 -> 0 | CN73: 5336.03 | CO73: -978.66 | CP73: 4357.37 | CQ73: 5336.03 | CR73: 11 | CS73: 0 | CT73: 0 | CU73: 4728.83
A74: =IFERROR(__xludf.DUMMYFUNCTION("""COMPUTED_VALUE"""),"FABIANO DE OLIVEIRA MACHADO") -> FABIANO DE OLIVEIRA MACHADO | C74: =IF(COUNTIF(A:A, H74)>0, "OK", "Incompleto") -> OK | D74: =AN74+BY74 -> 3996.9535 | E74: 45809 | F74: 07.391.921/0001-71 | G74: 3521 | H74: IGOR BARROS DA SILVA | I74: INSTALADOR JUNIOR | J74: 45740 | K74: 1700 | M74: 1700 | O74: 0 | P74: 510 | T74: 0 | Y74: 0 | AD74: 212.44 | AE74: 183.06 | AF74: 98.88 | AM74: 0.74 | AN74: =SUM(M74:AM74) -> 2705.12 | AP74: -4.8 | AQ74: -102 | AT74: -0.7 | AV74: 0 | BB74: 0 | BC74: 0 | BD74: 0 | BF74: 0 | BG74: -220.62 | BH74: 0 | BJ74: 0 | BL74: =SUM(AO74:BK74) -> -328.12 | BM74: =AN74+BL74 -> 2377 | BN74: =K74/12*1 -> 141.66667 | BO74: =K74/12*1 -> 141.66667 | BP74: =BO74/3 -> 47.222222 | BQ74: =CQ74*CR74% -> 220.61791 | BR74: =CT74 -> 216.35 | BS74: =-(-CD74-AP74) -> 475.2 | BT74: =IF(CE74+AQ74<0, 0, CE74+AQ74) -> 25.4 | BU74: =CB74+CC74 -> 0 | BV74: =SUMIFS('SEGURO DE VIDA'!E:E, 'SEGURO DE VIDA'!D:D, H74, 'SEGURO DE VIDA'!G:G, E74) -> 13.71 | BW74: =SUMIFS(TREINAMENTOS!E:E, TREINAMENTOS!D:D, H74, TREINAMENTOS!G:G, E74) -> 0 | BX74: =SUMIFS(EXAMES!E:E, EXAMES!D:D, H74, EXAMES!G:G, E74) -> 10 | BY74: =SUM(BN74:BU74)+SUM(BV74:BX74) -> 1291.8335 | CA74: IGOR BARROS DA SILVA | CB74: =IF(SUM(BB74:BD74)+CF74<0, 0, SUM(BB74:BD74)+CF74) -> 0 | CC74: =IF(SUM(AV74:AW74)+CG74<0, 0, SUM(AV74:AW74)+CG74) -> 0 | CD74: =SUMIFS(ALIMENTAÇÃO!E:E, ALIMENTAÇÃO!D:D, H74, ALIMENTAÇÃO!G:G, E74) -> 480 | CE74: =SUMIFS(TRANSPORTE!E:E, TRANSPORTE!D:D, H74, TRANSPORTE!G:G, E74) -> 127.4 | CF74: =SUMIFS('PLANO DE SAÚDE'!E:E, 'PLANO DE SAÚDE'!D:D, H74, 'PLANO DE SAÚDE'!G:G, E74) -> 0 | CG74: =SUMIFS('PLANO ODONTO'!E:E, 'PLANO ODONTO'!D:D, H74, 'PLANO ODONTO'!G:G, E74) -> 0 | CH74: =BB74+BC74+BD74 -> 0 | CI74: =BI74+BJ74 -> 0 | CJ74: =AA74+AB74 -> 0 | CM74: =AV74+AW74 -> 0 | CN74: 2705.12 | CO74: -328.12 | CP74: 2377 | CQ74: 2704.38 | CR74: 8.1578 | CS74: 2704.38 | CT74: 216.35 | CU74: 2097.18
A75: =IFERROR(__xludf.DUMMYFUNCTION("""COMPUTED_VALUE"""),"FABRICIO LORENCINI ZANONI") -> FABRICIO LORENCINI ZANONI | C75: =IF(COUNTIF(A:A, H75)>0, "OK", "Incompleto") -> OK | D75: =AN75+BY75 -> 8035.05 | E75: 45809 | F75: 07.391.921/0001-71 | G75: 3 | H75: IVAN DE MELLO | I75: PRO LABORE | M75: 4 | AD75: 0 | AE75: 0 | AF75: 0 | AM75: 0 | AN75: =SUM(M75:AM75) -> 4 | AP75: 0 | AQ75: 0 | AR75: 0 | AT75: 0 | AV75: 0 | BB75: 0 | BC75: 0 | BD75: 0 | BG75: -0.44 | BH75: 0 | BL75: =SUM(AO75:BK75) -> -0.44 | BM75: =AN75+BL75 -> 3.56 | BN75: =K75/12*1 -> 0 | BO75: =K75/12*1 -> 0 | BP75: =BO75/3 -> 0 | BQ75: =CQ75*CR75% -> 0.44 | BR75: =CT75 -> 0 | BS75: =-(-CD75-AP75) -> 665 | BT75: =IF(CE75+AQ75<0, 0, CE75+AQ75) -> 0 | BU75: =CB75+CC75 -> 7204.51 | BV75: =SUMIFS('SEGURO DE VIDA'!E:E, 'SEGURO DE VIDA'!D:D, H75, 'SEGURO DE VIDA'!G:G, E75) -> 161.1 | BW75: =SUMIFS(TREINAMENTOS!E:E, TREINAMENTOS!D:D, H75, TREINAMENTOS!G:G, E75) -> 0 | BX75: =SUMIFS(EXAMES!E:E, EXAMES!D:D, H75, EXAMES!G:G, E75) -> 0 | BY75: =SUM(BN75:BU75)+SUM(BV75:BX75) -> 8031.05 | CA75: IVAN DE MELLO | CB75: =IF(SUM(BB75:BD75)+CF75<0, 0, SUM(BB75:BD75)+CF75) -> 7204.51 | CC75: =IF(SUM(AV75:AW75)+CG75<0, 0, SUM(AV75:AW75)+CG75) -> 0 | CD75: =SUMIFS(ALIMENTAÇÃO!E:E, ALIMENTAÇÃO!D:D, H75, ALIMENTAÇÃO!G:G, E75) -> 665 | CE75: =SUMIFS(TRANSPORTE!E:E, TRANSPORTE!D:D, H75, TRANSPORTE!G:G, E75) -> 0 | CF75: =SUMIFS('PLANO DE SAÚDE'!E:E, 'PLANO DE SAÚDE'!D:D, H75, 'PLANO DE SAÚDE'!G:G, E75) -> 7204.51 | CG75: =SUMIFS('PLANO ODONTO'!E:E, 'PLANO ODONTO'!D:D, H75, 'PLANO ODONTO'!G:G, E75) -> 0 | CH75: =BB75+BC75+BD75 -> 0 | CI75: =BI75+BJ75 -> 0 | CJ75: =AA75+AB75 -> 0 | CM75: =AV75+AW75 -> 0 | CN75: 4 | CO75: -0.44 | CP75: 3.56 | CQ75: 4 | CR75: 11 | CS75: 0 | CT75: 0 | CU75: 0
A76: =IFERROR(__xludf.DUMMYFUNCTION("""COMPUTED_VALUE"""),"FELIPE CORREA CONCEIÇÃO") -> FELIPE CORREA CONCEIÇÃO | C76: =IF(COUNTIF(A:A, H76)>0, "OK", "Incompleto") -> OK | D76: =AN76+BY76 -> 5396.2433 | E76: 45809 | F76: 07.391.921/0001-71 | G76: 3387 | H76: JANILSON FERREIRA ACIOLI JUNIOR | I76: INSTALADOR JUNIOR | J76: 45215 | K76: 1664 | M76: 1664 | O76: 88.69 | P76: 499.2 | T76: 0 | Y76: 0 | AD76: 356.12 | AE76: 150.34 | AF76: 148.79 | AM76: 0.66 | AN76: =SUM(M76:AM76) -> 2907.8 | AP76: -6.65 | AQ76: -99.84 | AT76: -0.15 | AV76: 0 | BB76: 0 | BC76: 0 | BD76: -2.01 | BF76: -125.89 | BG76: -242.26 | BH76: 0 | BJ76: 0 | BL76: =SUM(AO76:BK76) -> -476.8 | BM76: =AN76+BL76 -> 2431 | BN76: =K76/12*1 -> 138.66667 | BO76: =K76/12*1 -> 138.66667 | BP76: =BO76/3 -> 46.222222 | BQ76: =CQ76*CR76% -> 242.25779 | BR76: =CT76 -> 232.57 | BS76: =-(-CD76-AP76) -> 658.35 | BT76: =IF(CE76+AQ76<0, 0, CE76+AQ76) -> 225.06 | BU76: =CB76+CC76 -> 193.93 | BV76: =SUMIFS('SEGURO DE VIDA'!E:E, 'SEGURO DE VIDA'!D:D, H76, 'SEGURO DE VIDA'!G:G, E76) -> 13.71 | BW76: =SUMIFS(TREINAMENTOS!E:E, TREINAMENTOS!D:D, H76, TREINAMENTOS!G:G, E76) -> 0 | BX76: =SUMIFS(EXAMES!E:E, EXAMES!D:D, H76, EXAMES!G:G, E76) -> 599.01 | BY76: =SUM(BN76:BU76)+SUM(BV76:BX76) -> 2488.4433 | CA76: JANILSON FERREIRA ACIOLI JUNIOF | CB76: =IF(SUM(BB76:BD76)+CF76<0, 0, SUM(BB76:BD76)+CF76) -> 193.93 | CC76: =IF(SUM(AV76:AW76)+CG76<0, 0, SUM(AV76:AW76)+CG76) -> 0 | CD76: =SUMIFS(ALIMENTAÇÃO!E:E, ALIMENTAÇÃO!D:D, H76, ALIMENTAÇÃO!G:G, E76) -> 665 | CE76: =SUMIFS(TRANSPORTE!E:E, TRANSPORTE!D:D, H76, TRANSPORTE!G:G, E76) -> 324.9 | CF76: =SUMIFS('PLANO DE SAÚDE'!E:E, 'PLANO DE SAÚDE'!D:D, H76, 'PLANO DE SAÚDE'!G:G, E76) -> 195.94 | CG76: =SUMIFS('PLANO ODONTO'!E:E, 'PLANO ODONTO'!D:D, H76, 'PLANO ODONTO'!G:G, E76) -> 0 | CH76: =BB76+BC76+BD76 -> -2.01 | CI76: =BI76+BJ76 -> 0 | CJ76: =AA76+AB76 -> 0 | CM76: =AV76+AW76 -> 0 | CN76: 2907.8 | CO76: -476.8 | CP76: 2431 | CQ76: 2907.14 | CR76: 8.3332 | CS76: 2907.14 | CT76: 232.57 | CU76: 2299.94
A77: =IFERROR(__xludf.DUMMYFUNCTION("""COMPUTED_VALUE"""),"FELIPE GOMES SILVA") -> FELIPE GOMES SILVA | C77: =IF(COUNTIF(A:A, H77)>0, "OK", "Incompleto") -> OK | D77: =AN77+BY77 -> 2916.9199 | E77: 45809 | F77: 07.391.921/0001-71 | G77: 3455 | H77: JEANDERSON CRISTIAN DA SILVA TEIXEIRA | I77: INSTALADOR | J77: 45495 | K77: 1600 | M77: 1600 | O77: 0 | P77: 0 | T77: 0 | Y77: 0 | AD77: 0 | AE77: 0 | AF77: 0 | AM77: 0.77 | AN77: =SUM(M77:AM77) -> 1600.77 | AP77: -6.3 | AQ77: 0 | AT77: -0.23 | AV77: -14 | BB77: 0 | BC77: 0 | BD77: -2.01 | BF77: 0 | BG77: -121.23 | BH77: 0 | BJ77: 0 | BL77: =SUM(AO77:BK77) -> -143.77 | BM77: =AN77+BL77 -> 1457 | BN77: =K77/12*1 -> 133.33333 | BO77: =K77/12*1 -> 133.33333 | BP77: =BO77/3 -> 44.444444 | BQ77: =CQ77*CR77% -> 121.2288 | BR77: =CT77 -> 128 | BS77: =-(-CD77-AP77) -> 623.7 | BT77: =IF(CE77+AQ77<0, 0, CE77+AQ77) -> 0 | BU77: =CB77+CC77 -> 118.4 | BV77: =SUMIFS('SEGURO DE VIDA'!E:E, 'SEGURO DE VIDA'!D:D, H77, 'SEGURO DE VIDA'!G:G, E77) -> 13.71 | BW77: =SUMIFS(TREINAMENTOS!E:E, TREINAMENTOS!D:D, H77, TREINAMENTOS!G:G, E77) -> 0 | BX77: =SUMIFS(EXAMES!E:E, EXAMES!D:D, H77, EXAMES!G:G, E77) -> 0 | BY77: =SUM(BN77:BU77)+SUM(BV77:BX77) -> 1316.1499 | CA77: JEANDERSON CRISTIAN DA SILVA T | CB77: =IF(SUM(BB77:BD77)+CF77<0, 0, SUM(BB77:BD77)+CF77) -> 118.4 | CC77: =IF(SUM(AV77:AW77)+CG77<0, 0, SUM(AV77:AW77)+CG77) -> 0 | CD77: =SUMIFS(ALIMENTAÇÃO!E:E, ALIMENTAÇÃO!D:D, H77, ALIMENTAÇÃO!G:G, E77) -> 630 | CE77: =SUMIFS(TRANSPORTE!E:E, TRANSPORTE!D:D, H77, TRANSPORTE!G:G, E77) -> 0 | CF77: =SUMIFS('PLANO DE SAÚDE'!E:E, 'PLANO DE SAÚDE'!D:D, H77, 'PLANO DE SAÚDE'!G:G, E77) -> 120.41 | CG77: =SUMIFS('PLANO ODONTO'!E:E, 'PLANO ODONTO'!D:D, H77, 'PLANO ODONTO'!G:G, E77) -> 14 | CH77: =BB77+BC77+BD77 -> -2.01 | CI77: =BI77+BJ77 -> 0 | CJ77: =AA77+AB77 -> 0 | CM77: =AV77+AW77 -> -14 | CN77: 1600.77 | CO77: -143.77 | CP77: 1457 | CQ77: 1600 | CR77: 7.5768 | CS77: 1600 | CT77: 128 | CU77: 992.8
A78: =IFERROR(__xludf.DUMMYFUNCTION("""COMPUTED_VALUE"""),"FELIPE TAVARES ARAUJO") -> FELIPE TAVARES ARAUJO | C78: =IF(COUNTIF(A:A, H78)>0, "OK", "Incompleto") -> OK | D78: =AN78+BY78 -> 2986.3567 | E78: 45809 | F78: 07.391.921/0001-71 | G78: 3479 | H78: JENIFFER LUISA CHAGAS DA CONCEIÇÃO | I78: AUX. DE INSTALACAO DE R | J78: 45597 | K78: 1518 | M78: 1518 | O78: 0 | P78: 0 | T78: 0 | Y78: 0 | AD78: 0 | AE78: 0 | AF78: 0 | AM78: 0.45 | AN78: =SUM(M78:AM78) -> 1518.45 | AP78: -5.95 | AQ78: -91.08 | AT78: -0.59 | AV78: 0 | BB78: 0 | BC78: -65.27 | BD78: -1.71 | BF78: 0 | BG78: -113.85 | BH78: 0 | BJ78: 0 | BL78: =SUM(AO78:BK78) -> -278.45 | BM78: =AN78+BL78 -> 1240 | BN78: =K78/12*1 -> 126.5 | BO78: =K78/12*1 -> 126.5 | BP78: =BO78/3 -> 42.166667 | BQ78: =CQ78*CR78% -> 113.85 | BR78: =CT78 -> 121.44 | BS78: =-(-CD78-AP78) -> 589.05 | BT78: =IF(CE78+AQ78<0, 0, CE78+AQ78) -> 233.82 | BU78: =CB78+CC78 -> 100.87 | BV78: =SUMIFS('SEGURO DE VIDA'!E:E, 'SEGURO DE VIDA'!D:D, H78, 'SEGURO DE VIDA'!G:G, E78) -> 13.71 | BW78: =SUMIFS(TREINAMENTOS!E:E, TREINAMENTOS!D:D, H78, TREINAMENTOS!G:G, E78) -> 0 | BX78: =SUMIFS(EXAMES!E:E, EXAMES!D:D, H78, EXAMES!G:G, E78) -> 0 | BY78: =SUM(BN78:BU78)+SUM(BV78:BX78) -> 1467.9067 | CA78: JENIFFER LUISA CHAGAS DA CONC | CB78: =IF(SUM(BB78:BD78)+CF78<0, 0, SUM(BB78:BD78)+CF78) -> 100.87 | CC78: =IF(SUM(AV78:AW78)+CG78<0, 0, SUM(AV78:AW78)+CG78) -> 0 | CD78: =SUMIFS(ALIMENTAÇÃO!E:E, ALIMENTAÇÃO!D:D, H78, ALIMENTAÇÃO!G:G, E78) -> 595 | CE78: =SUMIFS(TRANSPORTE!E:E, TRANSPORTE!D:D, H78, TRANSPORTE!G:G, E78) -> 324.9 | CF78: =SUMIFS('PLANO DE SAÚDE'!E:E, 'PLANO DE SAÚDE'!D:D, H78, 'PLANO DE SAÚDE'!G:G, E78) -> 167.85 | CG78: =SUMIFS('PLANO ODONTO'!E:E, 'PLANO ODONTO'!D:D, H78, 'PLANO ODONTO'!G:G, E78) -> 0 | CH78: =BB78+BC78+BD78 -> -66.98 | CI78: =BI78+BJ78 -> 0 | CJ78: =AA78+AB78 -> 0 | CM78: =AV78+AW78 -> 0 | CN78: 1518.45 | CO78: -278.45 | CP78: 1240 | CQ78: 1518 | CR78: 7.5 | CS78: 1518 | CT78: 121.44 | CU78: 910.8
A79: =IFERROR(__xludf.DUMMYFUNCTION("""COMPUTED_VALUE"""),"FELIPE VARGAS DE SOUZA") -> FELIPE VARGAS DE SOUZA | C79: =IF(COUNTIF(A:A, H79)>0, "OK", "Incompleto") -> OK | D79: =AN79+BY79 -> 2716.0502 | E79: 45809 | F79: 07.391.921/0001-71 | G79: 271 | H79: JHEANCARLOS JESUS DA SILVA | I79: INSTALADOR DE REDES TE | J79: 44127 | K79: 2002.59 | L79: Férias | M79: 1068.05 | O79: 0 | P79: 320.42 | T79: 0 | Y79: 0 | AD79: 173.45 | AE79: 0 | AF79: 43.36 | AM79: 0.09 | AN79: =SUM(M79:AM79) -> 1605.37 | AP79: -2.7 | AQ79: -64.08 | AT79: -0.51 | AV79: 0 | BB79: 0 | BC79: 0 | BD79: -100.08 | BF79: 0 | BG79: -163.4 | BH79: 0 | BJ79: -303.6 | BL79: =SUM(AO79:BK79) -> -634.37 | BM79: =AN79+BL79 -> 971 | BN79: =K79/12*1 -> 166.8825 | BO79: =K79/12*1 -> 166.8825 | BP79: =BO79/3 -> 55.6275 | BQ79: =CQ79*CR79% -> 142.66765 | BR79: =CT79 -> 128.42 | BS79: =-(-CD79-AP79) -> 267.3 | BT79: =IF(CE79+AQ79<0, 0, CE79+AQ79) -> 24.12 | BU79: =CB79+CC79 -> 145.07 | BV79: =SUMIFS('SEGURO DE VIDA'!E:E, 'SEGURO DE VIDA'!D:D, H79, 'SEGURO DE VIDA'!G:G, E79) -> 13.71 | BW79: =SUMIFS(TREINAMENTOS!E:E, TREINAMENTOS!D:D, H79, TREINAMENTOS!G:G, E79) -> 0 | BX79: =SUMIFS(EXAMES!E:E, EXAMES!D:D, H79, EXAMES!G:G, E79) -> 0 | BY79: =SUM(BN79:BU79)+SUM(BV79:BX79) -> 1110.6802 | CA79: JHEANCARLOS JESUS DA SILVA | CB79: =IF(SUM(BB79:BD79)+CF79<0, 0, SUM(BB79:BD79)+CF79) -> 145.07 | CC79: =IF(SUM(AV79:AW79)+CG79<0, 0, SUM(AV79:AW79)+CG79) -> 0 | CD79: =SUMIFS(ALIMENTAÇÃO!E:E, ALIMENTAÇÃO!D:D, H79, ALIMENTAÇÃO!G:G, E79) -> 270 | CE79: =SUMIFS(TRANSPORTE!E:E, TRANSPORTE!D:D, H79, TRANSPORTE!G:G, E79) -> 88.2 | CF79: =SUMIFS('PLANO DE SAÚDE'!E:E, 'PLANO DE SAÚDE'!D:D, H79, 'PLANO DE SAÚDE'!G:G, E79) -> 245.15 | CG79: =SUMIFS('PLANO ODONTO'!E:E, 'PLANO ODONTO'!D:D, H79, 'PLANO ODONTO'!G:G, E79) -> 0 | CH79: =BB79+BC79+BD79 -> -100.08 | CI79: =BI79+BJ79 -> -303.6 | CJ79: =AA79+AB79 -> 0 | CM79: =AV79+AW79 -> 0 | CN79: 1605.37 | CO79: -634.37 | CP79: 971 | CQ79: 1605.28 | CR79: 8.8874 | CS79: 1605.28 | CT79: 128.42 | CU79: 998.08
A80: =IFERROR(__xludf.DUMMYFUNCTION("""COMPUTED_VALUE"""),"FERNANDA GIOIA GONÇALVES VAZ") -> FERNANDA GIOIA GONÇALVES VAZ | C80: =IF(COUNTIF(A:A, H80)>0, "OK", "Incompleto") -> OK | D80: =AN80+BY80 -> 1377.7433 | E80: 45809 | F80: 07.391.921/0001-71 | G80: 3543 | H80: JOÃO GABRIEL DE LIMA PEREIRA | I80: ESTAGIARIO EM TELECOM | J80: 45824 | K80: 750 | M80: 375 | O80: 0 | P80: 0 | T80: 0 | Y80: 0 | AD80: 0 | AE80: 0 | AF80: 0 | AM80: 0.8 | AN80: =SUM(M80:AM80) -> 375.8 | AP80: -1.8 | AQ80: 0 | AT80: 0 | AV80: 0 | BB80: 0 | BC80: 0 | BD80: 0 | BF80: 0 | BG80: 0 | BH80: 0 | BJ80: 0 | BL80: =SUM(AO80:BK80) -> -1.8 | BM80: =AN80+BL80 -> 374 | BN80: =K80/12*1 -> 62.5 | BO80: =K80/12*1 -> 62.5 | BP80: =BO80/3 -> 20.833333 | BQ80: =CQ80*CR80% -> 0 | BR80: =CT80 -> 0 | BS80: =-(-CD80-AP80) -> 103.2 | BT80: =IF(CE80+AQ80<0, 0, CE80+AQ80) -> 153.9 | BU80: =CB80+CC80 -> 0 | BV80: =SUMIFS('SEGURO DE VIDA'!E:E, 'SEGURO DE VIDA'!D:D, H80, 'SEGURO DE VIDA'!G:G, E80) -> 0 | BW80: =SUMIFS(TREINAMENTOS!E:E, TREINAMENTOS!D:D, H80, TREINAMENTOS!G:G, E80) -> 0 | BX80: =SUMIFS(EXAMES!E:E, EXAMES!D:D, H80, EXAMES!G:G, E80) -> 599.01 | BY80: =SUM(BN80:BU80)+SUM(BV80:BX80) -> 1001.9433 | CA80: JOAO GABRIEL DE LIMA PEREIRA | CB80: =IF(SUM(BB80:BD80)+CF80<0, 0, SUM(BB80:BD80)+CF80) -> 0 | CC80: =IF(SUM(AV80:AW80)+CG80<0, 0, SUM(AV80:AW80)+CG80) -> 0 | CD80: =SUMIFS(ALIMENTAÇÃO!E:E, ALIMENTAÇÃO!D:D, H80, ALIMENTAÇÃO!G:G, E80) -> 105 | CE80: =SUMIFS(TRANSPORTE!E:E, TRANSPORTE!D:D, H80, TRANSPORTE!G:G, E80) -> 153.9 | CF80: =SUMIFS('PLANO DE SAÚDE'!E:E, 'PLANO DE SAÚDE'!D:D, H80, 'PLANO DE SAÚDE'!G:G, E80) -> 0 | CG80: =SUMIFS('PLANO ODONTO'!E:E, 'PLANO ODONTO'!D:D, H80, 'PLANO ODONTO'!G:G, E80) -> 0 | CH80: =BB80+BC80+BD80 -> 0 | CI80: =BI80+BJ80 -> 0 | CJ80: =AA80+AB80 -> 0 | CM80: =AV80+AW80 -> 0 | CN80: 375.8 | CO80: -1.8 | CP80: 374 | CQ80: 0 | CR80: 0 | CS80: 0 | CT80: 0 | CU80: 0
A81: =IFERROR(__xludf.DUMMYFUNCTION("""COMPUTED_VALUE"""),"FERNANDO MENDONÇA FERNANDES") -> FERNANDO MENDONÇA FERNANDES | C81: =IF(COUNTIF(A:A, H81)>0, "OK", "Incompleto") -> OK | D81: =AN81+BY81 -> 4037.9778 | E81: 45809 | F81: 07.391.921/0001-71 | G81: 3458 | H81: JOAO PAULO TAVARES SILVA | I81: AUX. COMPRAS JR. | J81: 45505 | K81: 2200 | M81: 2200 | O81: 0 | P81: 0 | T81: 0 | Y81: 0 | AD81: 0 | AE81: 0 | AF81: 0 | AM81: 0.07 | AN81: =SUM(M81:AM81) -> 2200.07 | AP81: -6.65 | AQ81: -132 | AT81: -0.89 | AV81: -14 | BB81: 0 | BC81: -13.41 | BD81: -2 | BF81: -125.89 | BG81: -175.23 | BH81: 0 | BJ81: 0 | BL81: =SUM(AO81:BK81) -> -470.07 | BM81: =AN81+BL81 -> 1730 | BN81: =K81/12*1 -> 183.33333 | BO81: =K81/12*1 -> 183.33333 | BP81: =BO81/3 -> 61.111111 | BQ81: =CQ81*CR81% -> 175.23 | BR81: =CT81 -> 176 | BS81: =-(-CD81-AP81) -> 658.35 | BT81: =IF(CE81+AQ81<0, 0, CE81+AQ81) -> 192.9 | BU81: =CB81+CC81 -> 193.94 | BV81: =SUMIFS('SEGURO DE VIDA'!E:E, 'SEGURO DE VIDA'!D:D, H81, 'SEGURO DE VIDA'!G:G, E81) -> 13.71 | BW81: =SUMIFS(TREINAMENTOS!E:E, TREINAMENTOS!D:D, H81, TREINAMENTOS!G:G, E81) -> 0 | BX81: =SUMIFS(EXAMES!E:E, EXAMES!D:D, H81, EXAMES!G:G, E81) -> 0 | BY81: =SUM(BN81:BU81)+SUM(BV81:BX81) -> 1837.9078 | CA81: JOAO PAULO TAVARES SILVA | CB81: =IF(SUM(BB81:BD81)+CF81<0, 0, SUM(BB81:BD81)+CF81) -> 193.94 | CC81: =IF(SUM(AV81:AW81)+CG81<0, 0, SUM(AV81:AW81)+CG81) -> 0 | CD81: =SUMIFS(ALIMENTAÇÃO!E:E, ALIMENTAÇÃO!D:D, H81, ALIMENTAÇÃO!G:G, E81) -> 665 | CE81: =SUMIFS(TRANSPORTE!E:E, TRANSPORTE!D:D, H81, TRANSPORTE!G:G, E81) -> 324.9 | CF81: =SUMIFS('PLANO DE SAÚDE'!E:E, 'PLANO DE SAÚDE'!D:D, H81, 'PLANO DE SAÚDE'!G:G, E81) -> 209.35 | CG81: =SUMIFS('PLANO ODONTO'!E:E, 'PLANO ODONTO'!D:D, H81, 'PLANO ODONTO'!G:G, E81) -> 14 | CH81: =BB81+BC81+BD81 -> -15.41 | CI81: =BI81+BJ81 -> 0 | CJ81: =AA81+AB81 -> 0 | CM81: =AV81+AW81 -> -14 | CN81: 2200.07 | CO81: -470.07 | CP81: 1730 | CQ81: 2200 | CR81: 7.965 | CS81: 2200 | CT81: 176 | CU81: 1592.8
A82: =IFERROR(__xludf.DUMMYFUNCTION("""COMPUTED_VALUE"""),"FERNANDO PAIVA SILVA DE SOUZA") -> FERNANDO PAIVA SILVA DE SOUZA | C82: =IF(COUNTIF(A:A, H82)>0, "OK", "Incompleto") -> OK | D82: =AN82+BY82 -> 710.94222 | E82: 45809 | F82: 07.391.921/0001-71 | G82: 3556 | H82: JOÃO VICTOR VASCONCELLOS DE SOUSA | I82: ESTAGIARIO(A) | J82: 45831 | K82: 950 | M82: 253.33 | O82: 0 | P82: 0 | T82: 0 | Y82: 0 | AD82: 0 | AE82: 0 | AF82: 0 | AM82: 0.77 | AN82: =SUM(M82:AM82) -> 254.1 | AP82: -2.1 | AQ82: 0 | AT82: 0 | AV82: 0 | BB82: 0 | BC82: 0 | BD82: 0 | BF82: 0 | BG82: 0 | BH82: 0 | BJ82: 0 | BL82: =SUM(AO82:BK82) -> -2.1 | BM82: =AN82+BL82 -> 252 | BN82: =K82/12*1 -> 79.166667 | BO82: =K82/12*1 -> 79.166667 | BP82: =BO82/3 -> 26.388889 | BQ82: =CQ82*CR82% -> 0 | BR82: =CT82 -> 0 | BS82: =-(-CD82-AP82) -> 207.9 | BT82: =IF(CE82+AQ82<0, 0, CE82+AQ82) -> 17.1 | BU82: =CB82+CC82 -> 0 | BV82: =SUMIFS('SEGURO DE VIDA'!E:E, 'SEGURO DE VIDA'!D:D, H82, 'SEGURO DE VIDA'!G:G, E82) -> 0 | BW82: =SUMIFS(TREINAMENTOS!E:E, TREINAMENTOS!D:D, H82, TREINAMENTOS!G:G, E82) -> 0 | BX82: =SUMIFS(EXAMES!E:E, EXAMES!D:D, H82, EXAMES!G:G, E82) -> 47.12 | BY82: =SUM(BN82:BU82)+SUM(BV82:BX82) -> 456.84222 | CA82: JOAO VICTOR VASCONCELLOS DES | CB82: =IF(SUM(BB82:BD82)+CF82<0, 0, SUM(BB82:BD82)+CF82) -> 0 | CC82: =IF(SUM(AV82:AW82)+CG82<0, 0, SUM(AV82:AW82)+CG82) -> 0 | CD82: =SUMIFS(ALIMENTAÇÃO!E:E, ALIMENTAÇÃO!D:D, H82, ALIMENTAÇÃO!G:G, E82) -> 210 | CE82: =SUMIFS(TRANSPORTE!E:E, TRANSPORTE!D:D, H82, TRANSPORTE!G:G, E82) -> 17.1 | CF82: =SUMIFS('PLANO DE SAÚDE'!E:E, 'PLANO DE SAÚDE'!D:D, H82, 'PLANO DE SAÚDE'!G:G, E82) -> 0 | CG82: =SUMIFS('PLANO ODONTO'!E:E, 'PLANO ODONTO'!D:D, H82, 'PLANO ODONTO'!G:G, E82) -> 0 | CH82: =BB82+BC82+BD82 -> 0 | CI82: =BI82+BJ82 -> 0 | CJ82: =AA82+AB82 -> 0 | CM82: =AV82+AW82 -> 0 | CN82: 254.1 | CO82: -2.1 | CP82: 252 | CQ82: 0 | CR82: 0 | CS82: 0 | CT82: 0 | CU82: 0
A83: =IFERROR(__xludf.DUMMYFUNCTION("""COMPUTED_VALUE"""),"FILIPE DE SOUSA BOLONINI") -> FILIPE DE SOUSA BOLONINI | C83: =IF(COUNTIF(A:A, H83)>0, "OK", "Incompleto") -> OK | D83: =AN83+BY83 -> 866.44222 | E83: 45809 | F83: 07.391.921/0001-71 | G83: 3557 | H83: JOÃO VITOR MOÇO SANTOS | I83: ESTAGIÁRIO (A) | J83: 45831 | K83: 950 | M83: 253.33 | O83: 0 | P83: 0 | T83: 0 | Y83: 0 | AD83: 0 | AE83: 0 | AF83: 0 | AM83: 0.77 | AN83: =SUM(M83:AM83) -> 254.1 | AP83: -2.1 | AQ83: 0 | AT83: 0 | AV83: 0 | BB83: 0 | BC83: 0 | BD83: 0 | BF83: 0 | BG83: 0 | BH83: 0 | BJ83: 0 | BL83: =SUM(AO83:BK83) -> -2.1 | BM83: =AN83+BL83 -> 252 | BN83: =K83/12*1 -> 79.166667 | BO83: =K83/12*1 -> 79.166667 | BP83: =BO83/3 -> 26.388889 | BQ83: =CQ83*CR83% -> 0 | BR83: =CT83 -> 0 | BS83: =-(-CD83-AP83) -> 207.9 | BT83: =IF(CE83+AQ83<0, 0, CE83+AQ83) -> 172.6 | BU83: =CB83+CC83 -> 0 | BV83: =SUMIFS('SEGURO DE VIDA'!E:E, 'SEGURO DE VIDA'!D:D, H83, 'SEGURO DE VIDA'!G:G, E83) -> 0 | BW83: =SUMIFS(TREINAMENTOS!E:E, TREINAMENTOS!D:D, H83, TREINAMENTOS!G:G, E83) -> 0 | BX83: =SUMIFS(EXAMES!E:E, EXAMES!D:D, H83, EXAMES!G:G, E83) -> 47.12 | BY83: =SUM(BN83:BU83)+SUM(BV83:BX83) -> 612.34222 | CA83: JOAO VITOR MOCO SANTOS | CB83: =IF(SUM(BB83:BD83)+CF83<0, 0, SUM(BB83:BD83)+CF83) -> 0 | CC83: =IF(SUM(AV83:AW83)+CG83<0, 0, SUM(AV83:AW83)+CG83) -> 0 | CD83: =SUMIFS(ALIMENTAÇÃO!E:E, ALIMENTAÇÃO!D:D, H83, ALIMENTAÇÃO!G:G, E83) -> 210 | CE83: =SUMIFS(TRANSPORTE!E:E, TRANSPORTE!D:D, H83, TRANSPORTE!G:G, E83) -> 172.6 | CF83: =SUMIFS('PLANO DE SAÚDE'!E:E, 'PLANO DE SAÚDE'!D:D, H83, 'PLANO DE SAÚDE'!G:G, E83) -> 0 | CG83: =SUMIFS('PLANO ODONTO'!E:E, 'PLANO ODONTO'!D:D, H83, 'PLANO ODONTO'!G:G, E83) -> 0 | CH83: =BB83+BC83+BD83 -> 0 | CI83: =BI83+BJ83 -> 0 | CJ83: =AA83+AB83 -> 0 | CM83: =AV83+AW83 -> 0 | CN83: 254.1 | CO83: -2.1 | CP83: 252 | CQ83: 0 | CR83: 0 | CS83: 0 | CT83: 0 | CU83: 0
A84: =IFERROR(__xludf.DUMMYFUNCTION("""COMPUTED_VALUE"""),"FILIPE FERREIRA AGRA DE ARAUJO") -> FILIPE FERREIRA AGRA DE ARAUJO | C84: =IF(COUNTIF(A:A, H84)>0, "OK", "Incompleto") -> OK | D84: =AN84+BY84 -> 5817.4823 | E84: 45809 | F84: 07.391.921/0001-71 | G84: 190 | H84: JORGE LUIZ RAMOS JUNIOR | I84: SUPERVISOR TECNICO DE | J84: 42248 | K84: 3791.24 | M84: 3791.24 | O84: 0 | P84: 0 | T84: 0 | Y84: 0 | AD84: 0 | AE84: 0 | AF84: 0 | AM84: 0.01 | AN84: =SUM(M84:AM84) -> 3791.25 | AP84: -6.3 | AQ84: 0 | AT84: -0.96 | AV84: -14 | AY84: -37.91 | BB84: 0 | BC84: -34.55 | BD84: -442.73 | BF84: 0 | BG84: -348.35 | BH84: -83.45 | BJ84: 0 | BL84: =SUM(AO84:BK84) -> -968.25 | BM84: =AN84+BL84 -> 2823 | BN84: =K84/12*1 -> 315.93667 | BO84: =K84/12*1 -> 315.93667 | BP84: =BO84/3 -> 105.31222 | BQ84: =CQ84*CR84% -> 348.34671 | BR84: =CT84 -> 303.29 | BS84: =-(-CD84-AP84) -> 623.7 | BT84: =IF(CE84+AQ84<0, 0, CE84+AQ84) -> 0 | BU84: =CB84+CC84 -> 0 | BV84: =SUMIFS('SEGURO DE VIDA'!E:E, 'SEGURO DE VIDA'!D:D, H84, 'SEGURO DE VIDA'!G:G, E84) -> 13.71 | BW84: =SUMIFS(TREINAMENTOS!E:E, TREINAMENTOS!D:D, H84, TREINAMENTOS!G:G, E84) -> 0 | BX84: =SUMIFS(EXAMES!E:E, EXAMES!D:D, H84, EXAMES!G:G, E84) -> 0 | BY84: =SUM(BN84:BU84)+SUM(BV84:BX84) -> 2026.2323 | CA84: JORGE LUIZ RAMOS JUNIOR | CB84: =IF(SUM(BB84:BD84)+CF84<0, 0, SUM(BB84:BD84)+CF84) -> 0 | CC84: =IF(SUM(AV84:AW84)+CG84<0, 0, SUM(AV84:AW84)+CG84) -> 0 | CD84: =SUMIFS(ALIMENTAÇÃO!E:E, ALIMENTAÇÃO!D:D, H84, ALIMENTAÇÃO!G:G, E84) -> 630 | CE84: =SUMIFS(TRANSPORTE!E:E, TRANSPORTE!D:D, H84, TRANSPORTE!G:G, E84) -> 0 | CF84: =SUMIFS('PLANO DE SAÚDE'!E:E, 'PLANO DE SAÚDE'!D:D, H84, 'PLANO DE SAÚDE'!G:G, E84) -> 439.38 | CG84: =SUMIFS('PLANO ODONTO'!E:E, 'PLANO ODONTO'!D:D, H84, 'PLANO ODONTO'!G:G, E84) -> 14 | CH84: =BB84+BC84+BD84 -> -477.28 | CI84: =BI84+BJ84 -> 0 | CJ84: =AA84+AB84 -> 0 | CM84: =AV84+AW84 -> -14 | CN84: 3791.25 | CO84: -968.25 | CP84: 2823 | CQ84: 3791.24 | CR84: 9.1882 | CS84: 3791.24 | CT84: 303.29 | CU84: 3184.04
A85: =IFERROR(__xludf.DUMMYFUNCTION("""COMPUTED_VALUE"""),"FLAVIANO DE ALMEIDA DOS SANTOS") -> FLAVIANO DE ALMEIDA DOS SANTOS | C85: =IF(COUNTIF(A:A, H85)>0, "OK", "Incompleto") -> OK | D85: =AN85+BY85 -> 1792.6778 | E85: 45809 | F85: 07.391.921/0001-71 | G85: 3503 | H85: JOYCE DE OLIVEIRA MOTA | I85: ESTAGIÁRIO (A) AUXILIAR / | J85: 45677 | K85: 850 | M85: 850 | O85: 0 | P85: 0 | T85: 0 | Y85: 0 | AD85: 0 | AE85: 0 | AF85: 0 | AM85: 0.6 | AN85: =SUM(M85:AM85) -> 850.6 | AP85: -5.7 | AQ85: 0 | AT85: -0.9 | AV85: -14 | BB85: 0 | BC85: 0 | BD85: 0 | BF85: 0 | BG85: 0 | BH85: 0 | BJ85: 0 | BL85: =SUM(AO85:BK85) -> -20.6 | BM85: =AN85+BL85 -> 830 | BN85: =K85/12*1 -> 70.833333 | BO85: =K85/12*1 -> 70.833333 | BP85: =BO85/3 -> 23.611111 | BQ85: =CQ85*CR85% -> 0 | BR85: =CT85 -> 0 | BS85: =-(-CD85-AP85) -> 564.3 | BT85: =IF(CE85+AQ85<0, 0, CE85+AQ85) -> 186.2 | BU85: =CB85+CC85 -> 12.59 | BV85: =SUMIFS('SEGURO DE VIDA'!E:E, 'SEGURO DE VIDA'!D:D, H85, 'SEGURO DE VIDA'!G:G, E85) -> 13.71 | BW85: =SUMIFS(TREINAMENTOS!E:E, TREINAMENTOS!D:D, H85, TREINAMENTOS!G:G, E85) -> 0 | BX85: =SUMIFS(EXAMES!E:E, EXAMES!D:D, H85, EXAMES!G:G, E85) -> 0 | BY85: =SUM(BN85:BU85)+SUM(BV85:BX85) -> 942.07778 | CA85: JOYCE DE OLIVEIRA ΜΟΤΑ | CB85: =IF(SUM(BB85:BD85)+CF85<0, 0, SUM(BB85:BD85)+CF85) -> 0 | CC85: =IF(SUM(AV85:AW85)+CG85<0, 0, SUM(AV85:AW85)+CG85) -> 12.59 | CD85: =SUMIFS(ALIMENTAÇÃO!E:E, ALIMENTAÇÃO!D:D, H85, ALIMENTAÇÃO!G:G, E85) -> 570 | CE85: =SUMIFS(TRANSPORTE!E:E, TRANSPORTE!D:D, H85, TRANSPORTE!G:G, E85) -> 186.2 | CF85: =SUMIFS('PLANO DE SAÚDE'!E:E, 'PLANO DE SAÚDE'!D:D, H85, 'PLANO DE SAÚDE'!G:G, E85) -> 0 | CG85: =SUMIFS('PLANO ODONTO'!E:E, 'PLANO ODONTO'!D:D, H85, 'PLANO ODONTO'!G:G, E85) -> 26.59 | CH85: =BB85+BC85+BD85 -> 0 | CI85: =BI85+BJ85 -> 0 | CJ85: =AA85+AB85 -> 0 | CM85: =AV85+AW85 -> -14 | CN85: 850.6 | CO85: -20.6 | CP85: 830 | CQ85: 0 | CR85: 0 | CS85: 0 | CT85: 0 | CU85: 242.8
A86: =IFERROR(__xludf.DUMMYFUNCTION("""COMPUTED_VALUE"""),"FRANCISCO DA SILVA ALVES") -> FRANCISCO DA SILVA ALVES | C86: =IF(COUNTIF(A:A, H86)>0, "OK", "Incompleto") -> OK | D86: =AN86+BY86 -> 3495.7293 | E86: 45809 | F86: 07.391.921/0001-71 | G86: 3477 | H86: JUAN PATRICK MOURA NUNES | I86: INSTALADOR JUNIOR | J86: 45593 | K86: 1600 | M86: 1600 | O86: 0 | P86: 480 | T86: 0 | Y86: 0 | AD86: 0 | AE86: 0 | AF86: 0 | AM86: 0.85 | AN86: =SUM(M86:AM86) -> 2080.85 | AP86: -6.65 | AQ86: 0 | AT86: -0.07 | AV86: -14 | BB86: 0 | BC86: 0 | BD86: -1.7 | BF86: 0 | BG86: -164.43 | BH86: 0 | BJ86: 0 | BL86: =SUM(AO86:BK86) -> -186.85 | BM86: =AN86+BL86 -> 1894 | BN86: =K86/12*1 -> 133.33333 | BO86: =K86/12*1 -> 133.33333 | BP86: =BO86/3 -> 44.444444 | BQ86: =CQ86*CR86% -> 164.42816 | BR86: =CT86 -> 166.4 | BS86: =-(-CD86-AP86) -> 658.35 | BT86: =IF(CE86+AQ86<0, 0, CE86+AQ86) -> 0 | BU86: =CB86+CC86 -> 100.88 | BV86: =SUMIFS('SEGURO DE VIDA'!E:E, 'SEGURO DE VIDA'!D:D, H86, 'SEGURO DE VIDA'!G:G, E86) -> 13.71 | BW86: =SUMIFS(TREINAMENTOS!E:E, TREINAMENTOS!D:D, H86, TREINAMENTOS!G:G, E86) -> 0 | BX86: =SUMIFS(EXAMES!E:E, EXAMES!D:D, H86, EXAMES!G:G, E86) -> 0 | BY86: =SUM(BN86:BU86)+SUM(BV86:BX86) -> 1414.8793 | CA86: JUAN PATRICK MOURA NUNES | CB86: =IF(SUM(BB86:BD86)+CF86<0, 0, SUM(BB86:BD86)+CF86) -> 100.88 | CC86: =IF(SUM(AV86:AW86)+CG86<0, 0, SUM(AV86:AW86)+CG86) -> 0 | CD86: =SUMIFS(ALIMENTAÇÃO!E:E, ALIMENTAÇÃO!D:D, H86, ALIMENTAÇÃO!G:G, E86) -> 665 | CE86: =SUMIFS(TRANSPORTE!E:E, TRANSPORTE!D:D, H86, TRANSPORTE!G:G, E86) -> 0 | CF86: =SUMIFS('PLANO DE SAÚDE'!E:E, 'PLANO DE SAÚDE'!D:D, H86, 'PLANO DE SAÚDE'!G:G, E86) -> 102.58 | CG86: =SUMIFS('PLANO ODONTO'!E:E, 'PLANO ODONTO'!D:D, H86, 'PLANO ODONTO'!G:G, E86) -> 14 | CH86: =BB86+BC86+BD86 -> -1.7 | CI86: =BI86+BJ86 -> 0 | CJ86: =AA86+AB86 -> 0 | CM86: =AV86+AW86 -> -14 | CN86: 2080.85 | CO86: -186.85 | CP86: 1894 | CQ86: 2080 | CR86: 7.9052 | CS86: 2080 | CT86: 166.4 | CU86: 1472.8
A87: =IFERROR(__xludf.DUMMYFUNCTION("""COMPUTED_VALUE"""),"FREDERICO TAVARES GOMES DA CUNHA") -> FREDERICO TAVARES GOMES DA CUNHA | C87: =IF(COUNTIF(A:A, H87)>0, "OK", "Incompleto") -> OK | D87: =AN87+BY87 -> 1688.8599 | E87: 45809 | F87: 07.391.921/0001-71 | G87: 3542 | H87: JULIANA DA SILVA SILVEIRA | I87: APRENDIZ AUXILIAR DE ES | J87: 45824 | K87: 1069.48 | M87: 534.74 | O87: 0 | P87: 0 | T87: 0 | Y87: 0 | AD87: 0 | AE87: 0 | AF87: 0 | AM87: 0.51 | AN87: =SUM(M87:AM87) -> 535.25 | AP87: -3.15 | AQ87: 0 | AT87: 0 | AV87: 0 | BB87: 0 | BC87: 0 | BD87: 0 | BF87: 0 | BG87: -40.1 | BH87: 0 | BJ87: 0 | BL87: =SUM(AO87:BK87) -> -43.25 | BM87: =AN87+BL87 -> 492 | BN87: =K87/12*1 -> 89.123333 | BO87: =K87/12*1 -> 89.123333 | BP87: =BO87/3 -> 29.707778 | BQ87: =CQ87*CR87% -> 40.1055 | BR87: =CT87 -> 10.69 | BS87: =-(-CD87-AP87) -> -3.15 | BT87: =IF(CE87+AQ87<0, 0, CE87+AQ87) -> 0 | BU87: =CB87+CC87 -> 0 | BV87: =SUMIFS('SEGURO DE VIDA'!E:E, 'SEGURO DE VIDA'!D:D, H87, 'SEGURO DE VIDA'!G:G, E87) -> 0 | BW87: =SUMIFS(TREINAMENTOS!E:E, TREINAMENTOS!D:D, H87, TREINAMENTOS!G:G, E87) -> 299 | BX87: =SUMIFS(EXAMES!E:E, EXAMES!D:D, H87, EXAMES!G:G, E87) -> 599.01 | BY87: =SUM(BN87:BU87)+SUM(BV87:BX87) -> 1153.6099 | CA87: JULIANA DA SILVA SILVEIRA | CB87: =IF(SUM(BB87:BD87)+CF87<0, 0, SUM(BB87:BD87)+CF87) -> 0 | CC87: =IF(SUM(AV87:AW87)+CG87<0, 0, SUM(AV87:AW87)+CG87) -> 0 | CD87: =SUMIFS(ALIMENTAÇÃO!E:E, ALIMENTAÇÃO!D:D, H87, ALIMENTAÇÃO!G:G, E87) -> 0 | CE87: =SUMIFS(TRANSPORTE!E:E, TRANSPORTE!D:D, H87, TRANSPORTE!G:G, E87) -> 0 | CF87: =SUMIFS('PLANO DE SAÚDE'!E:E, 'PLANO DE SAÚDE'!D:D, H87, 'PLANO DE SAÚDE'!G:G, E87) -> 0 | CG87: =SUMIFS('PLANO ODONTO'!E:E, 'PLANO ODONTO'!D:D, H87, 'PLANO ODONTO'!G:G, E87) -> 0 | CH87: =BB87+BC87+BD87 -> 0 | CI87: =BI87+BJ87 -> 0 | CJ87: =AA87+AB87 -> 0 | CM87: =AV87+AW87 -> 0 | CN87: 535.25 | CO87: -43.25 | CP87: 492 | CQ87: 534.74 | CR87: 7.5 | CS87: 534.74 | CT87: 10.69 | CU87: 0
A88: =IFERROR(__xludf.DUMMYFUNCTION("""COMPUTED_VALUE"""),"GABRIEL CARVALHO PEREIRA") -> GABRIEL CARVALHO PEREIRA | C88: =IF(COUNTIF(A:A, H88)>0, "OK", "Incompleto") -> OK | D88: =AN88+BY88 -> 4160.383 | E88: 45809 | F88: 07.391.921/0001-71 | G88: 3520 | H88: KAIKE PENHA SOARES | I88: INSTALADOR JUNIOR | J88: 45740 | K88: 1700 | M88: 1700 | O88: 0 | P88: 510 | T88: 0 | Y88: 0 | AD88: 146.41 | AE88: 190.06 | AF88: 84.12 | AM88: 0.61 | AN88: =SUM(M88:AM88) -> 2631.2 | AP88: -5.7 | AQ88: 0 | AT88: -0.52 | AV88: 0 | BB88: 0 | BC88: 0 | BD88: 0 | BF88: 0 | BG88: -213.98 | BH88: 0 | BJ88: 0 | BL88: =SUM(AO88:BK88) -> -220.2 | BM88: =AN88+BL88 -> 2411 | BN88: =K88/12*1 -> 141.66667 | BO88: =K88/12*1 -> 141.66667 | BP88: =BO88/3 -> 47.222222 | BQ88: =CQ88*CR88% -> 213.97745 | BR88: =CT88 -> 210.44 | BS88: =-(-CD88-AP88) -> 564.3 | BT88: =IF(CE88+AQ88<0, 0, CE88+AQ88) -> 186.2 | BU88: =CB88+CC88 -> 0 | BV88: =SUMIFS('SEGURO DE VIDA'!E:E, 'SEGURO DE VIDA'!D:D, H88, 'SEGURO DE VIDA'!G:G, E88) -> 13.71 | BW88: =SUMIFS(TREINAMENTOS!E:E, TREINAMENTOS!D:D, H88, TREINAMENTOS!G:G, E88) -> 0 | BX88: =SUMIFS(EXAMES!E:E, EXAMES!D:D, H88, EXAMES!G:G, E88) -> 10 | BY88: =SUM(BN88:BU88)+SUM(BV88:BX88) -> 1529.183 | CA88: ΚΑIKE PENHA SOARES | CB88: =IF(SUM(BB88:BD88)+CF88<0, 0, SUM(BB88:BD88)+CF88) -> 0 | CC88: =IF(SUM(AV88:AW88)+CG88<0, 0, SUM(AV88:AW88)+CG88) -> 0 | CD88: =SUMIFS(ALIMENTAÇÃO!E:E, ALIMENTAÇÃO!D:D, H88, ALIMENTAÇÃO!G:G, E88) -> 570 | CE88: =SUMIFS(TRANSPORTE!E:E, TRANSPORTE!D:D, H88, TRANSPORTE!G:G, E88) -> 186.2 | CF88: =SUMIFS('PLANO DE SAÚDE'!E:E, 'PLANO DE SAÚDE'!D:D, H88, 'PLANO DE SAÚDE'!G:G, E88) -> 0 | CG88: =SUMIFS('PLANO ODONTO'!E:E, 'PLANO ODONTO'!D:D, H88, 'PLANO ODONTO'!G:G, E88) -> 0 | CH88: =BB88+BC88+BD88 -> 0 | CI88: =BI88+BJ88 -> 0 | CJ88: =AA88+AB88 -> 0 | CM88: =AV88+AW88 -> 0 | CN88: 2631.2 | CO88: -220.2 | CP88: 2411 | CQ88: 2630.59 | CR88: 8.1342 | CS88: 2630.59 | CT88: 210.44 | CU88: 2023.39
A89: =IFERROR(__xludf.DUMMYFUNCTION("""COMPUTED_VALUE"""),"GABRIEL DE ALMEIDA MONTEIRO") -> GABRIEL DE ALMEIDA MONTEIRO | C89: =IF(COUNTIF(A:A, H89)>0, "OK", "Incompleto") -> OK | D89: =AN89+BY89 -> 6879.4561 | E89: 45809 | F89: 07.391.921/0001-71 | G89: 273 | H89: KALEB PINHEIRO DA MATA | I89: Inst emendador de redes tele | J89: 44127 | K89: 2900 | L89: Férias | M89: 2610 | O89: 0 | P89: 783 | T89: 0 | Y89: 0 | AD89: 746.46 | AE89: 336.79 | AF89: 270.81 | AM89: 0.3 | AN89: =SUM(M89:AM89) -> 4747.36 | AP89: -5.7 | AQ89: -156.6 | AT89: -1.17 | AV89: -14 | AY89: 0 | BB89: 0 | BC89: -100.08 | BD89: 0 | BF89: 0 | BG89: -517.83 | BH89: -255.98 | BJ89: 0 | BL89: =SUM(AO89:BK89) -> -1051.36 | BM89: =AN89+BL89 -> 3696 | BN89: =K89/12*1 -> 241.66667 | BO89: =K89/12*1 -> 241.66667 | BP89: =BO89/3 -> 80.555556 | BQ89: =CQ89*CR89% -> 497.76722 | BR89: =CT89 -> 379.76 | BS89: =-(-CD89-AP89) -> 564.3 | BT89: =IF(CE89+AQ89<0, 0, CE89+AQ89) -> 12.6 | BU89: =CB89+CC89 -> 100.07 | BV89: =SUMIFS('SEGURO DE VIDA'!E:E, 'SEGURO DE VIDA'!D:D, H89, 'SEGURO DE VIDA'!G:G, E89) -> 13.71 | BW89: =SUMIFS(TREINAMENTOS!E:E, TREINAMENTOS!D:D, H89, TREINAMENTOS!G:G, E89) -> 0 | BX89: =SUMIFS(EXAMES!E:E, EXAMES!D:D, H89, EXAMES!G:G, E89) -> 0 | BY89: =SUM(BN89:BU89)+SUM(BV89:BX89) -> 2132.0961 | CA89: KALEB PINHEIRO DA MAΤΑ | CB89: =IF(SUM(BB89:BD89)+CF89<0, 0, SUM(BB89:BD89)+CF89) -> 100.07 | CC89: =IF(SUM(AV89:AW89)+CG89<0, 0, SUM(AV89:AW89)+CG89) -> 0 | CD89: =SUMIFS(ALIMENTAÇÃO!E:E, ALIMENTAÇÃO!D:D, H89, ALIMENTAÇÃO!G:G, E89) -> 570 | CE89: =SUMIFS(TRANSPORTE!E:E, TRANSPORTE!D:D, H89, TRANSPORTE!G:G, E89) -> 169.2 | CF89: =SUMIFS('PLANO DE SAÚDE'!E:E, 'PLANO DE SAÚDE'!D:D, H89, 'PLANO DE SAÚDE'!G:G, E89) -> 200.15 | CG89: =SUMIFS('PLANO ODONTO'!E:E, 'PLANO ODONTO'!D:D, H89, 'PLANO ODONTO'!G:G, E89) -> 14 | CH89: =BB89+BC89+BD89 -> -100.08 | CI89: =BI89+BJ89 -> 0 | CJ89: =AA89+AB89 -> 0 | CM89: =AV89+AW89 -> -14 | CN89: 4747.36 | CO89: -1051.36 | CP89: 3696 | CQ89: 4747.06 | CR89: 10.4858 | CS89: 4747.06 | CT89: 379.76 | CU89: 4139.86
A90: =IFERROR(__xludf.DUMMYFUNCTION("""COMPUTED_VALUE"""),"GABRIELLA VARELA DE OLIVEIRA") -> GABRIELLA VARELA DE OLIVEIRA | C90: =IF(COUNTIF(A:A, H90)>0, "OK", "Incompleto") -> OK | D90: =AN90+BY90 -> 1975.43 | E90: 45809 | F90: 07.391.921/0001-71 | G90: 3481 | H90: KANANDA SOARES DA CRUZ MORALES | I90: ESTAGIARIO EM TELECOM | J90: 45607 | K90: 720 | M90: 720 | O90: 0 | P90: 0 | Z90: 0 | AD90: 0 | AE90: 0 | AF90: 0 | AM90: 0.07 | AN90: =SUM(M90:AM90) -> 720.07 | AP90: -6.65 | AQ90: 0 | AT90: -0.41 | AV90: 0 | BB90: 0 | BC90: -2.01 | BD90: 0 | BF90: 0 | BG90: 0 | BH90: 0 | BI90: 0 | BL90: =SUM(AO90:BK90) -> -9.07 | BM90: =AN90+BL90 -> 711 | BN90: =K90/12*1 -> 60 | BO90: =K90/12*1 -> 60 | BP90: =BO90/3 -> 20 | BQ90: =CQ90*CR90% -> 0 | BR90: =CT90 -> 0 | BS90: =-(-CD90-AP90) -> 658.35 | BT90: =IF(CE90+AQ90<0, 0, CE90+AQ90) -> 324.9 | BU90: =CB90+CC90 -> 118.4 | BV90: =SUMIFS('SEGURO DE VIDA'!E:E, 'SEGURO DE VIDA'!D:D, H90, 'SEGURO DE VIDA'!G:G, E90) -> 13.71 | BW90: =SUMIFS(TREINAMENTOS!E:E, TREINAMENTOS!D:D, H90, TREINAMENTOS!G:G, E90) -> 0 | BX90: =SUMIFS(EXAMES!E:E, EXAMES!D:D, H90, EXAMES!G:G, E90) -> 0 | BY90: =SUM(BN90:BU90)+SUM(BV90:BX90) -> 1255.36 | CA90: ΚANANDA SOARES DA CRUZ MORAI | CB90: =IF(SUM(BB90:BD90)+CF90<0, 0, SUM(BB90:BD90)+CF90) -> 118.4 | CC90: =IF(SUM(AV90:AW90)+CG90<0, 0, SUM(AV90:AW90)+CG90) -> 0 | CD90: =SUMIFS(ALIMENTAÇÃO!E:E, ALIMENTAÇÃO!D:D, H90, ALIMENTAÇÃO!G:G, E90) -> 665 | CE90: =SUMIFS(TRANSPORTE!E:E, TRANSPORTE!D:D, H90, TRANSPORTE!G:G, E90) -> 324.9 | CF90: =SUMIFS('PLANO DE SAÚDE'!E:E, 'PLANO DE SAÚDE'!D:D, H90, 'PLANO DE SAÚDE'!G:G, E90) -> 120.41 | CG90: =SUMIFS('PLANO ODONTO'!E:E, 'PLANO ODONTO'!D:D, H90, 'PLANO ODONTO'!G:G, E90) -> 0 | CH90: =BB90+BC90+BD90 -> -2.01 | CI90: =BI90+BJ90 -> 0 | CJ90: =AA90+AB90 -> 0 | CM90: =AV90+AW90 -> 0 | CN90: 720.07 | CO90: -9.07 | CP90: 711 | CQ90: 0 | CR90: 0 | CS90: 0 | CT90: 0 | CU90: 112.8
A91: =IFERROR(__xludf.DUMMYFUNCTION("""COMPUTED_VALUE"""),"GABRIEL LIRA AUAD CARRIÓ") -> GABRIEL LIRA AUAD CARRIÓ | C91: =IF(COUNTIF(A:A, H91)>0, "OK", "Incompleto") -> OK | D91: =AN91+BY91 -> 3810.11 | E91: 45809 | F91: 07.391.921/0001-71 | G91: 3508 | H91: LARISSA LIMA DE MOURA | I91: ASSIST PROJETOS PLENO | J91: 45701 | K91: 2277 | M91: 2277 | O91: 0 | P91: 0 | Z91: 0 | AD91: 0 | AE91: 0 | AF91: 0 | AM91: 0.6 | AN91: =SUM(M91:AM91) -> 2277.6 | AP91: -6.65 | AQ91: -136.62 | AT91: -0.17 | AV91: 0 | BB91: 0 | BC91: 0 | BD91: 0 | BF91: 0 | BG91: -182.16 | BH91: 0 | BI91: 0 | BL91: =SUM(AO91:BK91) -> -325.6 | BM91: =AN91+BL91 -> 1952 | BN91: =K91/12*1 -> 189.75 | BO91: =K91/12*1 -> 189.75 | BP91: =BO91/3 -> 63.25 | BQ91: =CQ91*CR91% -> 182.16 | BR91: =CT91 -> 182.16 | BS91: =-(-CD91-AP91) -> 658.35 | BT91: =IF(CE91+AQ91<0, 0, CE91+AQ91) -> 53.38 | BU91: =CB91+CC91 -> 0 | BV91: =SUMIFS('SEGURO DE VIDA'!E:E, 'SEGURO DE VIDA'!D:D, H91, 'SEGURO DE VIDA'!G:G, E91) -> 13.71 | BW91: =SUMIFS(TREINAMENTOS!E:E, TREINAMENTOS!D:D, H91, TREINAMENTOS!G:G, E91) -> 0 | BX91: =SUMIFS(EXAMES!E:E, EXAMES!D:D, H91, EXAMES!G:G, E91) -> 0 | BY91: =SUM(BN91:BU91)+SUM(BV91:BX91) -> 1532.51 | CA91: LARISSA LIMA DE MOURA | CB91: =IF(SUM(BB91:BD91)+CF91<0, 0, SUM(BB91:BD91)+CF91) -> 0 | CC91: =IF(SUM(AV91:AW91)+CG91<0, 0, SUM(AV91:AW91)+CG91) -> 0 | CD91: =SUMIFS(ALIMENTAÇÃO!E:E, ALIMENTAÇÃO!D:D, H91, ALIMENTAÇÃO!G:G, E91) -> 665 | CE91: =SUMIFS(TRANSPORTE!E:E, TRANSPORTE!D:D, H91, TRANSPORTE!G:G, E91) -> 190 | CF91: =SUMIFS('PLANO DE SAÚDE'!E:E, 'PLANO DE SAÚDE'!D:D, H91, 'PLANO DE SAÚDE'!G:G, E91) -> 0 | CG91: =SUMIFS('PLANO ODONTO'!E:E, 'PLANO ODONTO'!D:D, H91, 'PLANO ODONTO'!G:G, E91) -> 0 | CH91: =BB91+BC91+BD91 -> 0 | CI91: =BI91+BJ91 -> 0 | CJ91: =AA91+AB91 -> 0 | CM91: =AV91+AW91 -> 0 | CN91: 2277.6 | CO91: -325.6 | CP91: 1952 | CQ91: 2277 | CR91: 8 | CS91: 2277 | CT91: 182.16 | CU91: 1669.8
A92: =IFERROR(__xludf.DUMMYFUNCTION("""COMPUTED_VALUE"""),"GABRIEL SAMPAIO DE SOUSA") -> GABRIEL SAMPAIO DE SOUSA | C92: =IF(COUNTIF(A:A, H92)>0, "OK", "Incompleto") -> OK | D92: =AN92+BY92 -> 2232.4526 | E92: 45809 | F92: 07.391.921/0001-71 | G92: 353 | H92: LEANDRO RANGEL DE OLIVEIRA | I92: INSTALADOR JUNIOR | J92: 44746 | K92: 1800 | L92: Férias | M92: 600 | O92: 0 | P92: 0 | Z92: 0 | AD92: 0 | AE92: 0 | AF92: 0 | AM92: 0.32 | AN92: =SUM(M92:AM92) -> 600.32 | AP92: -1.75 | AQ92: -36 | AT92: -0.84 | AV92: 0 | BB92: 0 | BC92: 0 | BD92: 0 | BF92: 0 | BG92: -51.73 | BH92: 0 | BI92: 0 | BL92: =SUM(AO92:BK92) -> -90.32 | BM92: =AN92+BL92 -> 510 | BN92: =K92/12*1 -> 150 | BO92: =K92/12*1 -> 150 | BP92: =BO92/3 -> 50 | BQ92: =CQ92*CR92% -> 47.0526 | BR92: =CT92 -> 48 | BS92: =-(-CD92-AP92) -> 173.25 | BT92: =IF(CE92+AQ92<0, 0, CE92+AQ92) -> 288.9 | BU92: =CB92+CC92 -> 0 | BV92: =SUMIFS('SEGURO DE VIDA'!E:E, 'SEGURO DE VIDA'!D:D, H92, 'SEGURO DE VIDA'!G:G, E92) -> 13.71 | BW92: =SUMIFS(TREINAMENTOS!E:E, TREINAMENTOS!D:D, H92, TREINAMENTOS!G:G, E92) -> 0 | BX92: =SUMIFS(EXAMES!E:E, EXAMES!D:D, H92, EXAMES!G:G, E92) -> 711.22 | BY92: =SUM(BN92:BU92)+SUM(BV92:BX92) -> 1632.1326 | CA92: LEANDRO RANGEL DE OLIVEIRA | CB92: =IF(SUM(BB92:BD92)+CF92<0, 0, SUM(BB92:BD92)+CF92) -> 0 | CC92: =IF(SUM(AV92:AW92)+CG92<0, 0, SUM(AV92:AW92)+CG92) -> 0 | CD92: =SUMIFS(ALIMENTAÇÃO!E:E, ALIMENTAÇÃO!D:D, H92, ALIMENTAÇÃO!G:G, E92) -> 175 | CE92: =SUMIFS(TRANSPORTE!E:E, TRANSPORTE!D:D, H92, TRANSPORTE!G:G, E92) -> 324.9 | CF92: =SUMIFS('PLANO DE SAÚDE'!E:E, 'PLANO DE SAÚDE'!D:D, H92, 'PLANO DE SAÚDE'!G:G, E92) -> 0 | CG92: =SUMIFS('PLANO ODONTO'!E:E, 'PLANO ODONTO'!D:D, H92, 'PLANO ODONTO'!G:G, E92) -> 0 | CH92: =BB92+BC92+BD92 -> 0 | CI92: =BI92+BJ92 -> 0 | CJ92: =AA92+AB92 -> 0 | CM92: =AV92+AW92 -> 0 | CN92: 600.32 | CO92: -90.32 | CP92: 510 | CQ92: 600 | CR92: 7.8421 | CS92: 600 | CT92: 48 | CU92: 0
A93: =IFERROR(__xludf.DUMMYFUNCTION("""COMPUTED_VALUE"""),"GEORGIA MARIANA DA SILVA") -> GEORGIA MARIANA DA SILVA | C93: =IF(COUNTIF(A:A, H93)>0, "OK", "Incompleto") -> OK | D93: =AN93+BY93 -> 1958.1678 | E93: 45809 | F93: 07.391.921/0001-71 | G93: 3538 | H93: LEANDRO SOUZA BRAUL | I93: ESTAGIARIO EM ENGENHA | J93: 45800 | K93: 850 | M93: 850 | O93: 0 | P93: 0 | Z93: 0 | AD93: 0 | AE93: 0 | AF93: 0 | AM93: 0.33 | AN93: =SUM(M93:AM93) -> 850.33 | AP93: -6.65 | AQ93: 0 | AT93: -0.68 | AV93: 0 | BB93: 0 | BC93: 0 | BD93: 0 | BF93: 0 | BG93: 0 | BH93: 0 | BI93: 0 | BL93: =SUM(AO93:BK93) -> -7.33 | BM93: =AN93+BL93 -> 843 | BN93: =K93/12*1 -> 70.833333 | BO93: =K93/12*1 -> 70.833333 | BP93: =BO93/3 -> 23.611111 | BQ93: =CQ93*CR93% -> 0 | BR93: =CT93 -> 0 | BS93: =-(-CD93-AP93) -> 658.35 | BT93: =IF(CE93+AQ93<0, 0, CE93+AQ93) -> 256.5 | BU93: =CB93+CC93 -> 14 | BV93: =SUMIFS('SEGURO DE VIDA'!E:E, 'SEGURO DE VIDA'!D:D, H93, 'SEGURO DE VIDA'!G:G, E93) -> 13.71 | BW93: =SUMIFS(TREINAMENTOS!E:E, TREINAMENTOS!D:D, H93, TREINAMENTOS!G:G, E93) -> 0 | BX93: =SUMIFS(EXAMES!E:E, EXAMES!D:D, H93, EXAMES!G:G, E93) -> 0 | BY93: =SUM(BN93:BU93)+SUM(BV93:BX93) -> 1107.8378 | CA93: LEANDRO SOUZA BRAUL | CB93: =IF(SUM(BB93:BD93)+CF93<0, 0, SUM(BB93:BD93)+CF93) -> 0 | CC93: =IF(SUM(AV93:AW93)+CG93<0, 0, SUM(AV93:AW93)+CG93) -> 14 | CD93: =SUMIFS(ALIMENTAÇÃO!E:E, ALIMENTAÇÃO!D:D, H93, ALIMENTAÇÃO!G:G, E93) -> 665 | CE93: =SUMIFS(TRANSPORTE!E:E, TRANSPORTE!D:D, H93, TRANSPORTE!G:G, E93) -> 256.5 | CF93: =SUMIFS('PLANO DE SAÚDE'!E:E, 'PLANO DE SAÚDE'!D:D, H93, 'PLANO DE SAÚDE'!G:G, E93) -> 0 | CG93: =SUMIFS('PLANO ODONTO'!E:E, 'PLANO ODONTO'!D:D, H93, 'PLANO ODONTO'!G:G, E93) -> 14 | CH93: =BB93+BC93+BD93 -> 0 | CI93: =BI93+BJ93 -> 0 | CJ93: =AA93+AB93 -> 0 | CM93: =AV93+AW93 -> 0 | CN93: 850.33 | CO93: -7.33 | CP93: 843 | CQ93: 0 | CR93: 0 | CS93: 0 | CT93: 0 | CU93: 242.8
A94: =IFERROR(__xludf.DUMMYFUNCTION("""COMPUTED_VALUE"""),"GEORGIA MARIANA DA SILVA PEREIRA") -> GEORGIA MARIANA DA SILVA PEREIRA | C94: =IF(COUNTIF(A:A, H94)>0, "OK", "Incompleto") -> OK | D94: =AN94+BY94 -> 5863.7065 | E94: 45809 | F94: 07.391.921/0001-71 | G94: 3419 | H94: LENON MARTINS DOS SANTOS | I94: TECNICO DE TELECOMUNI | J94: 45313 | K94: 2400 | M94: 2400 | O94: 0 | P94: 720 | Z94: 0 | AD94: 187.2 | AE94: 0 | AF94: 46.8 | AM94: 0.7 | AN94: =SUM(M94:AM94) -> 3354.7 | AP94: -6.3 | AQ94: -144 | AT94: -0.28 | AV94: -14 | BB94: 0 | BC94: -2.24 | BD94: 0 | BF94: -546 | BG94: -295.88 | BH94: 0 | BI94: 0 | BL94: =SUM(AO94:BK94) -> -1008.7 | BM94: =AN94+BL94 -> 2346 | BN94: =K94/12*1 -> 200 | BO94: =K94/12*1 -> 200 | BP94: =BO94/3 -> 66.666667 | BQ94: =CQ94*CR94% -> 295.87982 | BR94: =CT94 -> 268.32 | BS94: =-(-CD94-AP94) -> 623.7 | BT94: =IF(CE94+AQ94<0, 0, CE94+AQ94) -> 95.4 | BU94: =CB94+CC94 -> 132.26 | BV94: =SUMIFS('SEGURO DE VIDA'!E:E, 'SEGURO DE VIDA'!D:D, H94, 'SEGURO DE VIDA'!G:G, E94) -> 13.71 | BW94: =SUMIFS(TREINAMENTOS!E:E, TREINAMENTOS!D:D, H94, TREINAMENTOS!G:G, E94) -> 0 | BX94: =SUMIFS(EXAMES!E:E, EXAMES!D:D, H94, EXAMES!G:G, E94) -> 613.07 | BY94: =SUM(BN94:BU94)+SUM(BV94:BX94) -> 2509.0065 | CA94: LENON MARTINS DOS SANTOS | CB94: =IF(SUM(BB94:BD94)+CF94<0, 0, SUM(BB94:BD94)+CF94) -> 132.26 | CC94: =IF(SUM(AV94:AW94)+CG94<0, 0, SUM(AV94:AW94)+CG94) -> 0 | CD94: =SUMIFS(ALIMENTAÇÃO!E:E, ALIMENTAÇÃO!D:D, H94, ALIMENTAÇÃO!G:G, E94) -> 630 | CE94: =SUMIFS(TRANSPORTE!E:E, TRANSPORTE!D:D, H94, TRANSPORTE!G:G, E94) -> 239.4 | CF94: =SUMIFS('PLANO DE SAÚDE'!E:E, 'PLANO DE SAÚDE'!D:D, H94, 'PLANO DE SAÚDE'!G:G, E94) -> 134.5 | CG94: =SUMIFS('PLANO ODONTO'!E:E, 'PLANO ODONTO'!D:D, H94, 'PLANO ODONTO'!G:G, E94) -> 14 | CH94: =BB94+BC94+BD94 -> -2.24 | CI94: =BI94+BJ94 -> 0 | CJ94: =AA94+AB94 -> 0 | CM94: =AV94+AW94 -> -14 | CN94: 3354.7 | CO94: -1008.7 | CP94: 2346 | CQ94: 3354 | CR94: 8.8217 | CS94: 3354 | CT94: 268.32 | CU94: 2489.35
A95: =IFERROR(__xludf.DUMMYFUNCTION("""COMPUTED_VALUE"""),"GIOVANNI MATOS STELAI GIRÃO") -> GIOVANNI MATOS STELAI GIRÃO | C95: =IF(COUNTIF(A:A, H95)>0, "OK", "Incompleto") -> OK | D95: =AN95+BY95 -> 12331.973 | E95: 45809 | F95: 07.391.921/0001-71 | G95: 161 | H95: LEONARDO BEN SENOR CASALES MARQUES RIBAS | I95: COORDENADOR DE SERVI | J95: 42011 | K95: 7718.42 | M95: 7718.42 | O95: 15.31 | P95: 0 | Z95: 0 | AD95: 542.22 | AE95: 0 | AF95: 139.38 | AM95: 0.54 | AN95: =SUM(M95:AM95) -> 8415.87 | AP95: -6.65 | AQ95: 0 | AT95: -0.8 | AV95: 0 | BB95: 0 | BC95: -2.01 | BD95: 0 | BF95: 0 | BG95: -951.62 | BH95: -1143.79 | BI95: 0 | BL95: =SUM(AO95:BK95) -> -2104.87 | BM95: =AN95+BL95 -> 6311 | BN95: =K95/12*1 -> 643.20167 | BO95: =K95/12*1 -> 643.20167 | BP95: =BO95/3 -> 214.40056 | BQ95: =CQ95*CR95% -> 951.61898 | BR95: =CT95 -> 673.22 | BS95: =-(-CD95-AP95) -> 658.35 | BT95: =IF(CE95+AQ95<0, 0, CE95+AQ95) -> 0 | BU95: =CB95+CC95 -> 118.4 | BV95: =SUMIFS('SEGURO DE VIDA'!E:E, 'SEGURO DE VIDA'!D:D, H95, 'SEGURO DE VIDA'!G:G, E95) -> 13.71 | BW95: =SUMIFS(TREINAMENTOS!E:E, TREINAMENTOS!D:D, H95, TREINAMENTOS!G:G, E95) -> 0 | BX95: =SUMIFS(EXAMES!E:E, EXAMES!D:D, H95, EXAMES!G:G, E95) -> 0 | BY95: =SUM(BN95:BU95)+SUM(BV95:BX95) -> 3916.1029 | CA95: LEONARDO BEN SENOR CASALES M | CB95: =IF(SUM(BB95:BD95)+CF95<0, 0, SUM(BB95:BD95)+CF95) -> 118.4 | CC95: =IF(SUM(AV95:AW95)+CG95<0, 0, SUM(AV95:AW95)+CG95) -> 0 | CD95: =SUMIFS(ALIMENTAÇÃO!E:E, ALIMENTAÇÃO!D:D, H95, ALIMENTAÇÃO!G:G, E95) -> 665 | CE95: =SUMIFS(TRANSPORTE!E:E, TRANSPORTE!D:D, H95, TRANSPORTE!G:G, E95) -> 0 | CF95: =SUMIFS('PLANO DE SAÚDE'!E:E, 'PLANO DE SAÚDE'!D:D, H95, 'PLANO DE SAÚDE'!G:G, E95) -> 120.41 | CG95: =SUMIFS('PLANO ODONTO'!E:E, 'PLANO ODONTO'!D:D, H95, 'PLANO ODONTO'!G:G, E95) -> 0 | CH95: =BB95+BC95+BD95 -> -2.01 | CI95: =BI95+BJ95 -> 0 | CJ95: =AA95+AB95 -> 0 | CM95: =AV95+AW95 -> 0 | CN95: 8415.87 | CO95: -2104.87 | CP95: 6311 | CQ95: 8157.41 | CR95: 11.6657 | CS95: 8415.33 | CT95: 673.22 | CU95: 7463.71
A96: =IFERROR(__xludf.DUMMYFUNCTION("""COMPUTED_VALUE"""),"GLAUBER RODRIGUES GOMES") -> GLAUBER RODRIGUES GOMES | C96: =IF(COUNTIF(A:A, H96)>0, "OK", "Incompleto") -> OK | D96: =AN96+BY96 -> 8146.7836 | E96: 45809 | F96: 07.391.921/0001-71 | G96: 263 | H96: LEONARDO DUARTE RANGEL | I96: SUPERVISOR TEC EM TELE | J96: 43697 | K96: 4081.88 | M96: 4081.88 | O96: 0 | P96: 1224.56 | Z96: 0 | AD96: 0 | AE96: 0 | AF96: 0 | AM96: 0.65 | AN96: =SUM(M96:AM96) -> 5307.09 | AP96: -5.7 | AQ96: 0 | AT96: -0.35 | AV96: 0 | BB96: 0 | BC96: 0 | BD96: 0 | BF96: 0 | BG96: -552.48 | BH96: -383.56 | BI96: 0 | BL96: =SUM(AO96:BK96) -> -942.09 | BM96: =AN96+BL96 -> 4365 | BN96: =K96/12*1 -> 340.15667 | BO96: =K96/12*1 -> 340.15667 | BP96: =BO96/3 -> 113.38556 | BQ96: =CQ96*CR96% -> 552.47469 | BR96: =CT96 -> 424.51 | BS96: =-(-CD96-AP96) -> 564.3 | BT96: =IF(CE96+AQ96<0, 0, CE96+AQ96) -> 0 | BU96: =CB96+CC96 -> 0 | BV96: =SUMIFS('SEGURO DE VIDA'!E:E, 'SEGURO DE VIDA'!D:D, H96, 'SEGURO DE VIDA'!G:G, E96) -> 13.71 | BW96: =SUMIFS(TREINAMENTOS!E:E, TREINAMENTOS!D:D, H96, TREINAMENTOS!G:G, E96) -> 0 | BX96: =SUMIFS(EXAMES!E:E, EXAMES!D:D, H96, EXAMES!G:G, E96) -> 491 | BY96: =SUM(BN96:BU96)+SUM(BV96:BX96) -> 2839.6936 | CA96: LEONARDO DUARTE RANGEL | CB96: =IF(SUM(BB96:BD96)+CF96<0, 0, SUM(BB96:BD96)+CF96) -> 0 | CC96: =IF(SUM(AV96:AW96)+CG96<0, 0, SUM(AV96:AW96)+CG96) -> 0 | CD96: =SUMIFS(ALIMENTAÇÃO!E:E, ALIMENTAÇÃO!D:D, H96, ALIMENTAÇÃO!G:G, E96) -> 570 | CE96: =SUMIFS(TRANSPORTE!E:E, TRANSPORTE!D:D, H96, TRANSPORTE!G:G, E96) -> 0 | CF96: =SUMIFS('PLANO DE SAÚDE'!E:E, 'PLANO DE SAÚDE'!D:D, H96, 'PLANO DE SAÚDE'!G:G, E96) -> 0 | CG96: =SUMIFS('PLANO ODONTO'!E:E, 'PLANO ODONTO'!D:D, H96, 'PLANO ODONTO'!G:G, E96) -> 0 | CH96: =BB96+BC96+BD96 -> 0 | CI96: =BI96+BJ96 -> 0 | CJ96: =AA96+AB96 -> 0 | CM96: =AV96+AW96 -> 0 | CN96: 5307.09 | CO96: -942.09 | CP96: 4365 | CQ96: 5306.44 | CR96: 10.4114 | CS96: 5306.44 | CT96: 424.51 | CU96: 4699.24
A97: =IFERROR(__xludf.DUMMYFUNCTION("""COMPUTED_VALUE"""),"GLAUBERT RODRIGUES DE JESUS") -> GLAUBERT RODRIGUES DE JESUS | C97: =IF(COUNTIF(A:A, H97)>0, "OK", "Incompleto") -> OK | D97: =AN97+BY97 -> 5479.7323 | E97: 45809 | F97: 07.391.921/0001-71 | G97: 226 | H97: LEONARDO NERI DE MELLO | I97: ANALISTA DE MANUTENÇÃ | J97: 43122 | K97: 3275.97 | M97: 3275.97 | O97: 0 | P97: 0 | Z97: 0 | AD97: 31.12 | AE97: 0 | AF97: 7.78 | AM97: 0.95 | AN97: =SUM(M97:AM97) -> 3315.82 | AP97: -6.65 | AQ97: -196.56 | AT97: -0.61 | AV97: 0 | BB97: 0 | BC97: -2.01 | BD97: -125.89 | BF97: 0 | BG97: -291.18 | BH97: -20.92 | BI97: 0 | BL97: =SUM(AO97:BK97) -> -643.82 | BM97: =AN97+BL97 -> 2672 | BN97: =K97/12*1 -> 272.9975 | BO97: =K97/12*1 -> 272.9975 | BP97: =BO97/3 -> 90.999167 | BQ97: =CQ97*CR97% -> 291.17818 | BR97: =CT97 -> 265.18 | BS97: =-(-CD97-AP97) -> 658.35 | BT97: =IF(CE97+AQ97<0, 0, CE97+AQ97) -> 128.34 | BU97: =CB97+CC97 -> 68.04 | BV97: =SUMIFS('SEGURO DE VIDA'!E:E, 'SEGURO DE VIDA'!D:D, H97, 'SEGURO DE VIDA'!G:G, E97) -> 13.71 | BW97: =SUMIFS(TREINAMENTOS!E:E, TREINAMENTOS!D:D, H97, TREINAMENTOS!G:G, E97) -> 0 | BX97: =SUMIFS(EXAMES!E:E, EXAMES!D:D, H97, EXAMES!G:G, E97) -> 102.12 | BY97: =SUM(BN97:BU97)+SUM(BV97:BX97) -> 2163.9123 | CA97: LEONARDO NERI DE MELLO | CB97: =IF(SUM(BB97:BD97)+CF97<0, 0, SUM(BB97:BD97)+CF97) -> 68.04 | CC97: =IF(SUM(AV97:AW97)+CG97<0, 0, SUM(AV97:AW97)+CG97) -> 0 | CD97: =SUMIFS(ALIMENTAÇÃO!E:E, ALIMENTAÇÃO!D:D, H97, ALIMENTAÇÃO!G:G, E97) -> 665 | CE97: =SUMIFS(TRANSPORTE!E:E, TRANSPORTE!D:D, H97, TRANSPORTE!G:G, E97) -> 324.9 | CF97: =SUMIFS('PLANO DE SAÚDE'!E:E, 'PLANO DE SAÚDE'!D:D, H97, 'PLANO DE SAÚDE'!G:G, E97) -> 195.94 | CG97: =SUMIFS('PLANO ODONTO'!E:E, 'PLANO ODONTO'!D:D, H97, 'PLANO ODONTO'!G:G, E97) -> 0 | CH97: =BB97+BC97+BD97 -> -127.9 | CI97: =BI97+BJ97 -> 0 | CJ97: =AA97+AB97 -> 0 | CM97: =AV97+AW97 -> 0 | CN97: 3315.82 | CO97: -643.82 | CP97: 2672 | CQ97: 3314.87 | CR97: 8.784 | CS97: 3314.87 | CT97: 265.18 | CU97: 2707.67
A98: =IFERROR(__xludf.DUMMYFUNCTION("""COMPUTED_VALUE"""),"GRAZIELLE VITORIA NEVES GOMES") -> GRAZIELLE VITORIA NEVES GOMES | C98: =IF(COUNTIF(A:A, H98)>0, "OK", "Incompleto") -> OK | D98: =AN98+BY98 -> 4040.5308 | E98: 45809 | F98: 07.391.921/0001-71 | G98: 3501 | H98: LINCON LIMA MATIAS | I98: Operador de Audio e Video | J98: 45670 | K98: 2239.36 | M98: 2239.36 | O98: 0 | P98: 0 | Z98: 0 | AD98: 19.31 | AE98: 0 | AF98: 4.83 | AM98: 0.44 | AN98: =SUM(M98:AM98) -> 2263.94 | AP98: -6.3 | AQ98: -134.36 | AT98: -0.79 | AV98: 0 | BB98: 0 | BC98: -34.55 | BD98: 0 | BF98: 0 | BG98: -180.94 | BH98: 0 | BI98: 0 | BL98: =SUM(AO98:BK98) -> -356.94 | BM98: =AN98+BL98 -> 1907 | BN98: =K98/12*1 -> 186.61333 | BO98: =K98/12*1 -> 186.61333 | BP98: =BO98/3 -> 62.204444 | BQ98: =CQ98*CR98% -> 180.93966 | BR98: =CT98 -> 181.08 | BS98: =-(-CD98-AP98) -> 623.7 | BT98: =IF(CE98+AQ98<0, 0, CE98+AQ98) -> 190.54 | BU98: =CB98+CC98 -> 151.19 | BV98: =SUMIFS('SEGURO DE VIDA'!E:E, 'SEGURO DE VIDA'!D:D, H98, 'SEGURO DE VIDA'!G:G, E98) -> 13.71 | BW98: =SUMIFS(TREINAMENTOS!E:E, TREINAMENTOS!D:D, H98, TREINAMENTOS!G:G, E98) -> 0 | BX98: =SUMIFS(EXAMES!E:E, EXAMES!D:D, H98, EXAMES!G:G, E98) -> 0 | BY98: =SUM(BN98:BU98)+SUM(BV98:BX98) -> 1776.5908 | CA98: LINCON LIMA MATIAS | CB98: =IF(SUM(BB98:BD98)+CF98<0, 0, SUM(BB98:BD98)+CF98) -> 151.19 | CC98: =IF(SUM(AV98:AW98)+CG98<0, 0, SUM(AV98:AW98)+CG98) -> 0 | CD98: =SUMIFS(ALIMENTAÇÃO!E:E, ALIMENTAÇÃO!D:D, H98, ALIMENTAÇÃO!G:G, E98) -> 630 | CE98: =SUMIFS(TRANSPORTE!E:E, TRANSPORTE!D:D, H98, TRANSPORTE!G:G, E98) -> 324.9 | CF98: =SUMIFS('PLANO DE SAÚDE'!E:E, 'PLANO DE SAÚDE'!D:D, H98, 'PLANO DE SAÚDE'!G:G, E98) -> 185.74 | CG98: =SUMIFS('PLANO ODONTO'!E:E, 'PLANO ODONTO'!D:D, H98, 'PLANO ODONTO'!G:G, E98) -> 0 | CH98: =BB98+BC98+BD98 -> -34.55 | CI98: =BI98+BJ98 -> 0 | CJ98: =AA98+AB98 -> 0 | CM98: =AV98+AW98 -> 0 | CN98: 2263.94 | CO98: -356.94 | CP98: 1907 | CQ98: 2263.5 | CR98: 7.9938 | CS98: 2263.5 | CT98: 181.08 | CU98: 1656.3
A99: =IFERROR(__xludf.DUMMYFUNCTION("""COMPUTED_VALUE"""),"GUILHERME SIMOES DE CARVALHO") -> GUILHERME SIMOES DE CARVALHO | C99: =IF(COUNTIF(A:A, H99)>0, "OK", "Incompleto") -> OK | D99: =AN99+BY99 -> 2427.7878 | E99: 45809 | F99: 07.391.921/0001-71 | G99: 3533 | H99: LORRAINE SANTOS DA SILVA | I99: ESTAGIÁRIO (A) TEC SEG T | J99: 45782 | K99: 850 | M99: 850 | O99: 0 | P99: 0 | Z99: 0 | AD99: 0 | AE99: 0 | AF99: 0 | AM99: 0.24 | AN99: =SUM(M99:AM99) -> 850.24 | AP99: -6.65 | AQ99: 0 | AT99: -0.58 | AV99: -14 | BB99: 0 | BC99: -2.01 | BD99: 0 | BF99: 0 | BG99: 0 | BH99: 0 | BI99: 0 | BL99: =SUM(AO99:BK99) -> -23.24 | BM99: =AN99+BL99 -> 827 | BN99: =K99/12*1 -> 70.833333 | BO99: =K99/12*1 -> 70.833333 | BP99: =BO99/3 -> 23.611111 | BQ99: =CQ99*CR99% -> 0 | BR99: =CT99 -> 0 | BS99: =-(-CD99-AP99) -> 658.35 | BT99: =IF(CE99+AQ99<0, 0, CE99+AQ99) -> 324.9 | BU99: =CB99+CC99 -> 415.31 | BV99: =SUMIFS('SEGURO DE VIDA'!E:E, 'SEGURO DE VIDA'!D:D, H99, 'SEGURO DE VIDA'!G:G, E99) -> 13.71 | BW99: =SUMIFS(TREINAMENTOS!E:E, TREINAMENTOS!D:D, H99, TREINAMENTOS!G:G, E99) -> 0 | BX99: =SUMIFS(EXAMES!E:E, EXAMES!D:D, H99, EXAMES!G:G, E99) -> 0 | BY99: =SUM(BN99:BU99)+SUM(BV99:BX99) -> 1577.5478 | CA99: LORRAINE SANTOS DA SILVA | CB99: =IF(SUM(BB99:BD99)+CF99<0, 0, SUM(BB99:BD99)+CF99) -> 402.72 | CC99: =IF(SUM(AV99:AW99)+CG99<0, 0, SUM(AV99:AW99)+CG99) -> 12.59 | CD99: =SUMIFS(ALIMENTAÇÃO!E:E, ALIMENTAÇÃO!D:D, H99, ALIMENTAÇÃO!G:G, E99) -> 665 | CE99: =SUMIFS(TRANSPORTE!E:E, TRANSPORTE!D:D, H99, TRANSPORTE!G:G, E99) -> 324.9 | CF99: =SUMIFS('PLANO DE SAÚDE'!E:E, 'PLANO DE SAÚDE'!D:D, H99, 'PLANO DE SAÚDE'!G:G, E99) -> 404.73 | CG99: =SUMIFS('PLANO ODONTO'!E:E, 'PLANO ODONTO'!D:D, H99, 'PLANO ODONTO'!G:G, E99) -> 26.59 | CH99: =BB99+BC99+BD99 -> -2.01 | CI99: =BI99+BJ99 -> 0 | CJ99: =AA99+AB99 -> 0 | CM99: =AV99+AW99 -> -14 | CN99: 850.24 | CO99: -23.24 | CP99: 827 | CQ99: 0 | CR99: 0 | CS99: 0 | CT99: 0 | CU99: 242.8
A100: =IFERROR(__xludf.DUMMYFUNCTION("""COMPUTED_VALUE"""),"GUSTAVO MACHADO SOEIRO") -> GUSTAVO MACHADO SOEIRO | C100: =IF(COUNTIF(A:A, H100)>0, "OK", "Incompleto") -> OK | D100: =AN100+BY100 -> 3571.8357 | E100: 45809 | F100: 07.391.921/0001-71 | G100: 3446 | H100: LUAN MODESTO PINTO | I100: AUX. DE INSTALACAO DE R | J100: 45481 | K100: 1518 | M100: 1518 | O100: 0 | P100: 455.4 | Z100: 0 | AD100: 0 | AE100: 0 | AF100: 0 | AM100: 0.94 | AN100: =SUM(M100:AM100) -> 1974.34 | AP100: -6.3 | AQ100: -91.08 | AT100: -0.53 | AV100: 0 | BB100: 0 | BC100: -2.01 | BD100: 0 | BF100: -486.88 | BG100: -154.83 | BH100: 0 | BI100: -363.71 | BL100: =SUM(AO100:BK100) -> -1105.34 | BM100: =AN100+BL100 -> 869 | BN100: =K100/12*1 -> 126.5 | BO100: =K100/12*1 -> 126.5 | BP100: =BO100/3 -> 42.166667 | BQ100: =CQ100*CR100% -> 154.82902 | BR100: =CT100 -> 157.87 | BS100: =-(-CD100-AP100) -> 623.7 | BT100: =IF(CE100+AQ100<0, 0, CE100+AQ100) -> 233.82 | BU100: =CB100+CC100 -> 118.4 | BV100: =SUMIFS('SEGURO DE VIDA'!E:E, 'SEGURO DE VIDA'!D:D, H100, 'SEGURO DE VIDA'!G:G, E100) -> 13.71 | BW100: =SUMIFS(TREINAMENTOS!E:E, TREINAMENTOS!D:D, H100, TREINAMENTOS!G:G, E100) -> 0 | BX100: =SUMIFS(EXAMES!E:E, EXAMES!D:D, H100, EXAMES!G:G, E100) -> 0 | BY100: =SUM(BN100:BU100)+SUM(BV100:BX100) -> 1597.4957 | CA100: LUAN MODESTO PINTO | CB100: =IF(SUM(BB100:BD100)+CF100<0, 0, SUM(BB100:BD100)+CF100) -> 118.4 | CC100: =IF(SUM(AV100:AW100)+CG100<0, 0, SUM(AV100:AW100)+CG100) -> 0 | CD100: =SUMIFS(ALIMENTAÇÃO!E:E, ALIMENTAÇÃO!D:D, H100, ALIMENTAÇÃO!G:G, E100) -> 630 | CE100: =SUMIFS(TRANSPORTE!E:E, TRANSPORTE!D:D, H100, TRANSPORTE!G:G, E100) -> 324.9 | CF100: =SUMIFS('PLANO DE SAÚDE'!E:E, 'PLANO DE SAÚDE'!D:D, H100, 'PLANO DE SAÚDE'!G:G, E100) -> 120.41 | CG100: =SUMIFS('PLANO ODONTO'!E:E, 'PLANO ODONTO'!D:D, H100, 'PLANO ODONTO'!G:G, E100) -> 0 | CH100: =BB100+BC100+BD100 -> -2.01 | CI100: =BI100+BJ100 -> -363.71 | CJ100: =AA100+AB100 -> 0 | CM100: =AV100+AW100 -> 0 | CN100: 1974.34 | CO100: -1105.34 | CP100: 869 | CQ100: 1973.4 | CR100: 7.8458 | CS100: 1973.4 | CT100: 157.87 | CU100: 1366.2
...

Sheet rascunho
A1: EMPREGADO | B1: HORAS REFERÊNCIA | C1: H. NORMAIS/REFERÊNCIA | D1: H.PERIC./REFERÊNCIA | E1: R$ H.TOTAL PROJETO | F1: R$ HORAS NORMAIS | G1: R$ TOTAL HORAS NORMAIS | H1: R$ HORAS C/ PER. | I1: R$ TOTAL HORAS PERICULOSIDADE | J1: H/N PROJETO | K1: H/P PROJETO | L1: =E1 -> R$ H.TOTAL PROJETO | M1: Referência | N1: Vencimento | O1: Funcionário | P1: Função | Q1: Locação/Sal. Contratual | R1: PROV.: 001 - Salário Base | S1: Sobre Aviso | T1: Adicional de transferência | U1: Acumulo de função | V1: HE 50% | W1: HE 100% | X1: PROV.: 017 - Noturno 20% | Y1: Reflexo DSR HE | Z1: Insuficiencia de saldo | AA1: PROV.: 020 - Periculosidade 30% | AB1: Salário Familia | AC1: Gratificação | AD1: Reembolso Desc. Indev. | AE1: Aux. Educação | AF1: Arredondamento | AG1: Comissão | AI1: Soma Proventos | AJ1: Plano de Saúde descontado na folha | AK1: Plano Odontologico | AL1: Falta + DSR | AM1: Adiantamento | AN1: Multa de Transito | AO1: Pensão Alimenticia | AP1: Insuficiencia de Saldo | AQ1: INSS | AR1: IRRF | AS1: VA | AT1: VT | AU1: Emprestimo (cred trab) | AV1: EXTRAS | AW1: EXTRAS | AX1: Arredondamento | AY1: 2 via de VT | AZ1: Contribuição sindical | BA1: Soma Descontos | BB1: Total Folha | BC1: Rest. VA | BD1: Rest. VT | BE1: Rest. Plano | BF1: EXTRAS | BG1: EXTRAS | BH1: EXTRAS | BI1: Seguro de Vida | BJ1: Parcela 13 sálario | BK1: Parcela de Férias | BL1: 1/3 de férias | BM1: INSS Empresa | BN1: FGTS | BO1: Valor Empresa | BP1: Total dos gastos | BS1: VA Depositado | BT1: VT depositado | BU1: Valor Plano de Saúde total | BV1: EXTRAS | BW1: EXTRAS | BX1: EXTRAS | BY1: colaboradores | BZ1: Encontra esse nome na sólides? | CA1: Total horas úteis/referência | CB1: Total horas normais/referência | CC1: Total horas periculosidade/referência | CE1: LISTA SÓLIDES
A9: =IFERROR(__xludf.DUMMYFUNCTION("unique(flatten(1:1))"),"EMPREGADO") -> EMPREGADO
A10: =IFERROR(__xludf.DUMMYFUNCTION("""COMPUTED_VALUE"""),"HORAS REFERÊNCIA") -> HORAS REFERÊNCIA
A11: =IFERROR(__xludf.DUMMYFUNCTION("""COMPUTED_VALUE"""),"H. NORMAIS/REFERÊNCIA") -> H. NORMAIS/REFERÊNCIA
A12: =IFERROR(__xludf.DUMMYFUNCTION("""COMPUTED_VALUE"""),"H.PERIC./REFERÊNCIA") -> H.PERIC./REFERÊNCIA
A13: =IFERROR(__xludf.DUMMYFUNCTION("""COMPUTED_VALUE"""),"R$ H.TOTAL PROJETO") -> R$ H.TOTAL PROJETO
A14: =IFERROR(__xludf.DUMMYFUNCTION("""COMPUTED_VALUE"""),"R$ HORAS NORMAIS") -> R$ HORAS NORMAIS
A15: =IFERROR(__xludf.DUMMYFUNCTION("""COMPUTED_VALUE"""),"R$ TOTAL HORAS NORMAIS") -> R$ TOTAL HORAS NORMAIS
A16: =IFERROR(__xludf.DUMMYFUNCTION("""COMPUTED_VALUE"""),"R$ HORAS C/ PER.") -> R$ HORAS C/ PER.
A17: =IFERROR(__xludf.DUMMYFUNCTION("""COMPUTED_VALUE"""),"R$ TOTAL HORAS PERICULOSIDADE") -> R$ TOTAL HORAS PERICULOSIDADE
A18: =IFERROR(__xludf.DUMMYFUNCTION("""COMPUTED_VALUE"""),"H/N PROJETO") -> H/N PROJETO
A19: =IFERROR(__xludf.DUMMYFUNCTION("""COMPUTED_VALUE"""),"H/P PROJETO") -> H/P PROJETO
A20: =IFERROR(__xludf.DUMMYFUNCTION("""COMPUTED_VALUE"""),"Referência") -> Referência
A21: =IFERROR(__xludf.DUMMYFUNCTION("""COMPUTED_VALUE"""),"Vencimento") -> Vencimento
A22: =IFERROR(__xludf.DUMMYFUNCTION("""COMPUTED_VALUE"""),"Funcionário") -> Funcionário
A23: =IFERROR(__xludf.DUMMYFUNCTION("""COMPUTED_VALUE"""),"Função") -> Função
A24: =IFERROR(__xludf.DUMMYFUNCTION("""COMPUTED_VALUE"""),"Locação/Sal. Contratual") -> Locação/Sal. Contratual
A25: =IFERROR(__xludf.DUMMYFUNCTION("""COMPUTED_VALUE"""),"PROV.: 001 - Salário Base") -> PROV.: 001 - Salário Base
A26: =IFERROR(__xludf.DUMMYFUNCTION("""COMPUTED_VALUE"""),"Sobre Aviso") -> Sobre Aviso
A27: =IFERROR(__xludf.DUMMYFUNCTION("""COMPUTED_VALUE"""),"Adicional de transferência") -> Adicional de transferência
A28: =IFERROR(__xludf.DUMMYFUNCTION("""COMPUTED_VALUE"""),"Acumulo de função") -> Acumulo de função
A29: =IFERROR(__xludf.DUMMYFUNCTION("""COMPUTED_VALUE"""),"HE 50%") -> HE 50%
A30: =IFERROR(__xludf.DUMMYFUNCTION("""COMPUTED_VALUE"""),"HE 100%") -> HE 100%
A31: =IFERROR(__xludf.DUMMYFUNCTION("""COMPUTED_VALUE"""),"PROV.: 017 - Noturno 20%") -> PROV.: 017 - Noturno 20%
A32: =IFERROR(__xludf.DUMMYFUNCTION("""COMPUTED_VALUE"""),"Reflexo DSR HE") -> Reflexo DSR HE
A33: =IFERROR(__xludf.DUMMYFUNCTION("""COMPUTED_VALUE"""),"Insuficiencia de saldo") -> Insuficiencia de saldo
A34: =IFERROR(__xludf.DUMMYFUNCTION("""COMPUTED_VALUE"""),"PROV.: 020 - Periculosidade 30%") -> PROV.: 020 - Periculosidade 30%
A35: =IFERROR(__xludf.DUMMYFUNCTION("""COMPUTED_VALUE"""),"Salário Familia") -> Salário Familia
A36: =IFERROR(__xludf.DUMMYFUNCTION("""COMPUTED_VALUE"""),"Gratificação") -> Gratificação
A37: =IFERROR(__xludf.DUMMYFUNCTION("""COMPUTED_VALUE"""),"Reembolso Desc. Indev.") -> Reembolso Desc. Indev.
A38: =IFERROR(__xludf.DUMMYFUNCTION("""COMPUTED_VALUE"""),"Aux. Educação") -> Aux. Educação
